Workbook

Sheet Roadmap
A1: SponsorX — Full Programme Roadmap
A2: Six phases (the blueprint's four; the INFINEX game split out on 2026-10-16 and became Phase 6 on 2026-10-27, when the Certified Recruiting partnership took Phase 5), 356 tasks. Each phase has its own sheet. Every task says where the work physically happens.
A4: Phase | B4: Outcome | C4: Tasks | D4: Person-days | E4: Blueprint timeline | F4: Balanced budget | G4: Depends on
A5: Phase 1 | B5: Managed micro-NIL marketplace — the §39 loop working for 25 athletes and 10 businesses | C5: 249 | D5: 601 | E5: 14–18 weeks | F5: $75K–$105K | G5: Nothing — this is the start
A6: Phase 2 | B6: Transactional marketplace: external properties, payments, commission ledger, payouts, wallet rewards | C6: 64 | D6: 260 | E6: 16–20 weeks | F6: $80K–$120K | G6: Phase 1 auth/RBAC, sponsor/property/inventory/campaign/reward models, Zoho integration, core analytics
A7: Phase 3 | B7: Dynamic pricing, sponsor matching, forecasting, attribution and the data platform | C7: 44 | D7: 184 | E7: 18–22 weeks | F7: $105K–$160K | G7: Phase 2 transaction history, campaign performance data, marketplace activity, reliable event ingestion
A8: Phase 4 | B8: INFINEX virtual sponsorship, SponsorX's side as built (all Done). Every open task moved on 2026-10-20 to the game phase (Phase 6 since 2026-10-27): the game is parked | C8: 19 | D8: 62 | E8: 18–22 weeks | F8: $90K–$150K | G8: Stable SponsorX APIs, campaign/reward engine, identity/session model, metrics pipeline
A9: Phase 5 | B9: Certified Recruiting partnership: SponsorX and certified-recruiting.com link to each other (the site is already built on GoDaddy; BTG already links to it) | C9: 2 | D9: 2 | E9: — | F9: — | G9: certified-recruiting.com, live
A10: Phase 6 | B10: INFINEX game integration: the in-game connector, the staging world test, the pilot world, calibrated virtual pricing, and player accounts (email, Google, Apple, authenticator) with a live connection | C10: 50 | D10: 198 | E10: after the game's staging world exists | F10: — | G10: The INFINEX game (not started 2026-10-16), Phase 4's endpoints
A11: TOTAL | B11: Full SponsorX platform | C11: =SUM(C5:C10) | D11: =SUM(D5:D10) | E11: 66–82 weeks | F11: $350K–$535K
A13: WHERE THE WORK HAPPENS
A14: Why this column exists | B14: A task that says 'create the Zoho module' and a task that says 'author the Zoho mapping document' look identical in a list — but one is click-work in an admin UI and the other is a written spec. Every task now states which.
A15: Document | B15: A written decision or specification. No system is touched — the output is a document people agree on.
A16: Zoho dashboard | B16: Configuration clicked through the Zoho CRM admin UI (Setup → Modules and Fields, API credentials, users).
A17: Vendor console | B17: Configuration in a vendor's own UI — Railway, Cloudflare, Clerk, the payment or email provider.
A18: Code | B18: Work in the repository: schema, domain logic, routes, worker jobs, UI, tests, CI.
A19: Code + console | B19: Both: something configured at the vendor AND wired in the codebase.
A20: Design tool | B20: Visual design work producing artwork, diagrams or screen designs.
A21: Document + code | B21: A written policy that must then be enforced in the codebase.
A22: External · counsel | B22: Performed by a lawyer, not the team. Longest lead times in the programme — start these early.
A24: HOW TO READ THIS WORKBOOK
A25: One sheet per phase | B25: Phase 1–5, identical 18 columns, so they behave the same way.
A26: Task IDs | B26: Phase 1: P{stage}-{CAT}-{nn}, e.g. P4-BE-03. Phases 2–6: {phase}S{sprint}-{CAT}-{nn}, e.g. 2S5-BE-04 = Phase 2, Sprint 5, Backend, task 04. IDs never change — cite them in branches and commits.
A27: Order | B27: A dependency-respecting sort key, recomputed whenever tasks are added. It can shift; the ID cannot.
A28: Status | B28: Phase 1 is live. Every Phase 2–4 task starts Blocked because Phase 1 must finish first. Phase 5 (Certified Recruiting) is live. Phase 6 waits for the INFINEX game.
A29: Weight | B29: S=1 · M=3 · L=5 person-days. Estimates for one person, not calendar commitments.
A31: PHASE OVERLAP
A32: Permitted | B32: Begin Phase 3 warehouse and event modelling during the final 4–6 weeks of Phase 2. Begin the Phase 4 API contract and placement taxonomy during the final 4 weeks of Phase 3.
A33: Forbidden | B33: No ML pricing before clean history exists — launch Phase 3 on rules. No marketplace payouts before commission snapshots, reconciliation, refunds/disputes and audit logs are tested. No virtual impressions reported to sponsors before viewability and de-duplication are validated against pilot telemetry (Phase 6, 6S2-QA-01).
A35: SCOPE REALITY
A36: Team size | B36: The blueprint staffs Phase 1 at 4.5–7.5 FTE and Phases 2–4 higher. The team is two people. Phase 1 alone is ~44 weeks at that size. Scope, not stack, is the binding constraint.

Sheet Dashboard
A1: Dashboard
A2: Live formulas across all six phase sheets. Update Status on a phase sheet and this follows. Counts cover the 556 delivery tasks only — the 9 legal/counsel tasks moved to the Legal sheet on 2026-09-15 and are tracked there (565 total). 'External · counsel' therefore reads 0 here.
B4: Ready | C4: In progress | D4: Code review | E4: Blocked | F4: Done | G4: Total | H4: Days left
A5: Phase 1 | B5: =COUNTIF('Phase 1'!$I$5:$I$400,"Ready") | C5: =COUNTIF('Phase 1'!$I$5:$I$400,"In progress") | D5: =COUNTIF('Phase 1'!$I$5:$I$400,"Code review") | E5: =COUNTIF('Phase 1'!$I$5:$I$400,"Blocked") | F5: =COUNTIF('Phase 1'!$I$5:$I$400,"Done") | G5: =COUNTA('Phase 1'!$B$5:$B$400) | H5: =SUMIF('Phase 1'!$I$5:$I$400,"<>Done",'Phase 1'!$J$5:$J$400)
A6: Phase 2 | B6: =COUNTIF('Phase 2'!$I$5:$I$144,"Ready") | C6: =COUNTIF('Phase 2'!$I$5:$I$144,"In progress") | D6: =COUNTIF('Phase 2'!$I$5:$I$144,"Code review") | E6: =COUNTIF('Phase 2'!$I$5:$I$144,"Blocked") | F6: =COUNTIF('Phase 2'!$I$5:$I$144,"Done") | G6: =COUNTA('Phase 2'!$B$5:$B$144) | H6: =SUMIF('Phase 2'!$I$5:$I$144,"<>Done",'Phase 2'!$J$5:$J$144)
A7: Phase 3 | B7: =COUNTIF('Phase 3'!$I$5:$I$66,"Ready") | C7: =COUNTIF('Phase 3'!$I$5:$I$66,"In progress") | D7: =COUNTIF('Phase 3'!$I$5:$I$66,"Code review") | E7: =COUNTIF('Phase 3'!$I$5:$I$66,"Blocked") | F7: =COUNTIF('Phase 3'!$I$5:$I$66,"Done") | G7: =COUNTA('Phase 3'!$B$5:$B$66) | H7: =SUMIF('Phase 3'!$I$5:$I$66,"<>Done",'Phase 3'!$J$5:$J$66)
A8: Phase 4 | B8: =COUNTIF('Phase 4'!$I$5:$I$51,"Ready") | C8: =COUNTIF('Phase 4'!$I$5:$I$51,"In progress") | D8: =COUNTIF('Phase 4'!$I$5:$I$51,"Code review") | E8: =COUNTIF('Phase 4'!$I$5:$I$51,"Blocked") | F8: =COUNTIF('Phase 4'!$I$5:$I$51,"Done") | G8: =COUNTA('Phase 4'!$B$5:$B$51) | H8: =SUMIF('Phase 4'!$I$5:$I$51,"<>Done",'Phase 4'!$J$5:$J$51)
A9: Phase 5 | B9: =COUNTIF('Phase 5'!$I$5:$I$100,"Ready") | C9: =COUNTIF('Phase 5'!$I$5:$I$100,"In progress") | D9: =COUNTIF('Phase 5'!$I$5:$I$100,"Code review") | E9: =COUNTIF('Phase 5'!$I$5:$I$100,"Blocked") | F9: =COUNTIF('Phase 5'!$I$5:$I$100,"Done") | G9: =COUNTA('Phase 5'!$B$5:$B$100) | H9: =SUMIF('Phase 5'!$I$5:$I$100,"<>Done",'Phase 5'!$J$5:$J$100)
A10: Phase 6 | B10: =COUNTIF('Phase 6'!$I$5:$I$100,"Ready") | C10: =COUNTIF('Phase 6'!$I$5:$I$100,"In progress") | D10: =COUNTIF('Phase 6'!$I$5:$I$100,"Code review") | E10: =COUNTIF('Phase 6'!$I$5:$I$100,"Blocked") | F10: =COUNTIF('Phase 6'!$I$5:$I$100,"Done") | G10: =COUNTA('Phase 6'!$B$5:$B$100) | H10: =SUMIF('Phase 6'!$I$5:$I$100,"<>Done",'Phase 6'!$J$5:$J$100)
A11: TOTAL | B11: =SUM(B5:B10) | C11: =SUM(C5:C10) | D11: =SUM(D5:D10) | E11: =SUM(E5:E10) | F11: =SUM(F5:F10) | G11: =SUM(G5:G10) | H11: =SUM(H5:H10)
A12: BY WHERE THE WORK HAPPENS
B13: Phase 1 | C13: Phase 2 | D13: Phase 3 | E13: Phase 4 | F13: Phase 5 | G13: Phase 6 | H13: Total
A14: Document | B14: =COUNTIF('Phase 1'!$F$5:$F$400,"Document") | C14: =COUNTIF('Phase 2'!$F$5:$F$144,"Document") | D14: =COUNTIF('Phase 3'!$F$5:$F$66,"Document") | E14: =COUNTIF('Phase 4'!$F$5:$F$51,"Document") | F14: =COUNTIF('Phase 5'!$F$5:$F$100,"Document") | G14: =COUNTIF('Phase 6'!$F$5:$F$100,"Document") | H14: =SUM(B14:G14)
A15: Zoho dashboard | B15: =COUNTIF('Phase 1'!$F$5:$F$400,"Zoho dashboard") | C15: =COUNTIF('Phase 2'!$F$5:$F$144,"Zoho dashboard") | D15: =COUNTIF('Phase 3'!$F$5:$F$66,"Zoho dashboard") | E15: =COUNTIF('Phase 4'!$F$5:$F$51,"Zoho dashboard") | F15: =COUNTIF('Phase 5'!$F$5:$F$100,"Zoho dashboard") | G15: =COUNTIF('Phase 6'!$F$5:$F$100,"Zoho dashboard") | H15: =SUM(B15:G15)
A16: Vendor console | B16: =COUNTIF('Phase 1'!$F$5:$F$400,"Vendor console") | C16: =COUNTIF('Phase 2'!$F$5:$F$144,"Vendor console") | D16: =COUNTIF('Phase 3'!$F$5:$F$66,"Vendor console") | E16: =COUNTIF('Phase 4'!$F$5:$F$51,"Vendor console") | F16: =COUNTIF('Phase 5'!$F$5:$F$100,"Vendor console") | G16: =COUNTIF('Phase 6'!$F$5:$F$100,"Vendor console") | H16: =SUM(B16:G16)
A17: Code | B17: =COUNTIF('Phase 1'!$F$5:$F$400,"Code") | C17: =COUNTIF('Phase 2'!$F$5:$F$144,"Code") | D17: =COUNTIF('Phase 3'!$F$5:$F$66,"Code") | E17: =COUNTIF('Phase 4'!$F$5:$F$51,"Code") | F17: =COUNTIF('Phase 5'!$F$5:$F$100,"Code") | G17: =COUNTIF('Phase 6'!$F$5:$F$100,"Code") | H17: =SUM(B17:G17)
A18: Code + console | B18: =COUNTIF('Phase 1'!$F$5:$F$400,"Code + console") | C18: =COUNTIF('Phase 2'!$F$5:$F$144,"Code + console") | D18: =COUNTIF('Phase 3'!$F$5:$F$66,"Code + console") | E18: =COUNTIF('Phase 4'!$F$5:$F$51,"Code + console") | F18: =COUNTIF('Phase 5'!$F$5:$F$100,"Code + console") | G18: =COUNTIF('Phase 6'!$F$5:$F$100,"Code + console") | H18: =SUM(B18:G18)
A19: Design tool | B19: =COUNTIF('Phase 1'!$F$5:$F$400,"Design tool") | C19: =COUNTIF('Phase 2'!$F$5:$F$144,"Design tool") | D19: =COUNTIF('Phase 3'!$F$5:$F$66,"Design tool") | E19: =COUNTIF('Phase 4'!$F$5:$F$51,"Design tool") | F19: =COUNTIF('Phase 5'!$F$5:$F$100,"Design tool") | G19: =COUNTIF('Phase 6'!$F$5:$F$100,"Design tool") | H19: =SUM(B19:G19)
A20: Document + code | B20: =COUNTIF('Phase 1'!$F$5:$F$400,"Document + code") | C20: =COUNTIF('Phase 2'!$F$5:$F$144,"Document + code") | D20: =COUNTIF('Phase 3'!$F$5:$F$66,"Document + code") | E20: =COUNTIF('Phase 4'!$F$5:$F$51,"Document + code") | F20: =COUNTIF('Phase 5'!$F$5:$F$100,"Document + code") | G20: =COUNTIF('Phase 6'!$F$5:$F$100,"Document + code") | H20: =SUM(B20:G20)
A21: External · counsel | B21: =COUNTIF('Phase 1'!$F$5:$F$400,"External · counsel") | C21: =COUNTIF('Phase 2'!$F$5:$F$144,"External · counsel") | D21: =COUNTIF('Phase 3'!$F$5:$F$66,"External · counsel") | E21: =COUNTIF('Phase 4'!$F$5:$F$51,"External · counsel") | F21: =COUNTIF('Phase 5'!$F$5:$F$100,"External · counsel") | G21: =COUNTIF('Phase 6'!$F$5:$F$100,"External · counsel") | H21: =SUM(B21:G21)
A23: POLISH · URGENT, BEFORE LAUNCH
B24: Ready | C24: In progress | D24: Code review | E24: Blocked | F24: Done | G24: Total | H24: Days left
A25: Polish | B25: =COUNTIF('Polish'!$I$5:$I$200,"Ready") | C25: =COUNTIF('Polish'!$I$5:$I$200,"In progress") | D25: =COUNTIF('Polish'!$I$5:$I$200,"Code review") | E25: =COUNTIF('Polish'!$I$5:$I$200,"Blocked") | F25: =COUNTIF('Polish'!$I$5:$I$200,"Done") | G25: =COUNTA('Polish'!$B$5:$B$200) | H25: =SUMIF('Polish'!$I$5:$I$200,"<>Done",'Polish'!$J$5:$J$200)
A26: Kept apart from the phase totals above: these fixes cut across phases. Plan in documentation/polish.md.

Sheet Stage Progress
A1: Stage Progress — Phase 1
A2: Live formulas over the Phase 1 sheet — the top block needs no maintenance and is always current. The snapshot below is appended by hand once a day; that is the only part that shows velocity, because a formula cannot remember yesterday. Stage 9 is gated behind B8 and a sold edition — it is in the totals, not in the critical path.
A4: Stage | B4: Stage name | C4: Done | D4: Total | E4: % | F4: Days left | G4: In flight | H4: Blocked
A5: 0 | B5: Foundation & Decisions | C5: =COUNTIFS('Phase 1'!$C$5:$C$400,$A5,'Phase 1'!$I$5:$I$400,"Done") | D5: =COUNTIF('Phase 1'!$C$5:$C$400,$A5) | E5: =IF($D5=0,0,$C5/$D5) | F5: =SUMIFS('Phase 1'!$J$5:$J$400,'Phase 1'!$C$5:$C$400,$A5,'Phase 1'!$I$5:$I$400,"<>Done") | G5: =COUNTIFS('Phase 1'!$C$5:$C$400,$A5,'Phase 1'!$I$5:$I$400,"In progress")+COUNTIFS('Phase 1'!$C$5:$C$400,$A5,'Phase 1'!$I$5:$I$400,"Code review") | H5: =COUNTIFS('Phase 1'!$C$5:$C$400,$A5,'Phase 1'!$I$5:$I$400,"Blocked")
A6: 1 | B6: UI Scaffold on Fixtures | C6: =COUNTIFS('Phase 1'!$C$5:$C$400,$A6,'Phase 1'!$I$5:$I$400,"Done") | D6: =COUNTIF('Phase 1'!$C$5:$C$400,$A6) | E6: =IF($D6=0,0,$C6/$D6) | F6: =SUMIFS('Phase 1'!$J$5:$J$400,'Phase 1'!$C$5:$C$400,$A6,'Phase 1'!$I$5:$I$400,"<>Done") | G6: =COUNTIFS('Phase 1'!$C$5:$C$400,$A6,'Phase 1'!$I$5:$I$400,"In progress")+COUNTIFS('Phase 1'!$C$5:$C$400,$A6,'Phase 1'!$I$5:$I$400,"Code review") | H6: =COUNTIFS('Phase 1'!$C$5:$C$400,$A6,'Phase 1'!$I$5:$I$400,"Blocked")
A7: 2 | B7: Platform Foundations | C7: =COUNTIFS('Phase 1'!$C$5:$C$400,$A7,'Phase 1'!$I$5:$I$400,"Done") | D7: =COUNTIF('Phase 1'!$C$5:$C$400,$A7) | E7: =IF($D7=0,0,$C7/$D7) | F7: =SUMIFS('Phase 1'!$J$5:$J$400,'Phase 1'!$C$5:$C$400,$A7,'Phase 1'!$I$5:$I$400,"<>Done") | G7: =COUNTIFS('Phase 1'!$C$5:$C$400,$A7,'Phase 1'!$I$5:$I$400,"In progress")+COUNTIFS('Phase 1'!$C$5:$C$400,$A7,'Phase 1'!$I$5:$I$400,"Code review") | H7: =COUNTIFS('Phase 1'!$C$5:$C$400,$A7,'Phase 1'!$I$5:$I$400,"Blocked")
A8: 3 | B8: Athlete Network | C8: =COUNTIFS('Phase 1'!$C$5:$C$400,$A8,'Phase 1'!$I$5:$I$400,"Done") | D8: =COUNTIF('Phase 1'!$C$5:$C$400,$A8) | E8: =IF($D8=0,0,$C8/$D8) | F8: =SUMIFS('Phase 1'!$J$5:$J$400,'Phase 1'!$C$5:$C$400,$A8,'Phase 1'!$I$5:$I$400,"<>Done") | G8: =COUNTIFS('Phase 1'!$C$5:$C$400,$A8,'Phase 1'!$I$5:$I$400,"In progress")+COUNTIFS('Phase 1'!$C$5:$C$400,$A8,'Phase 1'!$I$5:$I$400,"Code review") | H8: =COUNTIFS('Phase 1'!$C$5:$C$400,$A8,'Phase 1'!$I$5:$I$400,"Blocked")
A9: 4 | B9: Sponsor Demand & Matching | C9: =COUNTIFS('Phase 1'!$C$5:$C$400,$A9,'Phase 1'!$I$5:$I$400,"Done") | D9: =COUNTIF('Phase 1'!$C$5:$C$400,$A9) | E9: =IF($D9=0,0,$C9/$D9) | F9: =SUMIFS('Phase 1'!$J$5:$J$400,'Phase 1'!$C$5:$C$400,$A9,'Phase 1'!$I$5:$I$400,"<>Done") | G9: =COUNTIFS('Phase 1'!$C$5:$C$400,$A9,'Phase 1'!$I$5:$I$400,"In progress")+COUNTIFS('Phase 1'!$C$5:$C$400,$A9,'Phase 1'!$I$5:$I$400,"Code review") | H9: =COUNTIFS('Phase 1'!$C$5:$C$400,$A9,'Phase 1'!$I$5:$I$400,"Blocked")
A10: 5 | B10: Campaign Execution | C10: =COUNTIFS('Phase 1'!$C$5:$C$400,$A10,'Phase 1'!$I$5:$I$400,"Done") | D10: =COUNTIF('Phase 1'!$C$5:$C$400,$A10) | E10: =IF($D10=0,0,$C10/$D10) | F10: =SUMIFS('Phase 1'!$J$5:$J$400,'Phase 1'!$C$5:$C$400,$A10,'Phase 1'!$I$5:$I$400,"<>Done") | G10: =COUNTIFS('Phase 1'!$C$5:$C$400,$A10,'Phase 1'!$I$5:$I$400,"In progress")+COUNTIFS('Phase 1'!$C$5:$C$400,$A10,'Phase 1'!$I$5:$I$400,"Code review") | H10: =COUNTIFS('Phase 1'!$C$5:$C$400,$A10,'Phase 1'!$I$5:$I$400,"Blocked")
A11: 6 | B11: Measurement & Reward | C11: =COUNTIFS('Phase 1'!$C$5:$C$400,$A11,'Phase 1'!$I$5:$I$400,"Done") | D11: =COUNTIF('Phase 1'!$C$5:$C$400,$A11) | E11: =IF($D11=0,0,$C11/$D11) | F11: =SUMIFS('Phase 1'!$J$5:$J$400,'Phase 1'!$C$5:$C$400,$A11,'Phase 1'!$I$5:$I$400,"<>Done") | G11: =COUNTIFS('Phase 1'!$C$5:$C$400,$A11,'Phase 1'!$I$5:$I$400,"In progress")+COUNTIFS('Phase 1'!$C$5:$C$400,$A11,'Phase 1'!$I$5:$I$400,"Code review") | H11: =COUNTIFS('Phase 1'!$C$5:$C$400,$A11,'Phase 1'!$I$5:$I$400,"Blocked")
A12: 7 | B12: Money & Reporting | C12: =COUNTIFS('Phase 1'!$C$5:$C$400,$A12,'Phase 1'!$I$5:$I$400,"Done") | D12: =COUNTIF('Phase 1'!$C$5:$C$400,$A12) | E12: =IF($D12=0,0,$C12/$D12) | F12: =SUMIFS('Phase 1'!$J$5:$J$400,'Phase 1'!$C$5:$C$400,$A12,'Phase 1'!$I$5:$I$400,"<>Done") | G12: =COUNTIFS('Phase 1'!$C$5:$C$400,$A12,'Phase 1'!$I$5:$I$400,"In progress")+COUNTIFS('Phase 1'!$C$5:$C$400,$A12,'Phase 1'!$I$5:$I$400,"Code review") | H12: =COUNTIFS('Phase 1'!$C$5:$C$400,$A12,'Phase 1'!$I$5:$I$400,"Blocked")
A13: 8 | B13: Integration, Hardening & Launch | C13: =COUNTIFS('Phase 1'!$C$5:$C$400,$A13,'Phase 1'!$I$5:$I$400,"Done") | D13: =COUNTIF('Phase 1'!$C$5:$C$400,$A13) | E13: =IF($D13=0,0,$C13/$D13) | F13: =SUMIFS('Phase 1'!$J$5:$J$400,'Phase 1'!$C$5:$C$400,$A13,'Phase 1'!$I$5:$I$400,"<>Done") | G13: =COUNTIFS('Phase 1'!$C$5:$C$400,$A13,'Phase 1'!$I$5:$I$400,"In progress")+COUNTIFS('Phase 1'!$C$5:$C$400,$A13,'Phase 1'!$I$5:$I$400,"Code review") | H13: =COUNTIFS('Phase 1'!$C$5:$C$400,$A13,'Phase 1'!$I$5:$I$400,"Blocked")
A14: 9 | B14: SponsorX NEXT (gated) | C14: =COUNTIFS('Phase 1'!$C$5:$C$400,$A14,'Phase 1'!$I$5:$I$400,"Done") | D14: =COUNTIF('Phase 1'!$C$5:$C$400,$A14) | E14: =IF($D14=0,0,$C14/$D14) | F14: =SUMIFS('Phase 1'!$J$5:$J$400,'Phase 1'!$C$5:$C$400,$A14,'Phase 1'!$I$5:$I$400,"<>Done") | G14: =COUNTIFS('Phase 1'!$C$5:$C$400,$A14,'Phase 1'!$I$5:$I$400,"In progress")+COUNTIFS('Phase 1'!$C$5:$C$400,$A14,'Phase 1'!$I$5:$I$400,"Code review") | H14: =COUNTIFS('Phase 1'!$C$5:$C$400,$A14,'Phase 1'!$I$5:$I$400,"Blocked")
B15: TOTAL | C15: =SUM(C5:C14) | D15: =SUM(D5:D14) | E15: =IF($D15=0,0,$C15/$D15) | F15: =SUM(F5:F14) | G15: =SUM(G5:G14) | H15: =SUM(H5:H14)
A17: DAILY SNAPSHOT
A18: One row per day, appended at end of day. Literal numbers, never formulas — a snapshot that recalculates is not a snapshot.
A19: Date | B19: S0 | C19: S1 | D19: S2 | E19: S3 | F19: S4 | G19: S5 | H19: S6 | I19: S7 | J19: S8 | K19: S9 | L19: Done | M19: Days left
A20: 2026-09-22 | B20: 22 | C20: 21 | D20: 18 | E20: 16 | F20: 8 | G20: 3 | H20: 0 | I20: 0 | J20: 0 | K20: 0 | L20: 88 | M20: 433
A21: 2026-09-23 | B21: 25 | C21: 21 | D21: 18 | E21: 17 | F21: 9 | G21: 11 | H21: 8 | I21: 12 | J21: 0 | K21: 0 | L21: 91 | M21: 428
A22: 2026-09-24 | B22: 25 | C22: 21 | D22: 19 | E22: 18 | F22: 10 | G22: 11 | H22: 11 | I22: 12 | J22: 12 | K22: 0 | L22: 139 | M22: 308
A23: 2026-09-25 | B23: 25 | C23: 21 | D23: 19 | E23: 18 | F23: 10 | G23: 11 | H23: 11 | I23: 12 | J23: 13 | K23: 0 | L23: 140 | M23: 305
A24: 2026-09-28 | B24: 25 | C24: 38 | D24: 19 | E24: 24 | F24: 16 | G24: 17 | H24: 17 | I24: 19 | J24: 18 | K24: 26 | L24: 219 | M24: 77
A25: 2026-09-29 | B25: 25 | C25: 38 | D25: 21 | E25: 26 | F25: 16 | G25: 17 | H25: 17 | I25: 19 | J25: 18 | K25: 26 | L25: 223 | M25: 79
A26: 2026-09-30 | B26: 25 | C26: 38 | D26: 21 | E26: 26 | F26: 16 | G26: 17 | H26: 17 | I26: 19 | J26: 18 | K26: 26 | L26: 223 | M26: 93
A27: 2026-10-01 | B27: 25 | C27: 42 | D27: 21 | E27: 29 | F27: 18 | G27: 17 | H27: 19 | I27: 20 | J27: 18 | K27: 27 | L27: 236 | M27: 60
A28: 2026-10-02 | B28: 25 | C28: 46 | D28: 23 | E28: 29 | F28: 18 | G28: 17 | H28: 19 | I28: 20 | J28: 18 | K28: 28 | L28: 243 | M28: 50
A29: 2026-10-05 | B29: 25 | C29: 47 | D29: 23 | E29: 29 | F29: 27 | G29: 19 | H29: 20 | I29: 20 | J29: 18 | K29: 37 | L29: 265 | M29: 47
A30: 2026-10-07 | B30: 25 | C30: 47 | D30: 23 | E30: 29 | F30: 27 | G30: 19 | H30: 20 | I30: 20 | J30: 18 | K30: 37 | L30: 265 | M30: 58.5
A31: 2026-10-08 | B31: 26 | C31: 56 | D31: 25 | E31: 29 | F31: 27 | G31: 19 | H31: 20 | I31: 20 | J31: 19 | K31: 37 | L31: 278 | M31: 37
... A42: 2026-10-28 | B42: 28 | C42: 62 | D42: 25 | E42: 29 | F42: 27 | G42: 19 | H42: 20 | I42: 20 | J42: 45 | K42: 38 | L42: 313 | M42: 23.5

Sheet Polish
A1: SponsorX — Polish · Fix before launch (URGENT)
A2: 53 tasks across 36 user-experience flaws found 2026-10-28 · do these before cleaning up any other task on the board · do POL-BE-04 first (hurting sponsors now, while Stripe is paused) · plan: documentation/polish.md
A4: Order | B4: ID | C4: Stage | D4: Stage name | E4: Cat | F4: Where the work happens | G4: Task | H4: DETAILS | I4: Status | J4: Weight (days) | K4: Date Started | L4: Date Done | M4: Owner | N4: Unblocks | O4: Depends On | P4: Acceptance Criteria | Q4: Refs | R4: Notes
A5: 1 | B5: POL-BE-01 | C5: 1 | D5: A · Money, minors, consent | E5: BE | F5: Code | G5: Payouts stop going to the old guardian | H5: After a guardian handoff or coming of age, the old payout account stops receiving money (PayoutAccount is unique per athlete, so it is reused today). Payouts wait for the new holder's own account; both are told. | I5: Done | J5: 2 | K5: 46323 | L5: 46323 | M5: rcfworks | N5: 1 | P5: No payout reaches the old account after a handoff or coming of age; new holder asked to set up; tests | Q5: polish.md #1 | R5: Raised 2026-10-28 from the UX review. Rule decided 2026-10-28: anything not yet paid out follows the athlete to the new holder.
A6: 2 | B6: POL-FE-01 | C6: 1 | D6: A · Money, minors, consent | E6: FE | F6: Code | G6: New guardian or adult athlete sets up payouts | H6: After a handoff or coming of age, the payouts screen asks the new holder to set up their own account and shows payouts waiting. | I6: Ready | J6: 1 | M6: HeckerCreatives | N6: 0 | O6: POL-BE-01 | P6: New holder sees the prompt and waiting payouts; old holder no longer sees the account | Q6: polish.md #1 | R6: Raised 2026-10-28 from the UX review.
A7: 3 | B7: POL-BE-02 | C7: 1 | D7: A · Money, minors, consent | E7: BE | F7: Code | G7: A minor's date-of-birth change and coming-of-age takeover are held | H7: While a minor, a DOB change is held for the guardian and BTG instead of applying at once. A coming-of-age takeover is always held for BTG, even when the ID reads clear. | I7: Done | J7: 2 | K7: 46323 | L7: 46323 | M7: rcfworks | N7: 1 | P7: Minor's DOB change waits for approval; coming of age never removes a guardian without BTG; tests | Q7: polish.md #2 | R7: Raised 2026-10-28 from the UX review. Decided 2026-10-28: BTG alone approves a change that would make a minor an adult; takeover automatic only when the ID reads clear.
A8: 4 | B8: POL-FE-02 | C8: 1 | D8: A · Money, minors, consent | E8: FE | F8: Code | G8: DOB change shows 'waiting for approval' | H8: Profile edit shows a minor's DOB change as waiting; guardian and BTG see Approve / Decline. | I8: Ready | J8: 1 | M8: HeckerCreatives | N8: 0 | O8: POL-BE-02 | P8: Minor sees waiting state; guardian and BTG can approve or decline | Q8: polish.md #2 | R8: Raised 2026-10-28 from the UX review.
A9: 5 | B9: POL-BE-03 | C9: 1 | D9: A · Money, minors, consent | E9: BE | F9: Code | G9: A team can't raise its share without the athlete's yes | H9: Any share raise (directly added athletes included, not just invited) needs the athlete's agreement, the guardian's for a minor. Lowering applies at once. Both emailed. | I9: Done | J9: 2 | K9: 46324 | L9: 46324 | M9: rcfworks | N9: 1 | P9: No share goes up without the athlete's or guardian's yes; tests for direct, invited and minor | Q9: polish.md #3 | R9: Raised 2026-10-28 from the UX review. Decided 2026-10-29: the share typed at Add athlete needs the athlete's yes too; BTG's standard share applies until then. PR #322.
A10: 6 | B10: POL-FE-03 | C10: 1 | D10: A · Money, minors, consent | E10: FE | F10: Code | G10: Accept or decline a team share change | H10: Athlete or guardian screen showing old and new share with Accept / Decline; team sees 'waiting for the athlete'. | I10: Ready | J10: 1 | M10: HeckerCreatives | N10: 0 | O10: POL-BE-03 | P10: Athlete or guardian can accept or decline; team sees the pending state | Q10: polish.md #3 | R10: Raised 2026-10-28 from the UX review.
A11: 7 | B11: POL-BE-04 | C11: 1 | D11: A · Money, minors, consent | E11: BE | F11: Code | G11: No reminders or cancellations while payment is off | H11: sweepUnpaidOrders and the reminders skip orders while the payment provider is off; the countdown starts when payment opens. Hurting sponsors now, while Stripe is paused. | I11: Done | J11: 1 | K11: 46323 | L11: 46323 | M11: rcfworks | N11: 1 | P11: With payment off no reminder and no cancellation; with it on unchanged; tests | Q11: polish.md #4 | R11: Raised 2026-10-28 from the UX review.
A12: 8 | B12: POL-FE-04 | C12: 1 | D12: A · Money, minors, consent | E12: FE | F12: Code | G12: Checkout says payment opens later | H12: Checkout and order page say plainly that payment is not open yet and the order is held, not cancelled. | I12: Ready | J12: 0.5 | M12: HeckerCreatives | N12: 0 | O12: POL-BE-04 | P12: Sponsor sees the order is held until payment opens | Q12: polish.md #4 | R12: Raised 2026-10-28 from the UX review.
A13: 9 | B13: POL-BE-05 | C13: 1 | D13: A · Money, minors, consent | E13: BE | F13: Code | G13: Order quote with fees before placing | H13: A quote endpoint returns subtotal, fees and total before the order is placed (skip if one already exists). | I13: Done | J13: 1 | K13: 46324 | L13: 46324 | M13: rcfworks | N13: 1 | P13: Quote total equals the charged total; tests | Q13: polish.md #5 | R13: Raised 2026-10-28 from the UX review. PR #324: the cart, the held checkout and placing carry a quote (subtotal, fees, total); placing refuses a changed total.
A14: 10 | B14: POL-FE-05 | C14: 1 | D14: A · Money, minors, consent | E14: FE | F14: Code | G14: Checkout shows the full total before committing | H14: Replace 'Fees: added when the order is placed' and 'Total so far' with the real total next to the button that commits. | I14: Ready | J14: 0.5 | M14: HeckerCreatives | N14: 0 | O14: POL-BE-05 | P14: Total shown before placing equals the total charged | Q14: polish.md #5 | R14: Raised 2026-10-28 from the UX review.
A15: 11 | B15: POL-BE-06 | C15: 1 | D15: A · Money, minors, consent | E15: BE | F15: Code | G15: Duplicate payment creates a refund to send | H15: A duplicate payment adds a row to Refunds to send and flags the order; BTG can mark it refunded. | I15: Done | J15: 1 | K15: 46324 | L15: 46324 | M15: rcfworks | N15: 1 | P15: Duplicate shows in Refunds to send and on the order; tests | Q15: polish.md #6 | R15: Raised 2026-10-28 from the UX review. PR #325: a card payment confirmed for an order already paid (PAID_TWICE) or refunded (PAID_AFTER_REFUND) is its own refund row; refunds of extra payments never shorten the order's own.
A16: 12 | B16: POL-FE-06 | C16: 1 | D16: A · Money, minors, consent | E16: FE | F16: Code | G16: Order page shows a duplicate payment | H16: Order page shows the duplicate and its refund status; BTG gets a Mark refunded button. | I16: Ready | J16: 0.5 | M16: HeckerCreatives | N16: 0 | O16: POL-BE-06 | P16: Sponsor and BTG see the duplicate and refund status | Q16: polish.md #6 | R16: Raised 2026-10-28 from the UX review.
A17: 13 | B17: POL-BE-07 | C17: 1 | D17: A · Money, minors, consent | E17: BE | F17: Code | G17: Staff redeem needs a venue code, with undo | H17: Redeem requires a staff PIN per reward or event; a redeem can be undone within a few minutes. | I17: Ready | J17: 2 | M17: rcfworks | N17: 1 | P17: No redeem without the venue code; undo works in the window; tests | Q17: polish.md #7 | R17: Raised 2026-10-28 from the UX review.
A18: 14 | B18: POL-FE-07 | C18: 1 | D18: A · Money, minors, consent | E18: FE | F18: Code | G18: Fan page asks for the staff code | H18: 'Staff: redeem now' asks for the code and confirms; shows Undo for a few minutes. | I18: Ready | J18: 1 | M18: HeckerCreatives | N18: 0 | O18: POL-BE-07 | P18: Redeem needs the code and a confirmation; undo shown | Q18: polish.md #7 | R18: Raised 2026-10-28 from the UX review.
A19: 15 | B19: POL-BE-08 | C19: 1 | D19: A · Money, minors, consent | E19: BE | F19: Code | G19: Each fan gets their own claim on a shared code | H19: Claims are per fan, not per code, up to the reward's limit; later fans' emails are collected. | I19: Ready | J19: 2 | M19: rcfworks | N19: 1 | P19: Two fans on one code each get their own claim; tests | Q19: polish.md #8 | R19: Raised 2026-10-28 from the UX review.
A20: 16 | B20: POL-FE-08 | C20: 1 | D20: A · Money, minors, consent | E20: FE | F20: Code | G20: Fan page shows the fan's own claim | H20: The page shows this fan's claim, or 'all claimed', never another fan's hold. | I20: Ready | J20: 0.5 | M20: HeckerCreatives | N20: 0 | O20: POL-BE-08 | P20: Each fan sees only their own claim | Q20: polish.md #8 | R20: Raised 2026-10-28 from the UX review.
A21: 17 | B21: POL-BE-09 | C21: 2 | D21: B · Waiting or stuck | E21: BE | F21: Code | G21: A minor's invitation emails go to the guardian | H21: Invitation, reminder and expiry emails for a minor go to the guardian (copy to the minor); today they go only to the minor (notify-invitation.mts). | I21: Ready | J21: 1 | M21: rcfworks | N21: 0 | P21: Guardian gets every email for a minor's invitation; tests | Q21: polish.md #9 | R21: Raised 2026-10-28 from the UX review.
A22: 18 | B22: POL-BE-10 | C22: 2 | D22: B · Waiting or stuck | E22: BE | F22: Code | G22: Guardian handoff reminders and escalation | H22: Remind the current guardian after 3 days; escalate to BTG after 7, who can decide with the documents. | I22: Ready | J22: 2 | M22: rcfworks | N22: 1 | P22: Reminders and escalation on schedule; BTG decides an escalated handoff; tests | Q22: polish.md #10 | R22: Raised 2026-10-28 from the UX review.
A23: 19 | B23: POL-FE-10 | C23: 2 | D23: B · Waiting or stuck | E23: FE | F23: Code | G23: Handoff desk shows age and BTG decide | H23: Handoff desk shows how long each has waited and a Decide button on escalated ones. | I23: Ready | J23: 0.5 | M23: HeckerCreatives | N23: 0 | O23: POL-BE-10 | P23: BTG sees age and can decide escalated handoffs | Q23: polish.md #10 | R23: Raised 2026-10-28 from the UX review.
A24: 20 | B24: POL-BE-11 | C24: 2 | D24: B · Waiting or stuck | E24: BE | F24: Code | G24: Account closure settles live deals first | H24: With live deals, closing is held for BTG, which settles each deal and tells the sponsor. A minor's closure needs the guardian. Earned money pays to the account on file without a login. | I24: Ready | J24: 2 | M24: rcfworks | N24: 1 | P24: No closure leaves a live deal unsettled or unannounced; a minor can't close alone; earned money still pays; tests | Q24: polish.md #11 | R24: Raised 2026-10-28 from the UX review.
A25: 21 | B25: POL-FE-11 | C25: 2 | D25: B · Waiting or stuck | E25: FE | F25: Code | G25: Closing screen lists live deals | H25: Before confirming, list the live deals and what happens to each; fix the payout promise wording. | I25: Ready | J25: 0.5 | M25: HeckerCreatives | N25: 0 | O25: POL-BE-11 | P25: Closing screen shows live deals and accurate payout wording | Q25: polish.md #11 | R25: Raised 2026-10-28 from the UX review.
A26: 22 | B26: POL-BE-12 | C26: 2 | D26: B · Waiting or stuck | E26: BE | F26: Code | G26: Held payouts email BTG and are counted | H26: A held payout emails BTG Finance with the reason and is included in the dashboard counts. | I26: Ready | J26: 1 | M26: rcfworks | N26: 1 | P26: Every held payout emails and is counted; tests | Q26: polish.md #12 | R26: Raised 2026-10-28 from the UX review.
A27: 23 | B27: POL-FE-12 | C27: 2 | D27: B · Waiting or stuck | E27: FE | F27: Code | G27: Held payouts on the BTG dashboard | H27: Dashboard tile for held payouts, linked to the queue. | I27: Ready | J27: 0.5 | M27: HeckerCreatives | N27: 0 | O27: POL-BE-12 | P27: Tile shows the count and opens the queue | Q27: polish.md #12 | R27: Raised 2026-10-28 from the UX review.
A28: 24 | B28: POL-FE-13 | C28: 2 | D28: B · Waiting or stuck | E28: FE | F28: Code | G28: Sponsor invoices screen | H28: 'Invoices to pay' and Billing open an invoices screen (GET /campaigns/{id}/invoices already exists) listing each invoice, status and a pay link. | I28: Ready | J28: 1.5 | M28: HeckerCreatives | N28: 0 | P28: Sponsor can open, see and pay every invoice | Q28: polish.md #13 | R28: Raised 2026-10-28 from the UX review.
A29: 25 | B29: POL-BE-14 | C29: 2 | D29: B · Waiting or stuck | E29: BE | F29: Code | G29: Held make-goods email BTG and are counted | H29: A held make-good emails BTG and is included in the dashboard counts (POL-BE-15). | I29: Ready | J29: 0.5 | M29: rcfworks | N29: 0 | P29: Every held make-good emails and is counted; tests | Q29: polish.md #14 | R29: Raised 2026-10-28 from the UX review.
A30: 26 | B30: POL-BE-15 | C30: 2 | D30: B · Waiting or stuck | E30: BE | F30: Code | G30: One counts endpoint for every BTG queue | H30: Counts for sign-ups, organisations, sponsor requests, handoffs, held listings and orders, delivery issues, payouts and make-goods, plus the existing four, with the oldest item's age. | I30: Ready | J30: 1.5 | M30: rcfworks | N30: 1 | P30: Every queue that waits on BTG has a count; roles and tenants enforced; tests | Q30: polish.md #15 | R30: Raised 2026-10-28 from the UX review.
A31: 27 | B31: POL-FE-15 | C31: 2 | D31: B · Waiting or stuck | E31: FE | F31: Code | G31: BTG dashboard shows every queue | H31: One tile per queue with its count and oldest age, linked to the queue. | I31: Ready | J31: 1 | M31: HeckerCreatives | N31: 0 | O31: POL-BE-15 | P31: Every BTG queue has a tile linked to it | Q31: polish.md #15 | R31: Raised 2026-10-28 from the UX review.
A32: 28 | B32: POL-FE-16 | C32: 3 | D32: C · Confusing or extra work | E32: FE | F32: Code | G32: Change guardian email at /join | H32: Add 'Change guardian email' on the /join status page (the API already allows it). | I32: Ready | J32: 0.5 | M32: HeckerCreatives | N32: 0 | P32: A mistyped guardian email can be fixed and the invite resent | Q32: polish.md #16 | R32: Raised 2026-10-28 from the UX review.
A33: 29 | B33: POL-BE-17 | C33: 3 | D33: C · Confusing or extra work | E33: BE | F33: Code | G33: Withdraw a sponsor request | H33: Add withdraw for a sent request if missing; confirm PATCH /briefs covers edit while editable. | I33: Ready | J33: 0.5 | M33: rcfworks | N33: 1 | P33: Sponsor can withdraw; edit allowed only while editable; tests | Q33: polish.md #17 | R33: Raised 2026-10-28 from the UX review.
A34: 30 | B34: POL-FE-17 | C34: 3 | D34: C · Confusing or extra work | E34: FE | F34: Code | G34: Sponsor request detail with Edit and Withdraw | H34: The request opens to a detail page with Edit (while editable) and Withdraw. | I34: Ready | J34: 1 | M34: HeckerCreatives | N34: 0 | O34: POL-BE-17 | P34: Sponsor can open, edit and withdraw a request | Q34: polish.md #17 | R34: Raised 2026-10-28 from the UX review.
A35: 31 | B35: POL-BE-18 | C35: 3 | D35: C · Confusing or extra work | E35: BE | F35: Code | G35: Resend and change the request confirmation email | H35: Endpoints to resend the confirmation email and change the address, rate limited (if missing). | I35: Ready | J35: 0.5 | M35: rcfworks | N35: 1 | P35: Resend and change work, rate limited; tests | Q35: polish.md #18 | R35: Raised 2026-10-28 from the UX review.
A36: 32 | B36: POL-FE-18 | C36: 3 | D36: C · Confusing or extra work | E36: FE | F36: Code | G36: Resend email and Change email on the request status | H36: Buttons on the sponsor request status page. | I36: Ready | J36: 0.5 | M36: HeckerCreatives | N36: 0 | O36: POL-BE-18 | P36: Sponsor can resend or fix the address | Q36: polish.md #18 | R36: Raised 2026-10-28 from the UX review.
A37: 33 | B37: POL-BE-19 | C37: 3 | D37: C · Confusing or extra work | E37: BE | F37: Code | G37: Sponsor admin invites teammates | H37: Invite by email and set roles within the sponsor's own organisation (if the API lacks it). | I37: Ready | J37: 1.5 | M37: rcfworks | N37: 1 | P37: Invite and role change work; own tenant only; tests | Q37: polish.md #19 | R37: Raised 2026-10-28 from the UX review.
A38: 34 | B38: POL-FE-19 | C38: 3 | D38: C · Confusing or extra work | E38: FE | F38: Code | G38: Sponsor team screen; hide dead menu items | H38: Team screen to invite and set roles; hide Settings and Messages until they work. | I38: Ready | J38: 1 | M38: HeckerCreatives | N38: 0 | O38: POL-BE-19 | P38: Sponsor admin can invite teammates; no dead menu items | Q38: polish.md #19 | R38: Raised 2026-10-28 from the UX review.
A39: 35 | B39: POL-FE-20 | C39: 3 | D39: C · Confusing or extra work | E39: FE | F39: Code | G39: 'Needs your OK' only when there is an action | H39: Show it only when the sponsor has an action, linked straight to it. | I39: Ready | J39: 0.5 | M39: HeckerCreatives | N39: 0 | P39: Never shown without a sponsor action; links to it | Q39: polish.md #20 | R39: Raised 2026-10-28 from the UX review.
A40: 36 | B40: POL-FE-21 | C40: 3 | D40: C · Confusing or extra work | E40: FE | F40: Code | G40: Request progress steps follow the real state | H40: No 'Price agreed' or 'Campaign live' before they happen. | I40: Ready | J40: 0.5 | M40: HeckerCreatives | N40: 0 | P40: Steps match the request's real state | Q40: polish.md #21 | R40: Raised 2026-10-28 from the UX review.
A41: 37 | B41: POL-BE-22 | C41: 3 | D41: C · Confusing or extra work | E41: BE | F41: Code | G41: Mark a stalled campaign | H41: The API flags a campaign whose staffing has stalled and when BTG stepped in. | I41: Ready | J41: 0.5 | M41: rcfworks | N41: 1 | P41: Stalled campaigns flagged; tests | Q41: polish.md #22 | R41: Raised 2026-10-28 from the UX review.
A42: 38 | B42: POL-FE-22 | C42: 3 | D42: C · Confusing or extra work | E42: FE | F42: Code | G42: Sponsor sees 'BTG is finding more athletes' | H42: Shown on a stalled campaign, with a date. | I42: Ready | J42: 0.5 | M42: HeckerCreatives | N42: 0 | O42: POL-BE-22 | P42: Sponsor sees the stalled message | Q42: polish.md #22 | R42: Raised 2026-10-28 from the UX review.
A43: 39 | B43: POL-FE-23 | C43: 3 | D43: C · Confusing or extra work | E43: FE | F43: Code | G43: Content review shows a review-by date and opens the post | H43: Show the due date (back end adds it if missing); the dashboard link opens the post. | I43: Ready | J43: 0.5 | M43: HeckerCreatives | N43: 0 | P43: Due date shown; link lands on the post | Q43: polish.md #23 | R43: Raised 2026-10-28 from the UX review.
A44: 40 | B44: POL-FE-24 | C44: 3 | D44: C · Confusing or extra work | E44: FE | F44: Code | G44: Athlete Campaign Orders list with Accept and Decline | H44: A Campaign Orders list; Decline uses the existing API; menu labels separate it from marketplace sales. | I44: Ready | J44: 1 | M44: HeckerCreatives | N44: 0 | P44: Athlete can see, accept and decline Campaign Orders | Q44: polish.md #24 | R44: Raised 2026-10-28 from the UX review.
A45: 41 | B45: POL-FE-25 | C45: 3 | D45: C · Confusing or extra work | E45: FE | F45: Code | G45: Earnings and Payouts say the same thing | H45: Remove 'BTG handles payouts outside the platform' where it contradicts the Payouts page. | I45: Ready | J45: 0.25 | M45: HeckerCreatives | N45: 0 | P45: One consistent message | Q45: polish.md #25 | R45: Raised 2026-10-28 from the UX review.
A46: 42 | B46: POL-FE-26 | C46: 3 | D46: C · Confusing or extra work | E46: FE | F46: Code | G46: Minors see 'your guardian sets this up' | H46: Hide the Stripe setup button for a minor; the guardian sees it. | I46: Ready | J46: 0.5 | M46: HeckerCreatives | N46: 0 | P46: Minor never sees a button that fails | Q46: polish.md #26 | R46: Raised 2026-10-28 from the UX review.
A47: 43 | B47: POL-FE-27 | C47: 3 | D47: C · Confusing or extra work | E47: FE | F47: Code | G47: Confirm before declining an invitation | H47: Add an 'are you sure?' like offers have. | I47: Ready | J47: 0.25 | M47: HeckerCreatives | N47: 0 | P47: Declining asks first | Q47: polish.md #27 | R47: Raised 2026-10-28 from the UX review.
A48: 44 | B48: POL-FE-28 | C48: 3 | D48: C · Confusing or extra work | E48: FE | F48: Code | G48: Confirm before 'Confirm delivered' | H48: Confirmation saying the seller will be paid. | I48: Ready | J48: 0.25 | M48: HeckerCreatives | N48: 0 | P48: Confirm delivered asks first | Q48: polish.md #28 | R48: Raised 2026-10-28 from the UX review.
A49: 45 | B49: POL-BE-29 | C49: 3 | D49: C · Confusing or extra work | E49: BE | F49: Code | G49: Handoff queue oldest first | H49: Sort guardian handoffs oldest first. | I49: Ready | J49: 0.25 | M49: rcfworks | N49: 0 | P49: Oldest first; test | Q49: polish.md #29 | R49: Raised 2026-10-28 from the UX review.
A50: 46 | B50: POL-FE-30 | C50: 3 | D50: C · Confusing or extra work | E50: FE | F50: Code | G50: Unsubscribe fallback points at support | H50: Replace 'reply to the email' (no-reply sender) with the support address. | I50: Ready | J50: 0.25 | M50: HeckerCreatives | N50: 0 | P50: Fallback reaches a person | Q50: polish.md #30 | R50: Raised 2026-10-28 from the UX review.
A51: 47 | B51: POL-FE-31 | C51: 4 | D51: D · Polish | E51: FE | F51: Code | G51: Plain message for a failed card payment | H51: Replace 'ref: pi_…' with what to do next and how to contact support. | I51: Ready | J51: 0.25 | M51: HeckerCreatives | N51: 0 | P51: No raw Stripe codes shown | Q51: polish.md #31 | R51: Raised 2026-10-28 from the UX review.
A52: 48 | B52: POL-FE-32 | C52: 4 | D52: D · Polish | E52: FE | F52: Code | G52: 'Welcome' on first sign-in | H52: Not 'Welcome back' for a brand-new user. | I52: Ready | J52: 0.25 | M52: HeckerCreatives | N52: 0 | P52: First sign-in says Welcome | Q52: polish.md #32 | R52: Raised 2026-10-28 from the UX review.
A53: 49 | B53: POL-FE-33 | C53: 4 | D53: D · Polish | E53: FE | F53: Code | G53: Remove 'Sample screens' for real users | H53: Settings stops linking real athletes to Riley's sample screens. | I53: Ready | J53: 0.25 | M53: HeckerCreatives | N53: 0 | P53: Real users see no sample link | Q53: polish.md #33 | R53: Raised 2026-10-28 from the UX review.
A54: 50 | B54: POL-FE-34 | C54: 4 | D54: D · Polish | E54: FE | F54: Code | G54: Sign in button on 'You're approved' | H54: Add a Sign in button to the approved /join status. | I54: Ready | J54: 0.25 | M54: HeckerCreatives | N54: 0 | P54: Approved person can sign in from the page | Q54: polish.md #34 | R54: Raised 2026-10-28 from the UX review.
... A56: 52 | B56: POL-BE-36 | C56: 5 | D56: E · Payments switch | E56: BE | F56: Code | G56: Payments on/off switch, held in the database | H56: A platform-wide Payments switch BTG Admin and Finance can flip at once without a deploy, with a reason, audited (who, when). Can only turn on when production has a live key and webhook secrets; PAYMENT_PROVIDER stays the master off. Off = no checkout, no transfer, no non-payment cancellation (with POL-BE-04). | I56: Ready | J56: 1.5 | M56: rcfworks | N56: 1 | P56: BTG Admin and Finance can switch payments on and off; each change audited with a reason; other roles refused; off blocks checkout, transfers and non-payment cancellation; can't turn on without keys; tests | Q56: polish.md #36 | R56: Raised 2026-10-28 by the user: live key ready today, payments stay off until polish is done.
A57: 53 | B57: POL-FE-36 | C57: 5 | D57: E · Payments switch | E57: FE | F57: Code | G57: Payments switch on BTG's admin screen | H57: A Payments on/off control on BTG's admin screen with a reason box and confirmation, showing who changed it and when; pay and payout buttons say payments open soon while it is off. | I57: Ready | J57: 0.5 | M57: HeckerCreatives | N57: 0 | O57: POL-BE-36 | P57: BTG Admin and Finance see and use the switch with a reason; others don't see it; screens say payments open soon while off | Q57: polish.md #36 | R57: Raised 2026-10-28 by the user.

Sheet Phase 1
A1: SponsorX — Phase 1 · Managed Marketplace
A2: 269 tasks · 615 person-days · the loop that must work before anything else is built · Stage 9 (SponsorX NEXT, spec v2.0) is gated, not queued
A4: Order | B4: ID | C4: Stage | D4: Stage name | E4: Cat | F4: Where the work happens | G4: Task | H4: DETAILS | I4: Status | J4: Weight (days) | K4: Date Started | L4: Date Done | M4: Owner | N4: Unblocks | O4: Depends On | P4: Acceptance Criteria | Q4: Refs | R4: Notes
A5: 0 | B5: P0-PMO-02 | C5: 0 | D5: Foundation & Decisions | E5: PMO | F5: Document | G5: Confirm data residency and set regions (G-02) | H5: DECISION GATE G-02 · Data residency — which region do Railway and R2 run in? — Pick the geographic region Railway and Cloudflare R2 run in, and write it down. Almost certainly US-only: NIL is US law, sponsors are local US businesses, minors' data is involved. Moving a database region later is painful, so this is decided before anything exists. | I5: Done | J5: 1 | N5: 2 | P5: Railway region and R2 region chosen explicitly, recorded, not left at defaults | Q5: Addendum A7
A6: 0 | B6: P1-ART-01 | C6: 1 | D6: UI Scaffold on Fixtures | E6: ART | F6: Design tool | G6: Brand retheme — mockup v1.0 purple/teal → BTG logo blue/orange | H6: Already shipped. The whole app was re-themed from the old mockup purple to the BTG logo's blue and orange via one token file. | I6: Done | P6: Token swap in globals.css; ground #0A0C10, primary #2E9BF5, accent #F97A1F, warn #FACC15; portal accents follow the logo | R6: Shipped before this plan
A7: 0 | B7: P1-ART-02 | C7: 1 | D7: UI Scaffold on Fixtures | E7: ART | F7: Design tool | G7: Wire official logo assets | H7: Already shipped. Official logo artwork wired into login, portal headers, marketing hero and the browser tab icon. | I7: Done | P7: sponsorx-badge/title/full.png in public/; Logo component; favicon via src/app/icon.png | R7: Shipped before this plan
A8: 0 | B8: P1-ART-03 | C8: 1 | D8: UI Scaffold on Fixtures | E8: ART | F8: Design tool | G8: Sponsor portal redesign — Command Deck + Executive Bento + radial ROI gauge | H8: Already shipped. The four sponsor-facing pages redesigned for client-demo quality, including the radial ROI gauge. | I8: Done | P8: Spec and plan under docs/superpowers/; shipped across 9 commits | R8: Shipped before this plan
A9: 0 | B9: P1-FE-01 | C9: 1 | D9: UI Scaffold on Fixtures | E9: FE | F9: Code | G9: Build the 10 remaining stub routes on fixtures | H9: Already shipped. The last ten placeholder screens were built out, so every portal is fully navigable on mock data. | I9: Done | P9: join, athlete/invitations, athlete/orders/[id], athlete/earnings, admin, admin/applications, admin/approvals, admin/finance, packages, property — no ScreenStub remains | R9: Shipped before this plan
A10: 0 | B10: P1-FE-02 | C10: 1 | D10: UI Scaffold on Fixtures | E10: FE | F10: Code | G10: State & polish pass across all routes (A2) | H10: Already shipped. Loading, empty and error states across all 25 routes, plus the light theme and responsive behaviour. | I10: Done | N10: 2 | P10: Loading / empty / error states; light theme; responsive; 25 routes build green | R10: Shipped before this plan
A11: 0 | B11: P1-FE-03 | C11: 1 | D11: UI Scaffold on Fixtures | E11: FE | F11: Code | G11: No-JS accessible fan redeem page | H11: Already shipped. The fan redeem page renders with JavaScript disabled and passes accessibility checks. | I11: Done | P11: r/[token] renders without JavaScript, branded, a11y-checked | R11: Shipped before this plan
A12: 1 | B12: P0-OPS-01 | C12: 0 | D12: Foundation & Decisions | E12: OPS | F12: Vendor console | G12: Create Railway account, project and billing | H12: Open the Railway account and project in the region chosen above. Set a spend alert — usage-based hosting surprises people. | I12: Done | J12: 1 | K12: 2026-09-18 | L12: 2026-09-23 | M12: rcfworks | N12: 1 | O12: P0-PMO-02 | P12: Project exists in the confirmed region; billing and spend alerts configured | Q12: Guide §10 | R12: Workspace 'rcarr-crypto's Projects'; project 'sponsorX' ID 1c11f29a-b569-4d14-98cf-e97a4d3ae209. PRO PLAN with spend limits set (compute hard $150 / email $25; agent hard $20 / email $20) - that half of the acceptance is met. REOPENED 2026-09-18: the region half is NOT met. Read from the Railway CLI, `region` is null on the service instance in BOTH environments - nothing was ever set explicitly. Railway therefore placed them by default: staging landed on US East, production landed on 'sfo' (San Francisco). The US East chip read in the console on 2026-09-18 was staging's. G-02 requires us-east4-eqdc4a, so production currently violates data residency. Fix is one serviceInstanceUpdate per environment setting region='us-east4-eqdc4a'; closes as soon as that is applied and must happen before Postgres exists under P2-OPS-01, because moving a database region later is exactly what G-02 was written to avoid. 2026-09-18 update: multiRegionConfig set to us-east4-eqdc4a on web in BOTH environments (the legacy `region` field is inert - Railway reads multiRegionConfig). web's running deployment still reports sfo and will move on its next redeploy, which this session is not permitted to trigger. CLOSED 2026-09-18: web's running deployment now reports multiRegionConfig {us-east4-eqdc4a: 1}. Both halves of the acceptance are met - region confirmed in the live deployment, billing and spend limits configured. 2026-09-18: set back to In progress under rcfworks at the user's instruction, so the whole Railway / Clerk / backend-setup cluster reads as one owned workstream. THE WORK ITSELF IS FINISHED and was completed on 2026-09-18 - the Date Done column still holds it. Status here signals ownership of the workstream, not that the work is outstanding. CLOSED 2026-09-23, verified in the console. PROJECT: sponsorX, environments production and staging; production runs web + Postgres-production. REGION: web is US East (Virginia, USA), matching A7's us-east4-eqdc4a. BILLING: Pro Workspace, card ending 1115, billing email rcarr@icarrefound.org. OWNERSHIP: the workspace reads 'rcarr-crypto's Project' — a personal workspace, confirmed by the user as the owner's own account and the one holding Pro; that is the BTG-controlled account for this purpose and the question is settled. SPEND ALERTS: compute hard limit $50 / email alert $25; agent hard limit $5 / alert $0 because nothing here uses Railway agents. Current usage $1.35 with $2.71 projected for the period against $20 included, so the limits are headroom against a runaway rather than a budget.
A13: 2 | B13: P0-PMO-07 | C13: 0 | D13: Foundation & Decisions | E13: PMO | F13: Document | G13: Author the RBAC matrix (§38 deliverable) | H13: A table: each of the 12 user roles down one side, every Phase 1 resource across the top, allow/deny in each cell. This table literally becomes the automated test suite later, so it has to be agreed by humans first. | I13: Done | J13: 3 | K13: 2026-09-14 | L13: 2026-09-14 | M13: rcfworks | N13: 3 | P13: All 12 roles × every Phase 1 resource, in a table, agreed — this becomes the authz test suite | Q13: §8, §38 | R13: 2026-09-14 DRAFTED, awaiting sign-off - documentation/SponsorX-RBAC-Matrix.md v0.1. 12 roles from blueprint S8 (which the graphify-converted copy has LOST - read the Drive original). Roles map 1:1 to the Prisma Role enum in the Implementation Guide V2. Task wording amended by PR in the phase doc: the original described a flat roles x resources grid, which cannot express ownership (PROPERTY_MGR may read own-property athletes, not other-property). Now 4 axes: role x resource(+field) x action x ownership. 85 active test cases + 3 deferred, in the S09 CASES format ready to lift into authz.matrix.test.ts. NOT DONE: acceptance requires 'agreed'; 5 open decisions D1-D5 need human answers (D1 guardian accept for minor - S8 explicitly defers; D2 athlete sees sponsor price; D3 property mgr sees roster earnings - legal; D4 sales sees athlete rates; D5 athlete sees own score). | DONE 2026-09-14. All five decisions adopted at the RESTRICTIVE option, so each can only be loosened later by a deliberate recorded decision: D1 guardian authorises AND athlete accepts (both required for a minor); D2 athlete does not see sponsor price; D3 property mgr does not see individual earnings; D4 sales cannot see athlete rates; D5 athlete sees tier not factor scores. Matrix promoted to v1.0, 91 active test cases, no deferred rows. D1 and D3 remain SUBJECT TO LEGAL CONFIRMATION - D1 ties to the open guardian e-signature question, D3 to whatever school/club agreements say; confirmation can only ratify or tighten, so neither blocks.
A14: 2.5 | B14: P0-OPS-06 | C14: 0 | D14: Foundation & Decisions | E14: OPS | F14: Vendor console | G14: Register the SponsorX domain and hold the DNS | H14: Buy the domain the whole product is addressed at, and keep control of its DNS. Nothing in the programme registers one, yet three separate threads assume it exists. | I14: Done | J14: 1 | K14: 2026-09-18 | L14: 46288 | M14: management | N14: 1 | O14: None | P14: Domain registered to a BTG-controlled account with auto-renew and registrar lock on; DNS managed somewhere the team can add records; the chosen name recorded in .claude/stack-decision.md | Q14: §38, Guide §10 | R14: Raised 2026-09-18. NOT A TASK DEPENDENCY - a real-world prerequisite the Depends On column cannot express, which is why three tasks have been quietly waiting on it. Blocks: P0-OPS-03 (a Clerk PRODUCTION instance needs a domain - that row has sat In progress since 2026-09-14 for exactly this), P2-OPS-11 (HTTP error rate needs web to be reachable, and web has no public domain in either environment), and SHORT_LINK_DOMAIN for the fan QR and tracking routes, which Guide §10 says must be owned rather than a third-party shortener. FINDING 2026-09-18: sponsorx.com is ALREADY REGISTERED to someone else (AWS nameservers), as are sponsorx.io, .app, .co and .pro. The Implementation Guide assumes sponsorx.com and app.sponsorx.com throughout, so that assumption is dead and the guide needs correcting once a name is chosen. No DNS records found for: sponsorx.us, sponsorx.dev, sponsorx.team, sponsorx.network, sponsorx.sport, btgsponsorx.com, joinsponsorx.com - availability must still be confirmed at a registrar, since no DNS is not the same as unregistered. IN PROGRESS 2026-09-18, HANDED TO MANAGEMENT: the developer has no card access, so the purchase itself is management's to complete. Everything up to payment is prepared - Cloudflare account exists (Rcarr@icarrefound.org), RECOMMENDED NAME sponsorx.us at $6.50/yr (exact brand, and the .us US-nexus requirement matches NIL being US law and the US-only residency decision); fallback sponsorx.net at $11.86 if WHOIS privacy is wanted, because .us publishes registrant data with no redaction option. Registrant: Organization = the legal entity (NOT a personal name), contact rcarr@icarrefound.org, +1 443 985 3256, 2601 Pennsylvania Ave, Baltimore, MD 21217, United States. After purchase: turn auto-renew AND registrar lock on, add no DNS records yet. | 2026-09-28: sponsorx.net NOW SERVES PRODUCTION. Railway custom domain on production web (CNAME @ → c0ojxycv.up.railway.app, DNS only; TXT _railway-verify), verified, TLS certificate valid; public pages 200, portals redirect to /login, sign-in page uses the live Clerk instance (clerk.sponsorx.net). Records added in the Cloudflare dashboard by the user — the repo's CLOUDFLARE_API_TOKEN is account-scoped with no DNS permission on the zone. Row stays In progress: auto-renew + registrar lock and the stack-decision.md note are the acceptance items not yet confirmed. | 2026-10-09: DONE — every clause was met on 2026-09-23 and recorded in .claude/stack-decision.md ("The domain — sponsorx.net"): Cloudflare account, auto-renew on (2027-08-19), registrar lock on, DNS on Cloudflare. Re-checked 2026-10-09: whois clientTransferProhibited, expires 2027-09-18, NS garrett/raegan.ns.cloudflare.com, https://sponsorx.net 200. The row was left In progress by mistake.
A15: 3 | B15: P0-OPS-03 | C15: 0 | D15: Foundation & Decisions | E15: OPS | F15: Vendor console | G15: Create Clerk application (dev + production instances) | H15: Create the Clerk account with separate dev and production instances. Clerk handles login, passwords and MFA only — it never stores who belongs to which tenant or what they can do. | I15: Done | J15: 1 | K15: 2026-09-14 | L15: 46311 | M15: rcfworks | N15: 2 | P15: Both instances exist (amended 2026-10-16 by the user: the MFA half is P2-INT-02's, closed when Clerk Pro is bought at launch) | Q15: Addendum A4, §26 | R15: 2026-10-16 DONE (rcfworks, the user's decision): both instances exist and production signs in on clerk.sponsorx.net; the MFA half of the old Done-when moved to P2-INT-02, which says the same thing. | 2026-09-14: Clerk account created, DEVELOPMENT instance 'SponsorXDev' exists. Free tier, no Pro purchased - MFA is Pro-only ($20/mo) and is a launch cost per provisioning sequence step 16, not now. PRODUCTION INSTANCE DELIBERATELY DEFERRED at the user's direction: it needs a domain BTG does not have yet, and there is nothing to deploy. Task stays In progress because 'Done when' requires both instances. No Clerk SDK installed - that is code work behind the B0 no-new-dependencies rule. 2026-09-21: PRODUCTION INSTANCE CREATED, so both instances now exist. The 2026-09-14 development instance 'SponsorXDev' was gone from the ICARRE FOUNDATION workspace (Applications list empty), so the application was recreated as 'SponsorX' - one Clerk application holds BOTH instances, which is why the old Dev-suffixed name was wrong. Settings: Consumer project type (NOT B2B - B2B turns on Clerk Organizations for roles, and Addendum A4 puts tenancy and roles in Postgres); Organizations off for the same reason; sign-in Email only, with phone off per G-06 (SMS out of Phase 1) and Google off to avoid a Google Cloud OAuth consent screen no task covers. app_3JcMVfla0x1djZe95U38EcsxfRP; dev ins_3JcMVgKOWFsPxVEQknFjjWg8d8k; prod ins_3JcQVIy69lPJqNJb4XcS0PHDe2o. PRODUCTION DOMAIN sponsorx.net, VERIFIED - the five CNAMEs were written by Cloudflare Domain Connect ('Configure automatically'), not by hand, which also guarantees they are DNS-only rather than proxied: clerk -> frontend-api.clerk.services, accounts -> accounts.clerk.services, clkmail -> mail.p7c0i8jb74bp.clerk.services, clk._domainkey -> dkim1..., clk2._domainkey -> dkim2... All five confirmed resolving on 1.1.1.1 and 8.8.8.8, and SSL has since ISSUED for both clerk.sponsorx.net and accounts.sponsorx.net (Google Trust Services WE1, valid from 2026-09-21). No _dmarc TXT exists on the zone; Clerk did not add one and it is not one of the five, so it did not block verification. STILL IN PROGRESS - the 'Done when' has two halves and only the first is met. On the Hobby plan ALL THREE MFA strategies are Pro-badged: SMS verification (also unavailable because phone numbers are off, correct per G-06), Authenticator application, and Backup codes; 'Require multi-factor authentication' needs at least one strategy enabled, so it is unreachable too. This matches the 2026-09-14 finding and stays a launch cost at provisioning sequence step 16. Keys NOT captured anywhere yet - pk_live/sk_live go into Railway when P2-INT-01 installs the SDK, not into a local .env.local, per the B0 no-new-dependencies rule. 2026-09-21 DECISION: Phase 1 proceeds on the Hobby plan; the MFA half of this row's 'Done when' is deferred to launch by choice and the reasoning is recorded on P2-INT-02. | 2026-10-02 (HeckerCreatives, via Claude): NEW FINDING: the development instance is at Clerk's 100-user cap ('You have reached your limit of 100 users') — no new identity can be created: a new developer cannot sign up, and browser tests or walkthroughs needing a login they have not created before fail. Clear stale test users in the dashboard (e2e.* and old QA addresses). Not done here — deleting identities is the owner's call. | 2026-10-09 AUDIT: NOT MET — both instances exist (production clerk.sponsorx.net serves sign-in), but the production instance has NO MFA strategy enabled (authenticator app, backup codes, phone all off; second factor not required — read from clerk.sponsorx.net/v1/environment). Needs Clerk Pro, deferred to launch on 2026-09-21. Closes with P2-INT-02.
A16: 7 | B16: P0-DATA-01 | C16: 0 | D16: Foundation & Decisions | E16: DATA | F16: Document | G16: Define the metric provenance taxonomy | H16: Agree the five honesty labels for numbers: verified by API, verified by a human checking, self-reported by the athlete, estimated, or attributed. Write the rule for when each applies. | I16: Done | J16: 1 | K16: 2026-09-14 | L16: 2026-09-14 | M16: rcfworks | N16: 1 | P16: The five labels (verified-API / verified-manual / self-reported / estimated / attributed) defined with a written rule for when each applies | Q16: §22, §26 | R16: 2026-09-14 DRAFTED - documentation/SponsorX-Metric-Provenance-Taxonomy.md v0.1. Five labels defined with qualification rules and who may assign each. Adds the two rules the blueprint never gave: a DERIVED value takes the weakest of its inputs, and a ROLLUP takes the weakest of its parts; ATTRIBUTED propagates upward and sits off the strength ladder. Proposes splitting provenance into two fields - source (the five labels) and retrieval (the named path) - because the codebase already uses both conventions in one field. AUDIT FOUND 6 ISSUES, 3 high severity and 2 of those on the sponsor-facing report: F-1 campaign Total Views labelled VERIFIED_MANUAL but built from SELF_REPORTED athlete figures; F-2 Cost per View / per Engagement inherit the wrong provenance; F-3 'Primary Age' and 'Core Age' are audience demographics, out of scope for Phase 1 - remove, do not relabel. NOT DONE: 2 open decisions D1 (does VERIFIED_API cover our own instrumentation) and D2 (is the weakest-input rollup rule too harsh). No code changed. | FIXES APPLIED 2026-09-14 to src/lib/fixtures.ts: F-1 sponsor-report Total Views and Engagements VERIFIED_MANUAL -> SELF_REPORTED (rollups of athlete-reported figures); F-2 Cost per View and Cost per Engagement follow their weakest input; F-3 'Primary Age' and 'Core Age' REMOVED from property and athlete stats - demographics are out of Phase 1 scope with no retrieval path. Each edit carries a comment citing the rule. F-4/F-5/F-6 outstanding, none on the sponsor report. BUILD VERIFIED 2026-09-14: npm ci + npm run build clean (27 routes, 21 static pages), tsc --noEmit clean, lint 0 errors / 1 pre-existing warning in t/[code]/route.ts. | DONE 2026-09-14, both decisions taken. D1: a SIXTH label added - VERIFIED_SYSTEM for events SponsorX records itself (QR scan, redemption), displayed as 'measured', and it outranks VERIFIED_API because we can audit ours end to end. VERIFIED_API narrows to mean an outside platform and its name is finally accurate. Costs one Prisma enum value. D2: rollups SHOW THEIR MIX with percentages, falling back to the weakest label only where a single value must fit. Implemented: SourceLabel takes six labels; Leads Generated and Rewards Redeemed -> VERIFIED_SYSTEM (F-4). Build, typecheck and lint clean. STILL OPEN, neither on the sponsor report: F-5 property stats need stated evidence; F-6 homepage counters need the two-field source/retrieval change, which is a fixture SHAPE change and must land in the Prisma model too.
A17: 8 | B17: P0-PMO-08 | C17: 0 | D17: Foundation & Decisions | E17: PMO | F17: Document | G17: Author the Zoho module + field mapping document (§38 deliverable) | H17: Map every SponsorX record to its Zoho equivalent, field by field, and say which system wins when they disagree. Without this, the two systems quietly drift apart. | I17: Done | J17: 3 | K17: 2026-09-11 | L17: 2026-09-14 | M17: rcfworks | N17: 2 | P17: Every object in §18 mapped field-by-field, with direction and system-of-record owner per field | Q17: §18, §38 | R17: 2026-09-14 CORRECTION: row read Ready but the deliverable shipped 2026-09-11 - documentation/SponsorX-Zoho-Field-Mapping.md, all nine S18 objects mapped field by field. The Claude outputs copy never received that update. Awaiting review; one open item O-1 (Invoice/Payment Reference mapping) which is why Books credentials stay deferred. | REVIEWED + APPROVED 2026-09-14 by rcfworks. Approved WITH O-1 CARRIED. Eight of the nine S18 objects are mapped field by field; the ninth (Invoice/Payment Reference) stays open as O-1 because it depends on the Phase 1 payment policy, which is deliberately on the backburner. The eight mapped objects are what the sync gets built from, so holding the whole document for a deferred question helps nobody. Reopen if O-1 changes any mapped field.
A18: 9 | B18: P0-OPS-02 | C18: 0 | D18: Foundation & Decisions | E18: OPS | F18: Vendor console | G18: Create Cloudflare R2 account and two buckets | H18: Set up Cloudflare R2 with two buckets: one private for contracts and draft creative, one public for published video. Different security rules — they must not share a policy. | I18: Done | J18: 1 | K18: 2026-09-18 | L18: 2026-09-21 | M18: rcfworks | N18: 2 | O18: P0-PMO-02 | P18: Private and public buckets exist with separate policies; region set explicitly | Q18: Addendum A8 | R18: DONE 2026-09-21. R2 WAS NOT ENABLED AT ALL until today - this row had sat In progress since 2026-09-18 with empty notes, and the account's R2 page was still the activation screen. Worth knowing that an In progress row with no notes may mean 'not started'. Both buckets now exist, both pinned to EASTERN NORTH AMERICA (ENAM) by an explicit location hint. THE DEFAULT WOULD HAVE BEEN WRONG: Cloudflare's 'Automatic' placement offered ASIA PACIFIC on both creation screens, which would have put athlete agreements and minors' data outside the US-only residency decision (G-02) and a continent away from Railway's us-east4. Bucket location is PERMANENT, so this was a one-shot choice. Note R2's 'Specify jurisdiction' option does not help here - its only jurisdictions are eu and fedramp - so a location hint is the correct mechanism. SEPARATE POLICIES, which is the acceptance: sponsorx-private has Public Access DISABLED and no public hostname at all; sponsorx-public has the Public Development URL enabled at https://pub-7d82e60511bb4bdc9198b547f4e37fe9.r2.dev. VERIFIED FROM OUTSIDE THE ACCOUNT: the public host answers 404 from R2 itself (Server: cloudflare) for a missing object, proving it serves; the S3 API endpoint returns 400 for unsigned requests to BOTH buckets, proving that path always requires a signature. S3 API ENDPOINT for the backend's S3_ENDPOINT: https://0a10106029579f2496ccf0956745525c.r2.cloudflarestorage.com (the hex string is the Cloudflare account id; not a secret on its own). STILL TO DO, BELONGS ELSEWHERE: (1) the r2.dev URL is rate-limited and Cloudflare says explicitly it is not for production - a CUSTOM DOMAIN such as cdn.sponsorx.net should replace it before launch, and it is available today because sponsorx.net is in this same Cloudflare account. (2) A CORS POLICY on sponsorx-private is required before a phone can PUT to a presigned URL from a browser - cross-origin uploads fail without it. That belongs to P2-BE-08 once the app's real hostnames are known.
A19: 10 | B19: P0-PMO-01 | C19: 0 | D19: Foundation & Decisions | E19: PMO | F19: Document | G19: Write the Phase 1 payment policy (G-01) | H19: DECISION GATE G-01 · Phase 1 payment policy — do we track payment status only, and collect no tax IDs? — One page stating that Phase 1 only tracks whether an athlete has been paid; money moves outside the system, no tax IDs collected. Required before any code touches earnings. | I19: Done | J19: 1 | K19: 2026-09-15 | L19: 2026-09-17 | M19: rcfworks | N19: 1 | P19: One page, signed by whoever runs payouts, stating earnings-status-only and no tax ID collection | Q19: §37, Addendum A6 | R19: Drafted 2026-09-15 as documentation/SponsorX-Phase1-Payment-Policy.md v0.1 and uploaded to the review folder in Google Drive as a Doc. Codifies the answer already settled in CLAUDE.md, the build roadmap and Addendum A6: earnings STATUS only, no tax ID, no bank details, money moves outside SponsorX. Six earning states match P7-BE-01's acceptance. NOT Done: acceptance requires a signature from whoever runs athlete payouts (rcfworks or Rodney). One open item for the signer - confirm nothing in the manual payout process pushes a tax ID into the app anyway. HELD at Code review 2026-09-16: approval needed is a signature from whoever runs athlete payouts, not a technical sign-off. Everything technical in it is agreed.
A20: 12 | B20: P0-PMO-11 | C20: 0 | D20: Foundation & Decisions | E20: PMO | F20: Code | G20: Re-verify and pin all dependency versions | H20: Check every library version against the registry and pin it exactly. A minor version bump breaking the build on a Tuesday is a cost a two-person team cannot absorb. | I20: Done | J20: 1 | K20: 2026-09-15 | L20: 2026-09-15 | M20: rcfworks | N20: 1 | P20: Every package in Guide §01 re-checked against the registry and pinned exactly, no carets | Q20: Guide §01 | R20: Registry re-verified 2026-09-15: 19 Guide §01 packages + 8 package.json toolchain packages. 7 carets removed; lockfile specs refreshed. npm run build passes. Open finding for P2-BE-01: @types/node pinned 20.19.43 but runtime is Node 24.21.0.
A21: 13 | B21: P0-PMO-03 | C21: 0 | D21: Foundation & Decisions | E21: PMO | F21: Document | G21: Select transactional email provider (G-04) | H21: DECISION GATE G-04 · Transactional email provider — Resend, Postmark or SES? — Choose who sends your emails — Resend, Postmark or SES. The whole campaign loop is email, so this is not optional, but it is a small decision. | I21: Done | J21: 1 | K21: 2026-09-15 | L21: 2026-09-16 | M21: rcfworks | N21: 2 | P21: Vendor chosen; single send-interface abstraction agreed so it stays reversible | Q21: Addendum A1 | R21: Decided 2026-09-15: RESEND, behind a single internal send interface (no feature code imports the SDK; templates ours not the vendor's; sends queued not inline). Postmark is the fallback, not SES. Doc in repo + Drive review folder. Blocker noted: every provider needs DNS verification and BTG has no domain. APPROVED 2026-09-16: technical approval given, moved Code review -> Done.
A22: 14 | B22: P0-PMO-05 | C22: 0 | D22: Foundation & Decisions | E22: PMO | F22: Document | G22: Confirm the sponsor report deliverable format (G-07) | H22: DECISION GATE G-07 · Sponsor report format — is a downloadable PDF required, or is the screen enough? — Decide whether sponsors need a downloadable PDF report, or whether the on-screen report is enough. This determines whether a whole PDF-rendering job gets built. | I22: Done | J22: 1 | K22: 2026-09-15 | L22: 2026-09-16 | M22: rcfworks | N22: 3 | P22: Written answer on whether a rendered PDF is required or screen 12 suffices | Q22: Addendum A10 | R22: Recommended 2026-09-15: a FILE is required (the renewal signer often never logs in), but in Phase 1 via a PRINT STYLESHEET, not a server-rendered PDF. Separating 'sponsor needs a file' from 'system must render it unattended' is what removes the PDF worker. Provenance labels must survive into print. Doc in repo + Drive. APPROVED 2026-09-16: technical approval given, moved Code review -> Done.
A23: 15 | B23: P0-PMO-09 | C23: 0 | D23: Foundation & Decisions | E23: PMO | F23: Document | G23: Confirm the SX-01…SX-07 job catalogue economics | H23: Have the business confirm the seven job types (SX-01 to SX-07) and their pay/price bands. These numbers get loaded into the database as the rate card. | I23: Done | J23: 1 | K23: 2026-09-15 | L23: 2026-09-17 | M23: rcfworks | N23: 1 | P23: Base pay and sell price bands confirmed by the business; these seed NilJob | Q23: §5 | R23: Transcribed from §5 2026-09-15; awaiting business confirmation. FINDING: the §6 tier multiplier is applied to athlete pay but nothing protects the sell floor - at the top of the base band a Premium (1.5x) athlete costs MORE than the sell floor on ALL SEVEN jobs (SX-07 is -$375; SX-02/03/04/06 are -$25; SX-01 is exactly $0). Creator tier also goes negative on SX-07. Midpoint margins are healthy and consistent at 60-67%. Recommended fix: a floor rule (price >= athlete cost x 1.4). HELD at Code review 2026-09-16: the outstanding approval is commercial, not technical. The document reports that athlete cost exceeds the sell floor on all seven jobs at the top of the base band with a Premium athlete (SX-07 by $375, SX-01 landing at exactly $0) and recommends a floor rule of price >= athlete cost x 1.4. Closing it needs a pricing decision from whoever owns rate cards. RESOLVED 2026-09-18: the margin collision is answered by P0-PMO-13 - floor rule at 1.4x with per-tier derived sell floors; SX-07 sell floor rises to $1,050.
A24: 16 | B24: P0-PMO-10 | C24: 0 | D24: Foundation & Decisions | E24: PMO | F24: Document | G24: Confirm the six sponsor packages and their inventory | H24: Confirm the six sponsor packages — Test Drive through Season Partner — with prices, athlete counts and what is included in each. | I24: Done | J24: 1 | K24: 2026-09-15 | L24: 2026-09-17 | M24: rcfworks | N24: 1 | P24: Name, price band, athlete count and inventory JSON confirmed per package | Q24: §7 | R24: Transcribed from §7 2026-09-15; awaiting business confirmation. FINDING: no package states which NIL jobs it contains, and price is fixed while athlete count is a range - Athlete Takeover at ~$10k swings from 83% margin to -31% depending on job mix. Cannot be seeded as a priced product until inventory is expressed in job codes; proposed line items included. Also: Local Blitz and 10-Athlete Blitz overlap at $2,500/10 athletes; 'iMC/BTG feature' has no cost line. HELD at Code review 2026-09-16: the outstanding approval is commercial, not technical. Packages cannot be seeded until each names its job codes; Athlete Takeover swings 83% to -31% margin on job mix alone. Needs a pricing/inventory decision, then it can close. RESOLVED 2026-09-18: line items, the Blitz overlap and the iMC/BTG feature are all answered by P0-PMO-13; P3-BE-11 can now seed.
A25: 16.5 | B25: P0-PMO-13 | C25: 0 | D25: Foundation & Decisions | E25: PMO | F25: Document | G25: Decide the margin floor rule and tier-derived sell floors | H25: Answer the commercial question P0-PMO-09 and P0-PMO-10 documented but could not close: sponsor price may never fall below athlete cost x 1.4, and each job carries a sell floor derived from that rule at each athlete tier. | I25: Done | J25: 1 | K25: 2026-09-18 | L25: 2026-09-18 | M25: rcfworks | N25: 4 | O25: None | P25: Floor multiple, per-tier derived sell floors, the SX-07 band correction and the six packages job-code line items all recorded in a decision document | Q25: §5, §6, §7 | R25: Raised 2026-09-18 from the pricing-collision analysis. Decision: floor rule at 1.4x (workbook option 1), with per-tier sell floors derived as base-band-top x tier multiplier x 1.4 rather than negotiated by hand. SX-07 sell band floor rises $750 to $1,050 because its base top equalled its old floor. Package line items adopted as proposed in P0-PMO-10 section 3; Local Blitz narrowed to $1,500-$2,400 / 5-9 athletes so 10-Athlete Blitz is a distinct product; iMC/BTG feature becomes a non-NIL inventory line with a record. ASSUMPTION recorded in the decision document: the sell-band floor is a real floor, so the rule is a hard block, not a warning - a discountable floor makes it decorative. Enforced by P3-BE-12.
A26: 17 | B26: P0-DATA-03 | C26: 0 | D26: Foundation & Decisions | E26: DATA | F26: Document | G26: Define Content Value Score v1 factors and weights | H26: Agree the seven things that make up an athlete's score and how much each counts. Phase 1 is rules-based and manual; the algorithm comes much later. | I26: Done | J26: 1 | K26: 2026-09-15 | L26: 2026-09-16 | M26: rcfworks | N26: 1 | P26: The seven §14 factors, their weights, and the manual inputs each depends on | Q26: §14 | R26: Transcribed from §14 2026-09-15; awaiting confirmation. Seven factors totalling 100%: Engagement 25, Content Quality 20, Audience 15, Reliability 15, Geography 10, Sport/Brand Fit 10, Sponsor Performance 5. FINDING: only 20% (Reliability + Sponsor Performance) is system-observed; 50% is self-reported by the athlete being scored - so the score must never display as a bare number. Open: new-athlete handling (20% of score has no history) and who may see the score. APPROVED 2026-09-16: technical approval given, moved Code review -> Done.
A27: 19 | B27: P0-ART-01 | C27: 0 | D27: Foundation & Decisions | E27: ART | F27: Design tool | G27: Produce the ERD as a distributable diagram (§38 deliverable) | H27: Draw the database diagram so a developer can see the whole data model on one page. Needs the RBAC matrix first so the relationships are right. | I27: Done | J27: 3 | K27: 2026-09-16 | L27: 2026-09-17 | M27: rcfworks | N27: 1 | O27: P0-PMO-07 | P27: All Phase 1 tables from §20 with relationships, readable at print size | Q27: §20, §38 | R27: 2026-09-14: unblocked - its only dependency P0-PMO-07 (RBAC matrix) completed today. Status corrected Blocked -> Ready. Format decided 2026-09-16: drawn as Mermaid committed in documentation/, not in a design tool. The ERD has to stay in sync with the Prisma schema P2-BE-02 builds, so it must diff in git and regenerate; SVG/PNG exported from it satisfies "readable at print size". Claude Design is reserved for the visual ART tasks (P1-ART-05/06/07, P4-ART-01, P5-ART-01). Built 2026-09-16. Mermaid source documentation/diagrams/SponsorX-Phase1-ERD.mmd; rendered to SponsorX-Phase1-ERD.pdf, one A0 landscape sheet (prints at A0, scales to A1/A2) plus .svg. All 29 Implementation-Guide-V2 models drawn with relationships, PK/FK/UK and state columns; tenantId deliberately not drawn as an FK since it is an application-enforced scoping column (S26). COVERAGE FINDING, for P2-BE-02 to settle: five S20 tables are not modelled in V2 at all - sponsor_contacts, athlete_content_capabilities, athlete_brand_preferences, integration_connections - and roles/user_roles are collapsed into a Role[] array on User, which conflicts with S20 and CLAUDE.md and cannot carry a grant's scope or grantor. athlete_brand_preferences is the sharp one: S26's conflict check needs the athlete's restricted categories and only the sponsor side exists today. payouts is deliberately absent per G-01, not a gap. Full table-by-table audit in documentation/diagrams/README.md.
A28: 20 | B28: P0-ART-02 | C28: 0 | D28: Foundation & Decisions | E28: ART | F28: Design tool | G28: Produce the state-machine diagrams (§38 deliverable) | H28: Draw the eight lifecycle diagrams — how an application, an invitation, a campaign order, a deliverable etc. move between states. Developers build directly from these. | I28: Done | J28: 3 | K28: 2026-09-16 | L28: 2026-09-17 | M28: rcfworks | P28: All eight §21 state machines drawn; athlete onboarding and Campaign Order are the two §38 names explicitly | Q28: §21, §38 | R28: Format decided 2026-09-16: the eight state machines drawn as Mermaid stateDiagram-v2 committed in documentation/, not in a design tool. Developers build enums directly from these and P2-BE-02 consumes them, so they must diff in git alongside the schema; SVG/PNG exported for distribution. Built 2026-09-16. Eight Mermaid sources in documentation/diagrams/state-machines/; rendered to SponsorX-Phase1-State-Machines.pdf, 9 pages A3 portrait (cover + one machine per page) plus per-machine .svg. All eight S21 machines drawn including the two S38 names explicitly - Athlete Application and Campaign Order. Every unlabelled arrow is verbatim from S21. NINE arrows across six machines are labelled '(derived)': S21 gives forward paths only, leaving dead ends where a review requests changes, a payment hold is resolved or a pause is lifted. Those are proposals for P2-BE-02 to confirm when the enums and transition guards are written, not established requirements.
A29: 21 | B29: P0-DATA-02 | C29: 0 | D29: Foundation & Decisions | E29: DATA | F29: Document | G29: Define the reward event taxonomy (§38 deliverable) | H29: Define exactly what counts as a scan, a landing, a claim and a redemption. If these are fuzzy, the whole reward funnel measures nothing. | I29: Done | J29: 1 | K29: 2026-09-15 | L29: 2026-09-16 | M29: rcfworks | O29: None | P29: SCAN / LANDING / CLAIM / REDEEM defined with the exact trigger for each | Q29: §16, §38 | R29: Defined 2026-09-15. SCAN (URL requested, before render, counts every request), LANDING (200 with reward content), CLAIM (consent given + token issued, deduped per fan - it IS the consent record), REDEEM (token marked used, once forever, enforced by a partial unique index). Only REDEEM is business outcome; presenting SCAN as a result is overselling. All four are verified-api. APPROVED 2026-09-16: technical approval given, moved Code review -> Done.
A30: 23 | B30: P0-OPS-04 | C30: 0 | D30: Foundation & Decisions | E30: OPS | F30: Zoho dashboard | G30: Provision Zoho API credentials and sandbox | H30: Get Zoho API credentials and a sandbox org, so sync can be built without touching real sales data. | I30: Done | J30: 1 | K30: 2026-09-11 | L30: 2026-09-14 | M30: rcfworks | P30: Client ID, secret and refresh token issued; a sandbox or test org available for sync development | Q30: §18 | R30: In progress 2026-09-11. SPEC COMPLETE — documentation/SponsorX-Zoho-Credentials-and-Sandbox.md gives the exact OAuth scope list, the Railway env var contract and the two console runbooks. Scoped to Zoho CRM only; Books credentials deferred because the Invoice/Payment Reference mapping is still OPEN as O-1 (§7.7) and provisioning against a guess means reissuing. Scope list grants READ/CREATE/UPDATE and NO DELETE on any module, because §6.3 suspends records and never deletes them - so ZohoCRM.modules.ALL would only ever permit a violation of the mapping. REMAINING, both console click-work with no API: (1) create a Self Client at api-console.zoho.com and exchange a grant token for a refresh token, secrets going straight to Railway and never into chat, git or a ticket; (2) create the sandbox at Setup > Developer Space > Sandbox and report which sandbox types the edition offers, since a configuration-only sandbox cannot rehearse P8-INT-07's backfill against realistic volumes. The sandbox will inherit Content_Partners and the five SponsorX_ID fields, since Zoho clones from production. NOTE: licence paid_expiry is 2026-09-18 - confirm the renewal before issuing long-lived tokens. | 2026-09-14: authorising account decided - rcfworks@gmail.com, INTERIM. TWO KEYS, not a transfer (doc S9 rewritten 2026-09-14): dev key under rcfworks@gmail.com, production key created separately by Rodney under rcarr@icarrefound.org. Both valid at once; Rodney must create his own - it cannot be made for him. Dev key must never be what production runs on. Scope line flattened to paste-ready (S2.1a, 24 scopes). Sandbox type still unread - connector cannot answer, needs eyes on Setup page (S5 step 6). Railway absent, so secrets held in a password manager until sequence step 14. BLOCKER: Zoho licence paid_expiry 2026-09-18. | 2026-09-14 CREDENTIALS HALF DONE: Self Client created under rcfworks@gmail.com, all 24 scopes granted (none trimmed), refresh token issued and VERIFIED - GET /crm/v8/settings/modules returned HTTP 200 with 56 modules incl. Content_Partners. Acceptance criterion 2 met. Secrets in macOS Keychain, not Railway (P0-OPS-01 unstarted). REMAINING: sandbox (S5) - the only thing between this task and Done. | SANDBOX REQUESTED 2026-09-14: 'SponsorX-Dev', type Sample Data, provisioning (Zoho gives no ETA). Edition offers all three types - Configuration / Sample Data / Partial Data; Partial Data rejected deliberately because it copies real contacts and deals into a break-it environment (privacy call, not technical). Sandbox page is under Data Administration, not Developer Space. Web access via crmsandbox.zoho.com. STILL OPEN: sandbox token strategy (acceptance criterion 3). | DONE 2026-09-14. Sandbox SponsorX-Dev live (Sample Data) at crmsandbox.zoho.com/crm/sponsorxdev. Token strategy answered: the SAME Self Client serves both orgs - the sandbox appears under a 'Sandbox' heading on the API console Select Portal screen, and choosing it yields a separate refresh token. No sandbox token minted - nothing consumes one yet; whoever builds the sync issues it first. CAVEAT: secrets are in macOS Keychain, not Railway (P0-OPS-01 unstarted) - they move under P2-OPS-04. 2026-09-18: set back to In progress under rcfworks at the user's instruction, so the whole Railway / Clerk / backend-setup cluster reads as one owned workstream. THE WORK ITSELF IS FINISHED and was completed on 2026-09-14 - the Date Done column still holds it. Status here signals ownership of the workstream, not that the work is outstanding. CLOSED 2026-09-23. The work finished 2026-09-14; the row was held In progress from 2026-09-18 to signal ownership of the workstream, which the note itself says. Re-verified live today through the CRM connector: org 749122837 'iCARRe Foundation', type production, Zoho One Enterprise, 7 licences, paid_expiry 2026-10-18 — which clears the old blocker, recorded when expiry read 2026-09-18. Credentials: Self Client under rcfworks@gmail.com, 24 scopes, refresh token verified against /settings/modules. Sandbox: SponsorX-Dev, Sample Data, live at crmsandbox.zoho.com/crm/sponsorxdev. Deliberately NOT done and previously agreed: no sandbox refresh token minted (nothing consumes one; whoever builds the sync issues it) and no production key created (Rodney must create his own under rcarr@icarrefound.org). Secrets are in macOS Keychain and move to Railway under P2-OPS-04.
A31: 24 | B31: P0-OPS-05 | C31: 0 | D31: Foundation & Decisions | E31: OPS | F31: Zoho dashboard | G31: Create the Athlete / Content Partner custom module in Zoho | H31: Click-work in the Zoho CRM admin UI: Setup → Modules and Fields → Create Module, then add the fields the mapping document specifies. This is the only object in §18 with no home in your CRM — Accounts, Contacts, Leads, Deals, Tasks and Campaigns all exist as stock modules already. It must come AFTER P0-PMO-08, because the mapping document is what says which fields the module needs; building it first means building it twice. rcfworks@gmail.com holds the Administrator profile, so no one else's permission is required. | I31: Done | J31: 3 | K31: 2026-09-11 | L31: 2026-09-11 | M31: rcfworks | O31: P0-PMO-08 | P31: The Athlete / Content Partner custom module exists in Zoho with every field the mapping document specifies, and its API name is recorded for the sync code to use | Q31: §18, §38 | R31: 2026-09-14 CORRECTION: row read Blocked but the work was completed 2026-09-11 and the Claude outputs copy never received that update. VERIFIED LIVE 2026-09-14 via the Zoho CRM API - GET /crm/v8/settings/modules returns the Content_Partners custom module (label 'Content Partners') in org 749122837. It demonstrably exists. 2026-09-18: set back to In progress under rcfworks at the user's instruction, so the whole Railway / Clerk / backend-setup cluster reads as one owned workstream. THE WORK ITSELF IS FINISHED and was completed on 2026-09-11 - the Date Done column still holds it. Status here signals ownership of the workstream, not that the work is outstanding. CLOSED 2026-09-23. Work finished 2026-09-11, held In progress from 2026-09-18 for workstream ownership. RE-VERIFIED LIVE TODAY through the connector, field by field against §6.2.1 of SponsorX-Zoho-Field-Mapping.md: Content_Partners carries all eleven — Name, SponsorX_ID, Public_Profile_URL, Sport, Home_State, Tier, Network_Status, Approved_On, Guardian_Auth_Required, Property_Name, Last_Synced (27 fields total, 10 custom plus the display field). API name for the sync code is Content_Partners, recorded in the mapping document. Carry forward for whoever writes the sync: Zoho prepends -None- to every picklist as its empty option, so send an omitted field rather than that literal; and mandatory is a LAYOUT property that the field-creation API cannot set, so §6.2's Req column is not enforced in Zoho for SponsorX_ID, Sport and Network_Status.
A32: 25 | B32: P0-PMO-04 | C32: 0 | D32: Foundation & Decisions | E32: PMO | F32: Document | G32: Decide SMS in/out for Phase 1 (G-06) | H32: DECISION GATE G-06 · SMS in Phase 1 — in or out? Default is out. — Decide whether text messages are in Phase 1. Default is no — it adds a vendor for little gain right now. | I32: Done | J32: 1 | K32: 2026-09-15 | L32: 2026-09-16 | M32: rcfworks | P32: Written decision; if out, no TWILIO_* appears in any environment | Q32: Addendum A1 | R32: Decided 2026-09-15: SMS is OUT of Phase 1. Compliance surface (consent, opt-out, quiet hours, plus parental consent for minors) is not worth adding while the fan-PII reward funnel is still unreviewed. Already enforced - no twilio package installed by P2-BE-01, and no TWILIO_* in any environment. Returns behind the G-04 send interface as one more adapter. APPROVED 2026-09-16: technical approval given, moved Code review -> Done.
A33: 26 | B33: P0-PMO-06 | C33: 0 | D33: Foundation & Decisions | E33: PMO | F33: Document | G33: Confirm the PDF worker has a real requirement | H33: PDF generation appears nowhere in the 39-section blueprint, yet it shaped the entire hosting decision. Confirm somebody actually needs it before it shapes anything else. | I33: Done | J33: 1 | K33: 2026-09-15 | L33: 2026-09-16 | M33: rcfworks | O33: P0-PMO-05 | P33: Either a stated requirement or a decision to drop it — it shaped the hosting architecture and appears in none of the 39 sections | Q33: Addendum A10 | R33: Recommended 2026-09-15: DROP the PDF worker from Phase 1; keep the worker service itself (queue, Zoho sync, rollups, geo, image derivatives still need it). No stated requirement exists in any of the blueprint's 39 sections. Returns if a report must be emailed on a schedule, auto-attached to an invoice, or archived as an immutable artefact. APPROVED 2026-09-16: technical approval given, moved Code review -> Done.
A34: 27 | B34: P0-PMO-12 | C34: 0 | D34: Foundation & Decisions | E34: PMO | F34: Document | G34: Reconcile the stale baseline memory snapshot | H34: The baseline notes in the repo still describe an older stack (Express, Redis, MinIO). Correct them or mark them superseded so nobody builds from the wrong page. | I34: Done | J34: 1 | K34: 2026-09-15 | L34: 2026-09-16 | M34: rcfworks | P34: Initial Memory/02-confirmed-tech-stack.md either corrected to the Railway stack or explicitly marked superseded | Q34: Memory 04 | R34: Done 2026-09-15. Corrected Memory/Initial Memory/02-confirmed-tech-stack.md to the Railway stack with the superseded 2026-09-10 version kept and labelled; closed the open-discrepancy section in 04; corrected 03's reversed 'no spreadsheet is committed' rule and the 344 -> 345 task count. Left 01 and 05 alone. Record doc in repo + Drive. APPROVED 2026-09-16: technical approval given, moved Code review -> Done.
A35: 28 | B35: P1-FE-04 | C35: 1 | D35: UI Scaffold on Fixtures | E35: FE | F35: Code | G35: Extend fixtures to cover every edge state | H35: The mock data currently shows happy paths. Add the awkward cases — a minor without a verified guardian, an expired invite, a campaign under-delivering — so the screens are designed for reality. | I35: Done | J35: 1 | K35: 2026-09-11 | L35: 2026-09-14 | M35: HeckerCreatives | N35: 6 | P35: A minor athlete with unverified guardian, an expired invite, an under-delivering campaign, a held earning, a declined order and a rejected application are all representable and rendered | Q35: Roadmap A3 | R35: Six edge cases shipped on branch P1-FE-QA-PMO (spec+plan in docs/superpowers). 11-URL prod smoke matrix all pass. Awaiting review; Date Done on merge. | REVIEWED + APPROVED 2026-09-14 by rcfworks. VERIFIED not assumed: all six edge states its acceptance names are present in fixtures.ts - athleteMinor with isMinor:true and a guardian whose verifiedAt can be null, plus EXPIRED, under-delivery, HELD, DECLINED and REJECTED. The minor is a separate fixture selected by ?demo=minor rather than duplicated screens.
A36: 29 | B36: P1-ART-04 | C36: 1 | D36: UI Scaffold on Fixtures | E36: ART | F36: Design tool | G36: Design the sponsor ROI report layout for print/PDF | H36: Design the sponsor's results report at print width, so it survives being turned into a PDF rather than looking broken. | I36: Done | J36: 3 | K36: 2026-09-17 | L36: 2026-09-18 | M36: rcfworks | O36: P0-PMO-05 | P36: A print-width layout exists for screen 12 that survives PDF rendering — feeds P7-BE-05 | Q36: §9 screen 12 | R36: Designed in Claude Design from documentation/Design/sponsor-report-print/BRIEF.md. 6 Letter pages + header/footer + print chart, black on white per G-07 Option A. Establishes the V/M/S/E/A provenance marks, greyscale-safe, plus two rules for P7-BE-05: attributed carries the weaker of its two sources, and a missing figure is blank, not zero. Not yet tested through a real browser Save-as-PDF. Closed Code review -> Done 2026-09-18 at the user's instruction.
A37: 30 | B37: P1-ART-05 | C37: 1 | D37: UI Scaffold on Fixtures | E37: ART | F37: Design tool | G37: Design the QR / reward fan-facing landing treatment | H37: Design what a fan sees after scanning: the offer, the consent text, and the 'already used' and 'expired' states. | I37: Done | J37: 1 | K37: 2026-09-16 | L37: 2026-09-17 | M37: rcfworks | O37: None | P37: Consent language placed, offer presentation designed, single-use and expired states designed | Q37: §16 | R37: 2026-09-15: legal dependency removed (P0-LEG-04) — legal approvals no longer gate development. Designed 2026-09-16 in Claude Design; canvas at documentation/Design/fan-reward-landing/SponsorX Reward Landing.dc.html, source zip kept in documentation/Design/other landing pages/. Seven artboards at 390px: offer, claim/consent, claimed, returning fan, already redeemed, expired, unavailable. ACCEPTANCE MET - consent language placed (above the button, below the field, four plain sentences, nothing pre-ticked), offer presentation designed, single-use and expired states designed. VERIFIED: every text/background pairing passes WCAG AA against its real background - lowest on-ground value is white at 50% = 5.36:1, the inverted code card is 18.4:1, the primary button 6.8:1; the four colours that fail against the dark ground are dark ink on the light card and are used correctly. No JavaScript in the design (the three script tags in the .dc.html are Claude Design canvas infrastructure, not page code); only an email field and a native required checkbox; no invented statistics, no countdown, no account or app prompt. THREE PROMISES THE COPY MAKES THAT NO TASK CURRENTLY DELIVERS, for decision before P6-FE-02 wires this page: (1) 'You can unsubscribe from any of it, at any time, in one tap' - zero tasks in the 348 mention unsubscribe or opt-out. (2) 'Northbridge Coffee receives your email address' - no task hands claimed emails to the sponsor; P6-SEC-02 is fan PII purpose limitation, which is the opposite direction. (3) 'We emailed this code to you as well' - a transactional send at CLAIM, which depends on P3-INT-01 (email send interface, Ready but unbuilt) and appears in no reward task. Either the backend gains these or the consent copy is narrowed before launch; a consent promise that is not true is the worst version of this page.
A38: 31 | B38: P1-ART-06 | C38: 1 | D38: UI Scaffold on Fixtures | E38: ART | F38: Design tool | G38: Produce the marketing site visual assets | H38: Produce the imagery for the public marketing site — hero, case-study slots, package presentation. | I38: Done | J38: 3 | K38: 2026-09-17 | L38: 2026-09-17 | M38: rcfworks | P38: Hero, proof/case-study slots and package presentation art ready for the public homepage | Q38: §9 screen 1 | R38: Designed in Claude Design from documentation/Design/marketing-visuals/BRIEF.md. Seven assets: hero (desktop+phone), proof slot, case-study section, package presentation, package detail, and a flat logo redraw (6 lockups, dark+light SVG, favicon, app icon). Second pass - first invented a package model and priced in GBP; brief corrected with the Sec.7 table. Logo SVGs reference Barlow Condensed by name: outline the type before public/ use.
A39: 32 | B39: P1-ART-07 | C39: 1 | D39: UI Scaffold on Fixtures | E39: ART | F39: Design tool | G39: Design the athlete onboarding flow visuals (§11 ten sections) | H39: Design the athlete sign-up as a progressive flow across its ten sections, including the branch where a parent has to be involved. | I39: Done | J39: 3 | K39: 2026-09-17 | L39: 2026-09-18 | M39: rcfworks | N39: 1 | P39: All ten §11 sections designed as a progressive flow, including the guardian branch | Q39: §11 | R39: Designed in Claude Design from documentation/Design/athlete-onboarding/BRIEF.md; 12 screens exported as PNG to that folder. Editable .dc.html stays in the Claude Design project - needs a one-time /design-login to import. Closed Code review -> Done 2026-09-18 at the user's instruction.
A40: 33 | B40: P1-FE-05 | C40: 1 | D40: UI Scaffold on Fixtures | E40: FE | F40: Code | G40: Field-level authz audit of every fixture-backed screen | H40: Walk every screen and confirm no sponsor can see what an athlete is paid, and no athlete can see a campaign budget. This is the leak that matters most in this product. | I40: Done | J40: 1 | K40: 2026-09-12 | L40: 2026-09-14 | M40: HeckerCreatives | O40: P1-FE-04 | P40: No sponsor-facing screen renders AthleteRate.amount; no athlete-facing screen renders Campaign.budget — verified route by route | Q40: §26, Guide §04 | R40: Audit complete, zero leaks, no code changes. Record: docs/superpowers/audits/2026-09-12-p1-fe-05-field-authz-audit.md. Started ahead of P1-FE-04 review gate (dependency complete on branch). | REVIEWED + APPROVED 2026-09-14 by rcfworks. VERIFIED by grep, route by route: no athlete rate renders on any sponsor-facing or public screen, and no campaign budget renders on any athlete screen. Budget appears only in admin, sponsor and public marketing pages, which is correct. Matches the P0-PMO-07 authz matrix.
A41: 33.5 | B41: P1-FE-06 | C41: 1 | D41: UI Scaffold on Fixtures | E41: FE | F41: Code | G41: Chart entrance + idle motion across all portal dashboards | H41: Give every graph a first-view entrance animation and a quiet idle loop so the dashboards feel alive - draw-on lines, sweeping gauges and donuts, staggered bars - without changing what any chart says. | I41: Done | J41: 1 | K41: 2026-09-12 | L41: 2026-09-14 | M41: HeckerCreatives | O41: P1-FE-04 | P41: Every chart primitive (sparkline, area, gauge, donut, funnel, bars, trust meter, progress ring) animates on first viewport entry and idles subtly; static final state identical to the pre-motion render; prefers-reduced-motion and no-JS renders stay correct; charts remain server components (one small client reveal gate). | Q41: Chart motion pass 2026-09-12; dataviz motion rules | R41: Raised 2026-09-12 (user request: wow-factor graph motion, first-view + idle). New src/components/reveal.tsx + sx-viz CSS in globals.css; charts.tsx and progress-ring.tsx wired. Verified: build clean, SSR markup + compiled CSS checked on all 8 chart-bearing pages. Note: property dashboard has no charts (uses the number formatter only). Iteration 2 (same day, senior-dataviz feedback): sparkline was rendering as scattered dashes (Chromium computes dashes in screen px under non-scaling-stroke, breaking pathLength) - switched to clip-path wipe + added gradient tint and endpoint dot; funnel bars re-designed left-aligned with sequential primary ramp + accent final stage (was centered with arbitrary 2+2 color split). | REVIEWED + APPROVED 2026-09-14 by rcfworks. VERIFIED against the running dev server: 8 chart-bearing pages carry data-reveal=out and the sx-viz classes (the 8th is /admin/campaigns/[id]); globals.css ships exactly 11 sx-viz keyframes, the @media (scripting: enabled) pause gate, and 4 prefers-reduced-motion guards. Every figure in the author's claim checked out precisely.
A42: 34 | B42: P1-PMO-01 | C42: 1 | D42: UI Scaffold on Fixtures | E42: PMO | F42: Document | G42: Produce wireframes/design records for all 12 core screens (§38) | H42: Capture the built screens as the formal design record. A contractual deliverable, and cheap to do now that the screens exist. | I42: Done | J42: 3 | K42: 2026-09-12 | L42: 2026-09-14 | M42: HeckerCreatives | O42: P1-FE-04 | P42: The §38 deliverable exists — current built screens captured as the design record | Q42: §38 | R42: documentation/SponsorX-Design-Record.md + design-record/*.png (12 captures) + design-record/SponsorX-Wireframes.html (schematic wireframes, all 12 screens). | REVIEWED + APPROVED 2026-09-14 by rcfworks. Accepted - documentation/SponsorX-Design-Record.md exists and captures the built screens as the S38 design record.
A43: 35 | B43: P1-QA-01 | C43: 1 | D43: UI Scaffold on Fixtures | E43: QA | F43: Code | G43: Walk the full §39 loop on fixtures and log every gap | H43: Click through the entire business loop on mock data and write down every place it breaks or dead-ends. | I43: Done | J43: 1 | K43: 2026-09-12 | L43: 2026-09-14 | M43: HeckerCreatives | O43: P1-FE-04 | P43: A written pass/fail list for all 11 loop steps; every gap is either fixed or filed as a task | Q43: §39 | R43: QA checklist (Word): documentation/SponsorX-Stage1-QA-Checklist.docx. Formal QA report: documentation/SponsorX-Stage1-QA-Report.md (23/23 cases pass, defect log D-01..D-11). 11/11 loop steps pass; 3 silent unwired CTAs annotated. Record: docs/superpowers/audits/2026-09-12-p1-qa-01-loop-walk.md | REVIEWED + APPROVED 2026-09-14 by rcfworks. Accepted on the audit record (docs/superpowers/audits/2026-09-12-p1-qa-01-loop-walk.md): 11/11 loop steps representable, 3 gaps found and fixed (athlete-side unwired CTAs).
A44: 36 | B44: P1-QA-02 | C44: 1 | D44: UI Scaffold on Fixtures | E44: QA | F44: Code | G44: Accessibility audit of all routes | H44: Check colour contrast, keyboard navigation, and that the fan redeem page works with JavaScript switched off. | I44: Done | J44: 3 | K44: 2026-09-12 | L44: 2026-09-14 | M44: HeckerCreatives | O44: P1-FE-04 | P44: Contrast AA in both themes; keyboard navigation complete; redeem page passes without JS | Q44: §16 | R44: QA checklist (Word): documentation/SponsorX-Stage1-QA-Checklist.docx. Formal QA report: documentation/SponsorX-Stage1-QA-Report.md (23/23 cases pass, defect log D-01..D-11). AA both themes via token fixes (faint, light accent-soft, CTA ink); keyboard + no-JS redeem verified. Record: ...p1-qa-02-accessibility-audit.md | REVIEWED + APPROVED 2026-09-14 by rcfworks. No-JS redeem page VERIFIED - /r/[token] returns HTTP 200 with server-rendered content and no JavaScript. Contrast AA and keyboard navigation accepted on the author's record; both need a browser to measure and their CDP method is more rigorous than a shell can manage.
A45: 37 | B45: P1-QA-03 | C45: 1 | D45: UI Scaffold on Fixtures | E45: QA | F45: Code | G45: Responsive audit — phone, tablet, desktop | H45: Check every screen on a phone. The athlete portal and redeem page are phone-first in real use. | I45: Done | J45: 1 | K45: 2026-09-12 | L45: 2026-09-14 | M45: HeckerCreatives | O45: P1-FE-04 | P45: No horizontal scroll at 360px; portal navigation usable on phone | Q45: §9 | R45: QA checklist (Word): documentation/SponsorX-Stage1-QA-Checklist.docx. Formal QA report: documentation/SponsorX-Stage1-QA-Report.md (23/23 cases pass, defect log D-01..D-11). 29 routes fit 360px after 4 min-w-0 fixes (implicit mobile grid columns); drawer verified on all portals. Record: ...p1-qa-03-responsive-audit.md | REVIEWED + APPROVED 2026-09-14 by rcfworks. No static culprits found - viewport meta correct, no min-width above 360px in globals.css, charts and insight-carousel both wrapped in overflow-x containers. Actual scrollWidth at 360px accepted on the author's CDP measurement.
A46: 38 | B46: P2-OPS-01 | C46: 2 | D46: Platform Foundations | E46: OPS | F46: Vendor console | G46: Create the Railway project with three services | H46: Create three services in one Railway project — the web app, the background worker, and Postgres — talking privately to each other with the database never exposed to the internet. | I46: Done | J46: 3 | K46: 2026-09-18 | L46: 2026-09-18 | M46: rcfworks | N46: 5 | O46: P0-OPS-01 | P46: web, worker and postgres exist in one project; web and worker reach Postgres over the internal hostname; the database has no public exposure | Q46: Guide §10 | R46: Started 2026-09-18 via the Railway CLI. DONE: three services exist in project sponsorX - web (renamed from sponsorX_dev, e004424e), worker (70a9ade0, same repo), Postgres (19fb0884). web and worker both carry DATABASE_URL=${{Postgres.DATABASE_URL}}, which resolves to postgres.railway.internal:5432 - private networking, never a public URL. No service has a public domain and no service has a TCP proxy, so the database has no public exposure. OUTSTANDING: (1) web and worker have not been deployed since the variable was set, so internal connectivity is configured but not yet proven at runtime; (2) THE POSTGRES VOLUME WAS PROVISIONED IN 'sfo' - Railway defaults a new service to sfo and the region pin only took effect after the volume existed. A volume is region-bound, so this needs the empty database deleted and recreated with the region pinned first. worker deployed correctly in us-east4-eqdc4a; web's running deployment is still sfo. 2026-09-18 region fix: rather than deleting the Postgres service, the VOLUME was swapped - volumes cannot be moved (VolumeInstanceUpdateInput has no region) but CAN be created with one (VolumeCreateInput does). Old volume 18d938bd (sfo) deleted, new volume 93e71f6d 'postgres-volume-Kkpa' created at /var/lib/postgresql/data in us-east4-eqdc4a, READY and attached to the Postgres service. The database was empty, so nothing was lost. CAVEAT: the old sfo volume still appears in the project listing detached (serviceId null) after volumeDelete returned true twice - check it is gone after the Postgres redeploy, or remove it in the console. Remaining for this task: redeploy Postgres, web and worker. CLOSED 2026-09-18: all three services deployed SUCCESS in us-east4-eqdc4a, Postgres on the new us-east4 volume. web and worker both resolve DATABASE_URL to postgres.railway.internal:5432; no service has a public domain and none has a TCP proxy. NOTE ON 'REACH': the internal address is configured and both services have deployed with it, but nothing in the repo opens a database connection yet, so live connectivity is proven by P2-BE-02's first migration rather than here. NOTE: `railway deployment redeploy` replays the PREVIOUS deployment's manifest and ignores config changes - the serviceInstanceRedeploy mutation is what picks up a new region. web sat in sfo through one pointless redeploy before that was understood. OPEN: orphaned sfo volume 18d938bd still listed detached after two volumeDelete calls and a full redeploy - remove it in the console. REBUILT IN STAGING 2026-09-18 at the user's instruction - 'everything needs to be a staging first, then when all is done we put it in production'. The spine now lives in the STAGING environment: web (e004424e), worker (ca264963) and Postgres (f345dcfb, volume 69f06876 in us-east4-eqdc4a), all deployed SUCCESS in us-east4-eqdc4a, both app services resolving DATABASE_URL to postgres-hhot.railway.internal:5432, no public domain on any service. The production copies were DELETED, not idled, because Railway service names are unique per PROJECT not per environment, so an idle production 'Postgres' would have forced an awkward name on the real one. Production now holds only web, with AUTO-DEPLOY TURNED OFF so a merge to main no longer ships it. Promotion is a deliberate act: recreate these services in production from the proven staging config. NOTE: the staging database's private hostname is postgres-hhot.railway.internal - Railway fixes the internal domain at creation from the generated name, and renaming the service to 'Postgres' afterwards does not change it. 2026-09-18: set back to In progress under rcfworks at the user's instruction, so the whole Railway / Clerk / backend-setup cluster reads as one owned workstream. THE WORK ITSELF IS FINISHED and was completed on 2026-09-18 - the Date Done column still holds it. Status here signals ownership of the workstream, not that the work is outstanding. | 2026-10-02 (HeckerCreatives, via Claude): Closed: the work was finished on 2026-09-18 (Date Done) and the row was held In progress only to show ownership of the Railway workstream. Topology has since changed by decision (Addendum B, 2026-09-21): web, api (API + worker in one process) and Postgres; web no longer has a database at all. Not re-checked in the Railway console today — no CLI on this machine; the 2026-09-24 log verified api.railway.internal and /health in both environments.
A47: 39 | B47: P2-BE-02 | C47: 2 | D47: Platform Foundations | E47: BE | F47: Code | G47: Author the full Prisma schema + initial migration | H47: Write the entire database structure in one go: every table, every lifecycle state, a tenant marker on everything. The single largest task in the project and almost everything depends on it. | I47: Done | J47: 5 | K47: 2026-09-18 | L47: 2026-09-18 | M47: rcfworks | N47: 12 | O47: P2-OPS-01, P0-PMO-07 | P47: Every §20 table modelled; tenantId on everything; all eight §21 state machines as enums; external IDs + lastSyncOrigin + lastSyncHash on every Zoho-touched model | Q47: §20, §21, Guide §03 | R47: Started 2026-09-18. Startability checked: authoring a migration normally needs a live connection, and postgres.railway.internal is unreachable from a developer machine by design. It works anyway - `prisma migrate diff` generates the migration SQL offline from the schema, and the `prisma migrate deploy` pre-deploy step wired in P2-OPS-03 applies it on the next release. Inputs all in-repo: the P0-ART-01 ERD, the eight state machines in documentation/diagrams/state-machines/, the P0-PMO-07 RBAC matrix and Guide §03. DELIVERED 2026-09-18: prisma/schema.prisma - 29 models, 13 enums; initial migration at prisma/migrations/20260918060000_init/migration.sql - 29 tables, 31 foreign keys, 55 indexes, generated offline with `prisma migrate diff --from-empty --to-schema` (note: --to-schema-datamodel was REMOVED in Prisma 7, the flag is now --to-schema). `prisma validate` passes, the client generates, npm run build compiles. ALL FOUR ACCEPTANCE CLAUSES VERIFIED PROGRAMMATICALLY: 29/29 models carry tenantId except Tenant itself; all eight §21 state machines present as enums and checked value-by-value against the .mmd files; sync markers on all four Zoho-touched models (Sponsor, Athlete, Property, Campaign) where the guide had given them to only two. BUG FOUND IN THE GUIDE: Implementation Guide V2 §03 gives Athlete both `state String?` (the US state) and `state_ AthleteState @map("state")` (the lifecycle). They collide on one column and the schema WILL NOT COMPILE as published. Resolved here by naming geography `stateCode` on Athlete, Property and CampaignBrief, leaving `state` to mean the lifecycle enum on every model. The guide still carries the broken version and should be corrected. ALSO ADDED beyond §03, from decisions taken since it was written: NilJob.sellFloorEmerging/Creator/Premium and SponsorPackage lineItems + athleteCountMin/Max, both from P0-PMO-13; an AthleteTier enum replacing a free-text tier string. AT CODE REVIEW because the migration has never been applied to a database - `migrate deploy` runs on the next release to main and that is the first time it will be executed anywhere. PROVEN 2026-09-18 07:27 UTC: merged to main as PR #7 (915c9a98); the staging deploy's pre-deploy step ran `npx prisma@7.10.0 migrate deploy` against postgres-hhot.railway.internal and logged '1 migration found', 'Applying migration 20260918060000_init', 'All migrations have been successfully applied.' Deployment 08cd56a3 SUCCESS. Every acceptance clause is now met AND executed; status left at In progress only because the user asked the whole backend cluster to read that way. 2026-09-21 THE MIGRATIONS ARE APPLIED. The 2026-09-18 note said 'the migration has never been applied to a database'; that is no longer true. All four ran in the staging pre-deploy: the 29-table init, the partial indexes, the athlete application fields and EmailSendLog. The risky one applied cleanly - 20260921120000 adds email TEXT NOT NULL with no default, which works only while Athlete is empty, and it was.
A48: 40 | B48: P2-INT-01 | C48: 2 | D48: Platform Foundations | E48: INT | F48: Code + console | G48: Replace mock-auth with Clerk | H48: Swap the fake sign-in for real Clerk authentication. Clerk proves who you are; your own database decides what you can do. | I48: Done | J48: 3 | K48: 2026-09-18 | L48: 2026-09-21 | M48: rcfworks | N48: 2 | O48: P0-OPS-03, P2-BE-02 | P48: Real sign-in works; User.clerkId mirrors the Clerk identity; no tenant or role data lives in Clerk Organizations or session claims | Q48: Addendum A4 | R48: 2026-09-18: moved Blocked -> In progress and assigned to rcfworks at the user's instruction, to show the backend/Railway/Clerk cluster as actively owned. THE BLOCKING IS STILL REAL - this row depends on P0-OPS-03, P2-BE-02. Read Depends On, not Status, to find what can actually be started. 2026-09-21 IMPLEMENTED, moved to Code review - the code is complete but one half of the 'Done when' is UNVERIFIED. Real sign-in works and is proven: all four portals and their nested pages 307 to /login when signed out, while /, /packages, /join, /map and the fan surfaces /r/[token] and /t/[code] stay open, as §16 requires. NOT proven: 'User.clerkId mirrors the Clerk identity' - the mirror needs a database and there is no local Postgres by design (Railway is private-networking only, no docker or psql on the machine), so it can only be exercised on a staging deploy. DESIGN NOTES THAT WILL OUTLIVE THIS ROW. (1) The file is src/proxy.ts, NOT middleware.ts: Next 16 deprecated the middleware file convention and renamed it, the exported function must be named proxy, and the edge runtime is unsupported under the new name. Clerk 7.9.2 already handles this - suggestMiddlewareLocation() looks for both names when Next is 16 or higher. (2) ROUTE PROTECTION IS NOT IN THE PROXY. Clerk deprecated createRouteMatcher() in this version with the reasoning that middleware path matching 'can diverge from how Next.js routes requests and leave protected resources reachable'. Protection therefore sits in each portal's layout.tsx via auth.protect(), which wraps every page beneath it so a new route cannot bypass it - and that is exactly where P2-BE-04's requireActor() belongs. The proxy now only attaches Clerk's request context. (3) NEXT_PUBLIC_CLERK_SIGN_IN_URL=/login is REQUIRED as an environment variable, not a ClerkProvider prop: Clerk's own note on auth() says server-side redirect URLs can only come from env vars. Without it, signed-out visitors are bounced to Clerk's hosted portal on accounts.dev instead of our designed screen. P2-OPS-04 must set it in Railway. (4) /portal is the post-sign-in router and the ONLY route that touches the database; every other screen still runs on fixtures, which is what keeps the app buildable and runnable with no DATABASE_URL. (5) THE MIRROR NEVER INVENTS A TENANT. A Clerk identity with no matching User row is authenticated but unprovisioned and is told so, because Phase 1 is a managed marketplace where access is granted by BTG staff rather than self-served. Linking is by verified email: an admin creates the User row ahead of time and first sign-in claims it by writing the real clerkId. (6) src/server/db.ts now builds the Prisma client on FIRST USE rather than on import - next build imports every route module to collect its config, so the eager client turned a missing DATABASE_URL into a build failure rather than a query failure. mock-auth.ts and login-form.tsx are deleted; the login screen keeps its two-panel design with Clerk's <SignIn routing='hash'> in the left panel. CLOSED 2026-09-21. The signed-in path was verified by the user on staging: /portal forwarded to /admin, which is only reachable if the mirror found the seeded row, wrote the real clerkId over the placeholder and read BTG_ADMIN back out of Postgres. All three clauses of the 'Done when' now hold - real sign-in works, User.clerkId mirrors the Clerk identity, and no tenant or role data is written to Clerk Organizations or session claims. 2026-09-21 PASSWORD RESET CONFIRMED WORKING on staging, end to end: Clerk emailed a code, accepted a new password and created a session, with no code of ours involved - <SignIn routing='hash'> drives the whole flow in the URL fragment. This also settles that the instance uses PASSWORDS rather than email codes. One thing seen and diagnosed: after the reset the page hung on 'Signing you in'. The cause was a STALE BROWSER TAB - 'Failed to find Server Action ... from an older or newer deployment' - because web had just been redeployed under an open tab. Not an API or networking fault; the API log showed no request had arrived at all. Any Next.js redeploy does this to open tabs; a hard reload clears it.
A49: 41 | B49: P2-BE-04 | C49: 2 | D49: Platform Foundations | E49: BE | F49: Code | G49: Build actor.ts and scope.ts | H49: Two files that answer 'who is asking' and 'what are they allowed to see'. Every database query in the codebase goes through them. Retrofitting this later is the most expensive mistake available. | I49: Done | J49: 3 | K49: 2026-09-18 | L49: 2026-09-21 | M49: rcfworks | N49: 3 | O49: P2-BE-02, P2-INT-01 | P49: requireActor() resolves a Clerk user to a Postgres tenant + roles; every scope function defaults to DENY; no query in the codebase bypasses them | Q49: Addendum A4, Guide §04 | R49: 2026-09-18: moved Blocked -> In progress and assigned to rcfworks at the user's instruction, to show the backend/Railway/Clerk cluster as actively owned. THE BLOCKING IS STILL REAL - this row depends on P2-BE-02, P2-INT-01. Read Depends On, not Status, to find what can actually be started. 2026-09-21 IMPLEMENTED, moved to Code review. src/server/actor.ts (requireActor), scope.ts, authz-policy.ts, portal.ts and errors.ts; deployed to staging and verified. THE KEY DESIGN CHOICE: policy and filter are SEPARATE. authz-policy.ts is a complete transcription of the agreed RBAC matrix as pure data - 32 resources x 12 roles x 3 actions, no Prisma, no imports that can drift - which is what lets P2-SEC-01 assert the whole matrix with no database and lets a reviewer diff it against the document line by line. scope.ts turns a scope token into a Prisma where fragment, and ONLY for resources something actually queries (today: user, tenant, auditLog). Writing 30 speculative where fragments for models nothing reads would be authorisation code whose correctness nobody can check, and wrong authorisation code is worse than absent because it looks like protection. Each B-milestone adds its builder with the model in front of it. DENY FAILS CLOSED TWICE: an unlisted resource/role/action denies, AND a resource whose builder is unwritten THROWS rather than returning {} - in Prisma an empty where matches EVERY ROW, so 'no restriction' and 'no access' would otherwise be the same object. That is the single most plausible way to leak a whole tenant. The three cells the matrix defers to its own decisions D1 and D3 resolve to a denial, not an allowance - widening later is safe, narrowing later is a regression someone has already built on. BUG FOUND AND FIXED DURING THE WORK: scopeFor() seeded its accumulator as 'deny' and only replaced on strictly-greater breadth, and 'deferred' and 'deny' are both zero-breadth, so 'deferred' could never surface. Access was still correctly refused but the distinction was unreachable. THIS ALSO CLOSES THE HOLE P2-INT-01 LEFT: the portal layouts checked authentication only, so any signed-in Clerk identity - including a stranger who self-registered - could open the admin workspace. requirePortalAccess() now admits only the roles a portal is for and forwards a wrong-portal visit to the actor's own portal instead of dead-ending. A failure that is neither unauthenticated nor unprovisioned is RETHROWN: an early draft caught everything and would have reported a database outage to the user as 'your account isn't set up yet'. KNOWN SMALL REGRESSION: the sign-in redirect no longer carries ?redirect_url=, because our own redirect('/login') replaced Clerk's auth.protect(). After signing in a user lands on their portal rather than the page they originally asked for. Cosmetic, worth picking up in a polish pass. NOT IN THIS TASK: the field-level rules in matrix §7.1/§7.2 (campaign.budget hidden from athletes, nilJob.athleteBasePay from sponsors) are P2-SEC-02, and 'no query bypasses them' is the bare-findMany lint rule in P2-OPS-06. Verified anonymously on staging: all four portals and /portal 307 to /login, public surface and /r unaffected, no runtime errors. CLOSED 2026-09-21. Verified by the user on staging: /portal forwarded to /admin, and /athlete bounced back to /admin rather than rendering - so requireActor() resolves a Clerk user to a Postgres tenant and roles, and the role gate refuses rather than admitting any signed-in identity. Scope functions default to DENY structurally (verified exhaustively by P2-SEC-01's 1,152-pair suite). ON THE THIRD CLAUSE, 'no query in the codebase bypasses them': one query does, by necessity - the actor bootstrap in identity.ts reads the User row by clerkId, and it CANNOT go through scope.ts because scope.ts needs an actor that does not exist yet. That is the single documented exception and it is inherent to any resolve-the-actor step. Every other database read goes through whereFor(). P2-OPS-06's bare-findMany lint rule is what keeps that true as the codebase grows. 2026-09-21 RELOCATED TO THE BACKEND, decision taken by the user the same day. policy/scope/errors/actor now live in backend/src/auth and the frontend no longer reads Postgres at all. THE DECIDING ARGUMENT: /api/v1 is reached by the portals, by §8's API service account and by INFINEX on equal terms, so authorisation enforced in the Next app covered exactly one caller of three. The secondary argument was two Prisma clients - one per workspace - where the forgotten enforcement point is the leak and will not be the one under test. New shape: resolveActor() is pure domain logic over Postgres (testable with no HTTP and no Clerk), requireActor() is Express middleware, and backend/src/auth/clerk.ts is the ONLY backend file that knows Clerk exists, because stack-decision.md keeps a live revisit trigger on Clerk. GET /api/v1/me returns tenant and roles and also completes a first sign-in, since claiming a provisioned row happens inside resolveActor(). @clerk/backend was already in the tree via @clerk/nextjs but is now DECLARED in backend/package.json - relying on a transitive dependency is how a build breaks on someone else's upgrade. portalFor() stayed in the frontend: which workspace to render is routing, not authorisation. The 1,152-pair suite moved to backend/tests and cost nothing to move, because P2-BE-04 kept the matrix as data. FOLLOW-UP LEFT OPEN: frontend/src/server/{db,audit,outbox}.ts are now orphaned - nothing imports them - but they are still a second Prisma client in the frontend, which is the hazard this move exists to remove. They are P2-BE-05/P2-BE-06 work, so they should follow in their own change rather than be swept up here.
A50: 42 | B50: P2-BE-05 | C50: 2 | D50: Platform Foundations | E50: BE | F50: Code | G50: Build the outbox + pg-boss drain | H50: Background jobs stored in Postgres rather than Redis. The key property: a job is saved in the same transaction as the thing that caused it, so neither can exist without the other. | I50: Done | J50: 3 | K50: 2026-09-18 | L50: 2026-09-18 | M50: rcfworks | N50: 7 | O50: P2-BE-02 | P50: enqueue() writes an outbox row in the caller's transaction; the worker drains with FOR UPDATE SKIP LOCKED; two worker instances never double-process a row | Q50: Addendum A3, Guide §05 | R50: 2026-09-18: moved Blocked -> In progress and assigned to rcfworks at the user's instruction, to show the backend/Railway/Clerk cluster as actively owned. THE BLOCKING IS STILL REAL - this row depends on P2-BE-02. Read Depends On, not Status, to find what can actually be started. DELIVERED 2026-09-18, closed straight to Done at the user's instruction (code review skipped). src/server/outbox.ts - enqueue(tx, tenantId, name, payload) takes a TransactionClient, not the db client, so writing outside the caller's transaction is awkward to do by accident; JobName is a string union so a typo is a compile error rather than a job nothing handles. src/server/db.ts - the Prisma 7 client built on the PrismaPg driver adapter, cached on globalThis in development because a fresh client per Next hot reload exhausts the pool in minutes. worker/index.mts - pg-boss boot (its schema installs HERE and only here, Guide §10 rule 3) plus a 1s drain doing SELECT ... FOR UPDATE SKIP LOCKED LIMIT 100, send, then mark dispatched. THREE THINGS WORTH KNOWING. (1) The worker is .mts, not .ts: the package is type=commonjs and the generated Prisma client is ESM-syntax TypeScript, so plain node cannot load it - Next bundles, this process does not. .mts is always ESM, Node 24 strips types natively, no build step and no bundler. (2) pg-boss 12 is ESM and exports PgBoss as a NAMED export; `import PgBoss from 'pg-boss'` fails at load with 'does not provide an export named default'. (3) DELIVERY IS AT-LEAST-ONCE - the drain sends then marks, so a crash between the two re-sends on the next tick. Deliberate: marking first risks losing a job, and a duplicated Zoho push is recoverable where a dropped one is silent. EVERY HANDLER MUST BE IDEMPOTENT. New pinned dependencies: @prisma/adapter-pg 7.10.0, pg 8.23.0, @types/pg 8.23.1 (dev) - exact versions, no carets, per P0-PMO-11. No job handlers are registered yet; each lands with the feature that needs it, and until then jobs queue visibly rather than dropping. Railway start command updated to `node worker/index.mts`; build and typecheck pass.
A51: 43 | B51: P2-BE-03 | C51: 2 | D51: Platform Foundations | E51: BE | F51: Code | G51: Add the partial indexes Prisma will not create | H51: A handful of database indexes Prisma cannot generate — including the one that makes a reward physically impossible to redeem twice. | I51: Done | J51: 1 | K51: 2026-09-18 | L51: 2026-09-18 | M51: rcfworks | N51: 1 | O51: P2-BE-02 | P51: prisma/sql/ holds them; critically the partial unique index that makes single-use reward redemption race-safe | Q51: Guide §03 | R51: 2026-09-18: moved Blocked -> In progress and assigned to rcfworks at the user's instruction, to show the backend/Railway/Clerk cluster as actively owned. THE BLOCKING IS STILL REAL - this row depends on P2-BE-02. Read Depends On, not Status, to find what can actually be started. DELIVERED 2026-09-18: prisma/sql/ holds the three indexes with a README, and migration 20260918080000_partial_indexes applies them. reward_single_redeem is the one that carries real risk - a UNIQUE index on RewardEvent(tokenId) WHERE type='REDEEM'. Two fans scanning the same code in the same millisecond at an event is not hypothetical, and an application-level 'already redeemed?' check reads before it writes and loses that race every time; the correct implementation is to attempt the insert, catch the unique violation and render 'already used'. outbox_pending keeps the drain index the size of the backlog rather than of all history. SCHEMA CHANGE MADE HERE: CampaignInvite's full @@unique([campaignId, athleteId, jobId]) was DROPPED and replaced by a plain index plus the partial unique invite_one_open over ('INVITED','VIEWED'). The full constraint was too strong - it forbade re-inviting an athlete whose previous invitation had EXPIRED or been DECLINED, which is ordinary business and which §21 treats as a normal terminal state. The rule actually wanted is 'no two live offers for the same work'. `prisma validate` passes, client regenerates, build compiles; the migration has not run yet - it applies on the next deploy to main. PROVEN 2026-09-18 08:44 UTC: merged as PR #8 (a0ddb357); the staging pre-deploy logged '2 migrations found', 'Applying migration 20260918080000_partial_indexes', 'All migrations have been successfully applied.' Deployment e40f2e89 SUCCESS. All three partial indexes and the CampaignInvite constraint change are live in the staging database. Verified 2026-09-22: prisma/sql/ holds invite_one_open.sql, outbox_pending.sql and reward_single_redeem.sql. The named critical one is a genuine PARTIAL UNIQUE index — CREATE UNIQUE INDEX ... WHERE type = 'REDEEM' — which is what makes single-use redemption race-safe in the database rather than in a query.
A52: 44 | B52: P2-BE-08 | C52: 2 | D52: Platform Foundations | E52: BE | F52: Code | G52: Build the R2 presign module | H52: Generate temporary upload links so a phone can send video straight to Cloudflare rather than through your server. Large uploads through a Node server is how a busy content day becomes an outage. | I52: Done | J52: 3 | K52: 2026-09-18 | L52: 2026-09-21 | M52: rcfworks | N52: 2 | O52: P0-OPS-02 | P52: presignUpload() issues short-TTL signed PUTs against the private bucket; public-bucket reads need no signing; every private grant is audited | Q52: Addendum A8, Guide §11 | R52: 2026-09-18: moved Blocked -> In progress and assigned to rcfworks at the user's instruction, to show the backend/Railway/Clerk cluster as actively owned. THE BLOCKING IS STILL REAL - this row depends on P0-OPS-02. Read Depends On, not Status, to find what can actually be started. 2026-09-21 PRESIGNING PROVEN AGAINST REAL R2, not just MinIO. An R2 Account API token (Object Read & Write, scoped to the two buckets, no expiry, no IP filter) is in the repo-root .env, which the backend reads via --env-file-if-exists. Results: presigned PUT with a 900s TTL uploaded through the signed URL (200); presigned GET read the same object back (200, exact content); THE SAME OBJECT UNSIGNED WAS REFUSED - HTTP 400 InvalidArgument/Authorization with the file's contents withheld, confirmed by writing a canary string and checking the error body does not contain it; an upload to the public bucket was then readable over the r2.dev host WITH NO SIGNATURE (200). That is the acceptance's 'short-TTL signed PUTs against the private bucket; public-bucket reads need no signing' demonstrated end to end. All probe objects deleted afterwards; both buckets verified empty. NOTE ON THE 400: R2 answers an unsigned S3 request with 400, not 401/403. A test asserting only on 401/403 reports a false leak - assert on whether the CONTENT comes back, which is the property that matters. TOKEN SCOPE, DELIBERATE: Object Read & Write cannot edit bucket configuration, so it cannot set the CORS policy and cannot delete a bucket. That is the right trade for a credential that will live unattended in Railway. CORS is therefore a dashboard paste or a short-lived admin token, not a widening of this one. STILL OUTSTANDING FOR THIS ROW: (1) the audit clause - 'every private grant is audited' - now reachable because P2-BE-06's helper moved to backend/src/db/audit.ts, but the presign path does not call it yet; (2) the CORS policy on sponsorx-private, without which a browser PUT to a presigned URL fails as a cross-origin request; (3) R2 credentials are not yet in Railway (P2-OPS-04). DONE 2026-09-21. All three clauses of the 'Done when' now hold. SHORT-TTL SIGNED PUTS: 15 minutes, long enough for a phone on a poor connection, short enough that a leaked URL is worth little. PUBLIC READS NEED NO SIGNING: verified over the r2.dev host with no credential. EVERY PRIVATE GRANT IS AUDITED - and the way that is made true matters: the raw presigners are NO LONGER EXPORTED, so the private bucket is reachable only through presignPrivateUpload/presignPrivateDownload, both of which demand an actor and write the audit row first. Removing the unaudited path is what makes the rule hold; remembering to call the audit is not. THE GRANT IS THE AUDITABLE EVENT, not the upload. The browser talks straight to R2, so the server never observes the PUT - the last moment anything can be recorded is when the credential is handed over. The row records bucket, key, contentType and TTL, and DELIBERATELY NOT THE SIGNED URL: that string IS the credential, and copying it into a table every BTG_ADMIN can read would turn the audit log into a set of live keys to the private bucket. There is a test asserting the URL never appears in the audit payload. FAILS CLOSED: the audit runs inside a transaction before the URL is returned, so if the audit write fails no credential is issued. An unlogged grant is precisely what the acceptance forbids. Also added assertSafeKey - a key containing .. or a leading slash is refused, because keys are built partly from user-supplied filenames and writing outside the intended prefix is the same failure as traversal by another mechanism. PUBLIC GRANTS ARE NOT AUDITED, deliberately: the bucket is world-readable by design, so a grant to write published assets discloses nothing the CDN does not already serve. CORS on sponsorx-private is live - preflight verified from all three allowed origins (204, echoing the origin, PUT+GET) and REFUSED for an unlisted origin (403). No wildcard: a presigned URL is a bearer credential in a query string, and '*' would let any site holding one use it from a victim's browser. TESTS: backend/tests/storage.grants.test.ts, 7 tests, no database and no network - Prisma and the presigner are mocked because the rule is what is under test, not AWS's signing. MUTATION-CHECKED: removing the audit call from the upload path makes 2 of them fail, so they catch the regression they exist for rather than merely passing. Backend suite now 26. STILL OUTSTANDING BUT NOT THIS ROW: R2 credentials are not yet in Railway (P2-OPS-04), and the r2.dev public hostname should become a custom domain such as cdn.sponsorx.net before launch.
A53: 45 | B53: P2-OPS-03 | C53: 2 | D53: Platform Foundations | E53: OPS | F53: Vendor console | G53: Wire migrations as a pre-deploy release step | H53: Database migrations run as a release step just before new code goes live — never during the build, which runs far more often. | I53: Done | J53: 1 | K53: 2026-09-18 | L53: 2026-09-18 | M53: rcfworks | N53: 1 | O53: P2-OPS-01 | P53: prisma migrate deploy runs as Railway's pre-deploy command before the new version takes traffic — never in the build step | Q53: Guide §10 | R53: 2026-09-18. preDeployCommand set on staging web: ['npx prisma migrate deploy']. The field takes an ARRAY, and a single shell string in that array - an argv-style array is rejected with 'Invalid input'. Set on web, not worker, so one service owns schema migration and two cannot race. AT CODE REVIEW because it has not run yet: the first execution happens on the next deploy to main, and that is also when we learn whether `prisma migrate deploy` exits 0 with no migrations directory present. If it exits non-zero the deploy is blocked and the previous version keeps serving - which is the correct failure, and the reason this was set in staging first. CLOSED 2026-09-18 at the user's instruction - no problem was encountered; the configuration is in place and verified by reading it back from the Railway API. What remains is execution, not correctness: these commands first RUN on the next deploy of main, and that cannot be brought forward without deploying. 2026-09-18: set back to In progress under rcfworks at the user's instruction, so the whole Railway / Clerk / backend-setup cluster reads as one owned workstream. THE WORK ITSELF IS FINISHED and was completed on 2026-09-18 - the Date Done column still holds it. Status here signals ownership of the workstream, not that the work is outstanding. PROVEN 2026-09-18 07:27 UTC: the pre-deploy step executed for the first time on deployment 08cd56a3 and applied the initial migration before the new version took traffic. Pinning mattered - the command is `npx prisma@7.10.0 migrate deploy`, and unpinned npx would have pulled 8.0.0-rc.15 against a client on 7.10.0. 2026-09-21 PROVEN, and it had been BROKEN by the repo split. The preDeployCommand read 'npx prisma@7.10.0 migrate deploy' and sat on the WEB service - written when Prisma lived at the repo root. After the split Prisma moved to backend/, so that command would have run in a workspace with no schema and applied nothing while reporting success. Corrected to 'npm run prisma:deploy -w @sponsorx/backend' AND MOVED OFF web ONTO the backend service, because Guide §10 is explicit that one service owns schema migration and two must not race. First real run output 'All migrations have been successfully applied' - see P2-BE-02.
A54: 46 | B54: P2-BE-01 | C54: 2 | D54: Platform Foundations | E54: BE | F54: Code | G54: Install and pin the dependency set | H54: Install every library at its pinned version and set up the Prisma config. | I54: Done | J54: 1 | K54: 2026-09-15 | L54: 2026-09-22 | M54: rcfworks | N54: 3 | O54: P0-PMO-11 | P54: Every package from Guide §01 installed at an exact version; prisma.config.ts present with the explicit client output path | Q54: Guide §01 | R54: Installed 2026-09-15 at the P0-PMO-11 pins: 17 deps + 11 devDeps, zero carets. twilio deliberately NOT installed (SMS undecided, G-06 open). @types/node corrected 20.19.43 -> 24.13.4 to match the Node 24.21.0 runtime. prisma.config.ts + skeleton prisma/schema.prisma; client generates to src/generated/prisma (gitignored). Two Prisma 7 breaking changes recorded in Guide S01. npm 11 blocks install scripts - prisma and @prisma/engines approved or the query engine never downloads. Open: npm audit reports 4 high in mysql2 via @prisma/config; unreachable (we use Postgres) and the only fix is a downgrade to prisma 6 - NOT taken. APPROVED 2026-09-16: technical approval given, moved Code review -> Done. 2026-09-18: set back to In progress under rcfworks at the user's instruction, so the whole Railway / Clerk / backend-setup cluster reads as one owned workstream. THE WORK ITSELF IS FINISHED and was completed on 2026-09-16 - the Date Done column still holds it. Status here signals ownership of the workstream, not that the work is outstanding. Audited 2026-09-22 — NOT met: four dependencies still carry caret ranges (express, ioredis, tsx, @types/express) where the acceptance asks for exact versions. prisma.config.ts is present. CLOSED 2026-09-22: the four caret ranges (express, ioredis, tsx, @types/express) are pinned exactly. prisma.config.ts carries the explicit client output path.
A55: 47 | B55: P2-OPS-09 | C55: 2 | D55: Platform Foundations | E55: OPS | F55: Vendor console | G55: Establish staging + production environments | H55: Stand up staging and production, each with its own database. Turn on backups and confirm you can actually restore to a point in time. | I55: Done | J55: 3 | K55: 2026-09-18 | L55: 2026-09-18 | M55: rcfworks | N55: 2 | O55: P2-OPS-03 | P55: Both exist with their own Postgres; scheduled backups on for production; point-in-time restore confirmed available on the plan | Q55: Guide §10 | R55: Started 2026-09-18, STAGING HALF DONE, production half deliberately deferred - see documentation/SponsorX-Database-Backup-Runbook.md. Staging has its own Postgres with point-in-time recovery ENABLED and bucket wired, daily + weekly scheduled backups on, and a RESTORE ACTUALLY TESTED: manual backup e005db9e created and restored in place, service back to SUCCESS in about a minute with PITR still on. Backup bucket 'sponsorx-pg-backups' 34211549 in region 'iad' - Railway bucket regions use their own names (sjc/iad/ams/sin), not service region ids, and iad is the US East one G-02 requires; a backup bucket in the wrong region puts a full copy of the database outside the agreed jurisdiction. TWO THINGS LEARNED: `pitr backup restore` has no --new-service-name and restores IN PLACE, destructively, while `pitr restore --at` builds a NEW service and leaves the live one alone - the second is the incident tool. And a restore to a time before PITR was enabled fails outright ('Failed to start the point-in-time restore'), so the recovery window starts at enable time. NOT CLOSED because production has no database yet: it gets one at promotion, from the runbook. Also not proven: any restore containing real data - the staging database is empty until P2-BE-02. CLOSED 2026-09-18: production now has its own database too, at the user's direction. 'Postgres-production' (75db2da3), volume 46c1b4b9 in us-east4-eqdc4a, PITR enabled and bucket wired, backups daily+weekly+monthly. production web's DATABASE_URL resolves to postgres-apsb.railway.internal. Creating it NOW rather than at promotion is the better call for one specific reason: the PITR recovery window starts when PITR is enabled, so a database protected from the moment it exists has no unprotected first hours. NAMING: service names are unique per project, so production's cannot also be called 'Postgres' - hence 'Postgres-production', and its DATABASE_URL reference is ${{Postgres-production.DATABASE_URL}} rather than ${{Postgres.DATABASE_URL}}. The two environments therefore use different reference strings; do not copy one to the other. 2026-09-18: set back to In progress under rcfworks at the user's instruction, so the whole Railway / Clerk / backend-setup cluster reads as one owned workstream. THE WORK ITSELF IS FINISHED and was completed on 2026-09-18 - the Date Done column still holds it. Status here signals ownership of the workstream, not that the work is outstanding. 2026-09-21 DECISION, and it is a cost decision rather than an architectural one: the Express API and the pg-boss worker will run in ONE Railway service for now, not two. Addendum B separated them deliberately - different scaling, a slow job should not slow a request, a crash in one should not take the other down - and that reasoning still holds. What changed is that Railway bills per service and Phase 1 is a 25-athlete pilot. The user chose the cheaper option explicitly. IT IS BUILT TO BE REVERSED. src/index.ts still runs the API alone and worker/index.mts still runs the worker alone; both are untouched. src/combined.mts starts both, and splitting later means pointing two services at the two existing files and deleting one. That is why the worker was refactored to EXPORT startWorker/stopWorker and to self-start only when it is the entrypoint - without that guard, importing it would start it twice and two drains would compete for the same rows. WHAT IS GIVEN UP, recorded so nobody is surprised: one crash takes both down; they restart together, so an API deploy interrupts the drain; they share an event loop. Phase 1's jobs are IO-bound so the last costs little - THE FIRST CPU-BOUND JOB (PDF rendering, image derivatives) IS THE SIGNAL TO SPLIT. Ordering verified locally: the API binds and logs 'listening' BEFORE the worker starts, so a slow pg-boss migration cannot fail Railway's health check; and when Postgres is absent the worker's failure exits the process, taking the API with it - which is intended, because a deploy whose queue cannot drain is not a successful deploy. STILL TO DO: create nothing, but repoint the existing services at the workspaces - web at frontend/, worker at 'npm run start -w @sponsorx/backend' - and set the R2 and Clerk variables on the combined service. The CLI can create and link services and set variables; per-service root directory and build/start commands are the part it does not expose. 2026-09-21 STAGING IS RUNNING BOTH HALVES OF THE SPLIT REPO. Service config was set through Railway's GraphQL API, since the CLI exposes neither build nor start commands: the backend service builds and starts @sponsorx/backend with healthcheck /health, web builds and starts @sponsorx/frontend. The 'worker' service was RENAMED to 'api' because it runs both processes - but NOTE THE PRIVATE HOSTNAME DID NOT FOLLOW, it is still worker.railway.internal. Railway fixes the internal domain at creation; a previous session recorded the same behaviour renaming the Postgres service. API_URL therefore stays worker.railway.internal:4000 and the name/hostname mismatch is permanent for this service. Verified live: /, /packages, /join, /brief and /r/[token] serve 200; /admin, /sponsor, /athlete and /portal 307 to /login; /login serves Clerk. The API has NO public domain, by design - only web reaches it, over the private network.
A56: 48 | B56: P2-OPS-05 | C56: 2 | D56: Platform Foundations | E56: OPS | F56: Code | G56: Write the environment seed job | H56: A script that fills an empty database with realistic demo data. Because preview environments start empty on Railway, this is infrastructure — if it rots, every preview becomes useless. | I56: Done | J56: 3 | K56: 2026-09-18 | L56: 2026-09-22 | M56: rcfworks | N56: 2 | O56: P2-BE-02 | P56: worker/jobs/seed-environment.ts builds a usable demo tenant from scratch; a fresh PR environment is immediately usable | Q56: Guide §10 | R56: 2026-09-18: moved Blocked -> In progress and assigned to rcfworks at the user's instruction, to show the backend/Railway/Clerk cluster as actively owned. THE BLOCKING IS STILL REAL - this row depends on P2-BE-02. Read Depends On, not Status, to find what can actually be started. 2026-09-21 PARTIAL: the identity slice is built and running. worker/jobs/seed-environment.mts seeds a demo tenant and five users (the four portal roles reusing the old mock-auth addresses, plus the real operator account) at WORKER BOOT rather than as a command someone remembers, because Railway previews start empty. It refuses outright in production, is idempotent via deterministic ids and ON CONFLICT DO NOTHING, and writes PLACEHOLDER clerkIds only - a seeded user is an invitation to claim, which the mirror converts on first sign-in; a fabricated Clerk id would permanently shadow the real identity because clerkId is unique. Confirmed on staging: '[worker] seed complete - 1 tenant(s) and 5 user(s) created'. A seed failure is logged and swallowed so a worker that cannot seed still drains the outbox. BUILD GOTCHA FIXED HERE: the Next build type-checks the worker, and TypeScript rejected the ./jobs/seed-environment.mts specifier with TS5097 while Node's ESM loader REQUIRES that extension at runtime - the worker is not bundled. allowImportingTsExtensions reconciles them and is safe because noEmit is true. The first worker file to import another hit this; any future one would have too. STILL OUTSTANDING: the wider demo data across the §39 loop - athletes, sponsors, campaigns, deliverables - so the row stays In progress. Audited 2026-09-22 — NOT met: the seed builds a tenant, five users and the commercial catalogue, but no athletes, campaigns or orders, so a fresh environment is not 'immediately usable' as a demo. The roadmap lists the rest of the seed's demo data as still owed. CLOSED 2026-09-22: the seed now builds a usable demo tenant — a verified guardian, three athletes and a sponsor, plus the catalogue. The three athletes are an ACTIVE adult, an ACTIVE minor with a verified guardian and a SUBMITTED minor without one, because those take three different paths through §37 and a reviewer needs all three.
A57: 49 | B57: P2-OPS-11 | C57: 2 | D57: Platform Foundations | E57: OPS | F57: Vendor console | G57: Configure monitoring and alerting | H57: Make service health, queue depth and failed jobs visible, and make sure somebody gets woken up if the worker stops processing. | I57: Done | J57: 3 | K57: 2026-09-18 | L57: 46303 | M57: rcfworks | N57: 1 | O57: P2-OPS-09 | P57: Service health, queue depth, failed jobs and error rate all visible; someone is paged when the worker stops draining | Q57: §38 | R57: Started 2026-09-18 - see documentation/SponsorX-Monitoring-Plan.md. TWO OF FOUR SIGNALS ARE LIVE: service health (CPU, memory, network, service up/down) and volume usage vs limit, confirmed with `railway metrics --all`. Deployment success/failure is visible too. That is visibility, NOT alerting - nobody is told. THREE BLOCKERS, none of them task dependencies, which is why the board showed this Ready: (1) QUEUE DEPTH and FAILED JOBS cannot be measured because there is no queue - worker/index.js is a placeholder and pg-boss is not attached; these arrive with the task that makes the worker real, and they are the signals that matter most because a worker that is UP but not DRAINING looks perfectly healthy on CPU and memory. (2) HTTP ERROR RATE needs web to have a public domain; it has none in either environment, so there is no request volume to measure. (3) PAGING needs a destination vendor chosen (Slack/email/on-call tool) and a Railway project webhook configured IN THE CONSOLE - webhooks are not in the public GraphQL API, so it cannot be scripted. The alerting design is written and ordered: only 'worker not draining' should page; deployment failed, volume above 80% and job failure rate notify. Thresholds deliberately left unset until there is a baseline - a guessed threshold produces noise and teaches people to ignore the pager. | 2026-10-07 (rcfworks, via Claude): ALL FOUR VISIBLE, AND THE PAGE IS LIVE PATH. /health/full (public as /api/v1/public/health) gains checks.queue (depth = due pg-boss jobs + dispatchable outbox rows; oldest wait; jobs failed in 24 h) and traffic (API responses and 5xx over 15 min, per process). The queue check FAILS when a due job or a dispatchable outbox row has waited over 15 min, so the existing 15-minute health monitor posts 'worker not draining' to Slack. Parked rows are left out: types with no handler, and Zoho CRM jobs when CRM credentials are absent (production). NEEDS_ZOHO_CRM moved to src/lib/zoho-jobs.ts so the API never imports the Zoho client (zoho-boundary test). Verified on real SQL against a scratch Postgres with pg-boss 12; staging preview read-only: 0 waiting, 196 failed jobs in 24 h, all notify.email to example.com test addresses refused by Resend (test data). Production preview not run (needs the user). Monitoring Plan rewritten as v1.0. Done once deployed and the live answer shows the queue in both environments. | 2026-10-08 CHECKED, NOT YET DONE. Code meets the clause: a due job or outbox row waiting over 15 min makes /health/full 'degraded' (system-health.ts), and the monitor alerts on anything but 'ok'. Staging (1c423b9) shows checks.queue and traffic live; production is still on aae0ca2 and shows neither — needs the production release. ALSO FOUND: health-monitor.yml is scheduled every 15 min but GitHub ran it only every 4–6 h on 2026-10-07 (13:56, 19:42, 23:50 UTC), so a stuck worker could go unreported for hours. Done when production shows the queue and the monitor actually runs on a reliable cadence. | 2026-10-08 DONE — both clauses verified. (1) Visible: production deployed at 6669472 (api + web) and sponsorx.net/api/v1/public/health now shows checks.queue (depth, oldest wait, failed jobs 24 h) and traffic (requests, 5xx, rate), as staging does. (2) Paged when the worker stops draining: a due job waiting >15 min makes the answer 'degraded' and the health monitor posts to Slack. GitHub's own */15 schedule ran only every 4–6 h, so a Railway cron service 'monitor-trigger' (staging env, image curlimages/curl, */15 * * * *, restart NEVER) now dispatches health-monitor.yml on main with a fine-grained token GH_DISPATCH_TOKEN (BTG-Sports/sponsorX_dev only, Actions read/write, 1 year — renew before 2027-10). First cron-started run 07:02 UTC succeeded. GitHub's schedule stays as a backup.
A58: 50 | B58: P2-SEC-01 | C58: 2 | D58: Platform Foundations | E58: SEC | F58: Code | G58: Author the authorisation matrix test suite | H58: Turn the RBAC matrix into an automated test that runs on every commit. When someone widens a permission to fix a bug, this tells them what else they just widened. | I58: Done | J58: 3 | K58: 2026-09-18 | L58: 2026-09-22 | M58: rcfworks | N58: 2 | O58: P2-BE-04, P0-PMO-07 | P58: tests/authz.matrix.test.ts seeds two tenants, two sponsors, two athletes, a guardian and a property, and asserts every role against every resource | Q58: §30, Guide §09 | R58: 2026-09-18: moved Blocked -> In progress and assigned to rcfworks at the user's instruction, to show the backend/Railway/Clerk cluster as actively owned. THE BLOCKING IS STILL REAL - this row depends on P2-BE-04, P0-PMO-07. Read Depends On, not Status, to find what can actually be started. 2026-09-21 POLICY HALF DELIVERED, row stays In progress. frontend/tests/authz.matrix.test.ts - 19 tests, all passing, whole frontend suite 65/65. It asserts EVERY role against EVERY resource (32 x 12 x 3 = 1,152 pairs), which is the §30 coverage requirement, and it needs no database because P2-BE-04 deliberately made the matrix pure data. Named invariants: the grid is total; an unknown resource denies structurally; every declared resource has a POLICY entry; only SUPER_ADMIN ever holds a cross-tenant scope; the only cross-tenant 'catalog' resources are nilJob and sponsorPackage; athlete pay is unreachable by sponsor roles and sponsor spend by athlete/guardian/property; an athlete cannot read a sponsor report about themselves; NOBODY writes the audit log, not even SUPER_ADMIN; SERVICE may sync but cannot write athletes, read money, or approve ANYTHING anywhere; the D1/D3 cells report as deferred yet refuse, and never widen a multi-role actor; combining roles never grants less than the strongest single role. THE CHANGE DETECTOR: a sha256 digest of the entire grid is pinned (438e87a9a4d2fa80). Any policy change anyone makes fails the build with the moved pairs in the message - which is literally what this task exists for ('when someone widens a permission to fix a bug, this tells them what else they just widened'). Accepting a change means reading the failing pairs against the RBAC matrix document and then updating the constant. WHY NOT DONE: the acceptance also requires a SEEDED suite - two tenants, two sponsors, two athletes, a guardian and a property - proving the scope FILTERS return the right rows. That needs a live Postgres, which no developer machine has (by design) and which CI does not have either: there is NO .github workflow in the repo at all yet, so 'green in CI' is not merely unproven, it is unrunnable until P2-OPS-07 creates the workflow WITH a Postgres service container. The seeded half was deliberately not faked - asserting where-fragments against a mock would test the mock. NOTE ON LOCATION: the suite sits in the frontend workspace because authz-policy.ts does. If the open question about moving authorisation to backend/ is answered yes, this test moves with it - cheap, because it imports nothing but the policy data. 2026-09-21: the policy half now RUNS IN CI - workflow green on its first run, so the 1,152 pairs are checked on every push. The seeded half is still outstanding and the Postgres service it needs is already provisioned in the workflow. Audited 2026-09-22 — NOT met: authz.matrix.test.ts contains ZERO references to Prisma. It asserts the policy exhaustively without a database, where the acceptance asks it to seed two tenants, two sponsors, two athletes, a guardian and a property. The policy half is done; the seeded half is not. CLOSED 2026-09-22: the seeded half lives in tests/authz.matrix.test.ts as the acceptance names, with the fixture in tests/support/seeded-db.ts — two tenants, two sponsors (both in ONE tenant, because own-sponsor is a boundary tenant scoping does not draw), two athletes, a verified guardian and a property. 13 assertions covering the tenant boundary, own/ward reaching one row, own-sponsor inside a tenant, nested rows inheriting the athlete's reach, and a sweep that fails if any non-SUPER_ADMIN role gets an unrestricted filter for any scoped resource. RUN FOR REAL against a live Postgres before closing — all 13 pass; the suite skips with a reason when no database is reachable, and CI now runs prisma migrate deploy before the tests so it cannot skip silently and report green.
A59: 51 | B59: P2-BE-06 | C59: 2 | D59: Platform Foundations | E59: BE | F59: Code | G59: Build the audit helper | H59: A single helper that records who changed what and when, for pricing, agreements, campaigns, payouts and permissions. | I59: Done | J59: 1 | K59: 2026-09-18 | L59: 2026-09-18 | M59: rcfworks | N59: 1 | O59: P2-BE-02 | P59: audit(tx, actor, action, entity, id) writes inside the caller's transaction; pricing, agreement, campaign, payout and permission changes are all covered | Q59: §26 | R59: 2026-09-18: moved Blocked -> In progress and assigned to rcfworks at the user's instruction, to show the backend/Railway/Clerk cluster as actively owned. THE BLOCKING IS STILL REAL - this row depends on P2-BE-02. Read Depends On, not Status, to find what can actually be started. DELIVERED 2026-09-18, closed straight to Done (code review skipped, per the flow agreed on P2-BE-05). src/server/audit.ts: audit(tx, actor, action, entity, entityId, {before, after}) writes into AuditLog INSIDE the caller's transaction, same discipline as enqueue() - an audit written outside the transaction can describe a change that rolled back, which is worse than no audit because it is a confident record of something that never happened. tenantId comes from the actor, never from an argument: a row filed under the wrong tenant is invisible to the tenant it belongs to and visible to one it does not. AuditActor is a deliberately NARROW type ({userId, tenantId}) so this task did not have to wait for Clerk - P2-BE-04's full Actor satisfies it structurally and can widen it without a rewrite. AUDIT_ACTIONS names the actions for all five §26 areas (pricing, agreement, campaign, payout, permission) so the common ones are not spelled three different ways; AuditAction is a template type rather than a closed union so future domain functions add actions without editing this file. changedFields(before, after, fields) reduces a pair to only what changed - passing whole records into a Json column is how a bank detail or tax ID ends up in a table nobody thought of as sensitive (§26, Addendum A6). Verified: changed-only, subset, and no-op cases all behave. ON COVERAGE: the helper is in place and the call sites are named, but the five areas cannot be DEMONSTRATED covered yet because the domain functions that change pricing, agreements, campaigns, payouts and permissions do not exist - each calls audit() as it is built, and P7-SEC-01 is the task that proves the coverage. Build and lint clean.
A60: 52 | B60: P2-BE-07 | C60: 2 | D60: Platform Foundations | E60: BE | F60: Code | G60: Build the contracts registry and OpenAPI generation | H60: Define API shapes once in code and generate the API specification from them, rather than hand-writing a spec that drifts from reality. | I60: Done | J60: 3 | K60: 2026-09-15 | L60: 2026-09-21 | M60: rcfworks | N60: 1 | O60: P2-BE-01 | P60: src/contracts/registry.ts emits openapi.json at /api/v1/openapi.json; the spec is generated from Zod, never hand-written | Q60: §38, Addendum A2, Guide §02 | R60: Built 2026-09-15: src/contracts/registry.ts + common.ts + zod.ts, emitting at GET /api/v1/openapi.json. Verified live: HTTP 200, OpenAPI 3.1.0, 4 schemas + bearerAuth, constraints/defaults/enums carried from Zod. Registered shapes are cross-cutting only (ProblemDetails, PageQuery, PageMeta, Provenance) - domain contracts belong to B1+ against the real P2-BE-02 models. NOTE: import z from src/contracts/zod.ts, never from 'zod' - the .openapi() prototype patch did not survive the Next server build when applied inline. APPROVED 2026-09-16: technical approval given, moved Code review -> Done. 2026-09-18: set back to In progress under rcfworks at the user's instruction, so the whole Railway / Clerk / backend-setup cluster reads as one owned workstream. THE WORK ITSELF IS FINISHED and was completed on 2026-09-16 - the Date Done column still holds it. Status here signals ownership of the workstream, not that the work is outstanding. 2026-09-21 DONE. GET /api/v1/openapi.json is served BY THE API, generated from the Zod registry on every request. Verified live against a booted server: 200, application/json, openapi 3.1.0, servers [/api/v1], components ProblemDetails / PageQuery / PageMeta / Provenance, securitySchemes bearerAuth. THE THIRD INSTANCE OF THE SAME PATTERN TODAY. The registry, the generator dependency and the route all existed already - in frontend/. After Addendum B moved the API to Express, the published description of the API was being produced and served by a process that is no longer the API. The row's acceptance was technically satisfied by a route describing the wrong service, which is worse than no spec because it looks authoritative to §8's service account and INFINEX. Same shape as allowImportingTsExtensions landing in the wrong workspace and the Prisma select rule guarding a workspace with no Prisma. WHEN CODE MOVES BETWEEN WORKSPACES, ASK WHAT WAS DESCRIBING IT OR WATCHING IT - those things do not fail loudly, they just stop being true. WHAT MOVED: src/contracts/{zod,common,registry}.ts to backend/src/contracts (history preserved); the Next route deleted, so the frontend now ships NO /api routes at all; @asteasolutions/zod-to-openapi 9.1.0 declared in backend and removed from frontend, because the frontend no longer generates anything. Express route at backend/src/routes/v1/openapi.ts, Cache-Control no-store - a cached spec is the drift this task exists to prevent. ALSO VERIFIED while the server was up: /health 200, /api/v1 200, /api/v1/me 401 with no credential AND 401 with a bogus bearer token. Note the 500 seen first time was a fake probe key of mine, not a defect - Clerk rejects a publishable key that is not in pk_test/pk_live format before it ever looks at the request. FOUND, NOT FIXED, BELONGS TO SOMEONE: the published spec declares ProblemDetails (RFC 9457) as the error envelope for every endpoint, but app.ts returns {error:{code,message}} and labels a 401 as 'bad_request'. The spec and the API therefore disagree TODAY, which is precisely the drift this row exists to stop - but the error handler is P0-OPS-07's scaffold rather than this task's, so it is raised here rather than changed unilaterally.
A61: 53 | B61: P2-QA-01 | C61: 2 | D61: Platform Foundations | E61: QA | F61: Code | G61: Stand up the test harness | H61: Set up the testing tools so tests can run locally and automatically on every commit. | I61: Done | J61: 3 | K61: 2026-09-18 | L61: 2026-09-22 | M61: rcfworks | N61: 1 | O61: P2-BE-02 | P61: Vitest for unit + matrix, Playwright for E2E; both runnable locally and in CI against a seeded database | Q61: Guide §01 | R61: 2026-09-18: moved Blocked -> In progress and assigned to rcfworks at the user's instruction, to show the backend/Railway/Clerk cluster as actively owned. THE BLOCKING IS STILL REAL - this row depends on P2-BE-02. Read Depends On, not Status, to find what can actually be started. Audited 2026-09-22 — NOT met: Vitest is in place for unit and matrix, but there is no Playwright config anywhere, so the E2E half does not run locally or in CI. CLOSED 2026-09-22: @playwright/test 1.56.1 pinned, playwright.config.ts with chromium and a Pixel-7 mobile project, four specs in e2e/, and an `e2e` job in CI with the browser cached by lockfile hash. `npm run e2e` starts the app itself so it works from a clean checkout. It runs `next dev`, not `next start` — Next says plainly that next start does not serve output: 'standalone', and serving the standalone bundle is a packaging concern the deploy exercises. Seeded-database runs are wired rather than hypothetical: set E2E_BASE_URL at a seeded environment and the same specs run against real data; CI already has the Postgres service. P3-QA-01's loop tests attach to this harness rather than standing up a second one.
A62: 54 | B62: P2-BE-09 | C62: 2 | D62: Platform Foundations | E62: BE | F62: Code | G62: Establish the repo layout | H62: Create the folder structure: one repository, two deployable things (app and worker), sharing the same business logic so they can never disagree. | I62: Done | J62: 1 | K62: 2026-09-15 | L62: 2026-09-24 | M62: rcfworks | O62: P2-BE-01 | P62: The Addendum B workspace layout exists — backend/src/contracts/, backend/src/domain/, backend/worker/jobs/, backend/prisma/sql/, backend/tests/, and frontend/src/server/; one repo, two deployables (web, api), one lockfile | Q62: Guide §02 | R62: AC amended to the Addendum B layout (backend/ + frontend/ workspaces). Stale pre-split .gitkeep placeholders removed; layout pinned by backend/tests/layout.test.ts. | 2026-09-24: Done at the user's instruction — acceptance confirmed met.
A63: 55 | B63: P2-FE-01 | C63: 2 | D63: Platform Foundations | E63: FE | F63: Code | G63: Swap fixture reads for real queries behind a flag | H63: Point the finished screens at the real database instead of mock data, keeping mocks available for demos. | I63: Done | J63: 3 | K63: 2026-09-18 | L63: 2026-09-29 | M63: HeckerCreatives | O63: P2-BE-04 | P63: An authenticated user loads an empty portal from Postgres; fixtures remain available for demo mode | Q63: Roadmap B0 | R63: 2026-09-18: moved Blocked -> In progress and assigned to rcfworks at the user's instruction, to show the backend/Railway/Clerk cluster as actively owned. THE BLOCKING IS STILL REAL - this row depends on P2-BE-04. Read Depends On, not Status, to find what can actually be started. 2026-09-18: documentation/Mock-Data/SponsorX-Mock-Data-Register.md written as the inventory this task works from - all 81 fixtures.ts exports mapped to the Prisma model that replaces them, the roadmap block that makes that data exist, and the routes that read each one (27 app routes, 10 components). THREE FINDINGS. (1) Six exports are read by NOTHING - sponsorStats, performanceSeries, topCampaign, rewardFunnel, campaignSeries, roiSeries - left over from screens the 2026-09-11 sponsor redesign replaced; delete rather than port them. (2) roiRecommendation has NO retrieval path at all; it is advisory copy and must carry EST curated or come off the screen. metricTrust has the same trap in reverse - it renders the provenance chips, so it must be driven by each metric's real MetricSource rather than a hardcoded optimistic list. (3) Six components hold their own inline lists outside fixtures.ts, which a search for 'lib/fixtures' will not find: brief-request-drawer, marketplace-catalog, athlete-profile-view, applications-desk, profile-editor, sponsor-campaigns-list. 2026-09-29 (HeckerCreatives, taken over from rcfworks at the user's instruction): the remaining fixture-only screens wired live, fixtures kept for ?demo=. Sponsor Campaigns list + campaign detail (GET /campaigns + /campaigns/:id/ops; another sponsor's id is 'not found'); admin Operations Board (money/pacing from /campaigns, the four queues from the desks' own lists, integration health, audit log; a 403 section says 'not in your role'); athlete home (own invitations/deliverables/earnings/profile + guardian readiness gate); property portal (/properties/mine + /team/roster); public /properties/[slug] on NEW GET /public/properties/:slug (adults named, minors counted never named - confirm policy); public /brief now actually submits (POST /public/inquiries -> Inquiry + queued Zoho Lead); athlete profile editor seeded from /athletes/me, socials save via PUT, other sections say 'ask BTG' (user decision; raised P3-BE-15). Portal chrome was already real (QA pass 5). Left demo-only by design: /sponsor/marketplace/[jobId] (only reachable from the demo media tab). Verified: backend 1700/1700, frontend 386/386, lint + build green, 8 signed-in browser walks green, 0 console errors, 0px overflow at 390. 2026-09-29 QA passes 7+8 (Memory/2026-09-29/qa-pass7.md, qa-pass8.md): 15 findings; fixed F-1..F-6, F-9..F-13, F-15 the same day - NUL-byte 500s on public slugs, brief draft loss on failed send, unlinked athlete/property states, GET /campaigns paged (+ new GET /campaigns/:id) so counts and money no longer stop at 100, saveSocials returns errors instead of throwing, long-name wrap, outage vs not-found on the public property page, radio-group arrow keys, Dockerfile HOSTNAME. Open for the team: F-7 public notFound returns 200 under (public)/loading.tsx; F-8 SPONSOR_ANALYST spend visibility policy. Re-verified: backend 1711/1711, frontend 391/391, build green, re-test walks green. QA pass 9 (Memory/2026-09-29/qa-pass9.md): static review + official e2e (15/7/0) + scale/axe probes; fixed F-16 (HIGH: public school page named FEATURED minors with no recorded age - now confirmed adults only), F-17 (raw NUL bytes made 3 sources binary), F-18 (athlete socials save erased BTG-verified rows), F-19 (row-id cursor -> keyset: no silent truncation, no cross-tenant id oracle), F-20 (brief timeout copy), F-21..F-23. Backend 1720/1720, frontend 391/391, build green. Check pass (Memory/2026-09-29/check-pass.md): 14 roles x every page + access matrix + axe; fixed C-1 (role-aware admin desks + nav via lib/admin-access.ts, Not in your role instead of sample desks), C-2 (guardian demo notices), C-3 (campaign detail role state), C-4 (brief picker contrast), C-5 (SX-03 notice). Pagination design + live API paging contract verified on every list.
A64: 56 | B64: P2-INT-02 | C64: 2 | D64: Platform Foundations | E64: INT | F64: Vendor console | G64: Enable MFA for privileged roles | H64: Require two-factor authentication for admin and finance accounts in production. | I64: In progress | J64: 1 | K64: 2026-09-18 | M64: rcfworks | O64: P2-INT-01 | P64: Admin and finance roles require MFA in the production instance | Q64: §26 | R64: 2026-10-16: now also carries the MFA half of P0-OPS-03 (closed). | 2026-09-18: moved Blocked -> In progress and assigned to rcfworks at the user's instruction, to show the backend/Railway/Clerk cluster as actively owned. THE BLOCKING IS STILL REAL - this row depends on P2-INT-01. Read Depends On, not Status, to find what can actually be started. DECISION 2026-09-21 - DEFERRED TO LAUNCH BY CHOICE, NOT BLOCKED. Phase 1 proceeds on the Clerk HOBBY (free) plan. Hobby is not a sandbox: it includes a PRODUCTION instance with up to 10,000 monthly active users, and the production instance verified on sponsorx.net the same day is the one a minimal launch runs on. Launching on the DEVELOPMENT instance is explicitly rejected - dev instances cap at 100 users, serve .accounts.dev URLs, and Clerk treats their sessions as non-production. THIS ROW IS THE ONLY PHASE 1 TASK THAT NEEDS CLERK PRO: all three MFA strategies (SMS, Authenticator application, Backup codes) are Pro-badged on Hobby, and 'Require multi-factor authentication' needs at least one strategy enabled, so it is unreachable. Nothing else in the §39 loop touches a paid Clerk feature - sign-up, sign-in, sessions, the account portal and auth email sent from sponsorx.net are all included. Three further Pro traps are avoided by existing decisions: Satellites (multi-domain) is Pro and the single-host sponsorx.net decision removes the need; Organizations is where Clerk's B2B pricing sits and is off per Addendum A4; Google OAuth is off, which also avoids a Google Cloud consent screen. Visible cost of staying on Hobby: the 'Secured by Clerk' badge remains on the sign-in box. WHEN PRO IS BOUGHT (provisioning sequence step 16, before real admin and finance accounts touch invoices and earnings), the strategies to enable are AUTHENTICATOR APP (TOTP) + BACKUP CODES and NEVER SMS - G-06 puts SMS out of Phase 1 entirely, and the SMS strategy is in any case unavailable while phone numbers are disabled. Compensating control until then: admin accounts are limited to the two-person team. | 2026-10-09 AUDIT: NOT MET — confirmed: production Clerk has no MFA strategy enabled and does not require a second factor. Needs Clerk Pro (authenticator app + backup codes, never SMS). Deferred to launch by decision.
A65: 57 | B65: P2-OPS-02 | C65: 2 | D65: Platform Foundations | E65: OPS | F65: Code | G65: Configure web for standalone output | H65: Configure the app to build as a plain Node server, so it can move to another host without a rewrite. | I65: Done | J65: 1 | K65: 2026-09-18 | L65: 2026-09-18 | M65: rcfworks | O65: P2-OPS-01 | P65: next.config.ts sets output: 'standalone'; web runs next start; worker runs node worker/index.js with no public domain | Q65: Guide §10 | R65: 2026-09-18. next.config.ts ALREADY set output:'standalone' - done earlier, with a documented Vercel exception. Added this pass: worker/index.js, the entrypoint Guide §10 names, because Railway cannot run the worker as anything but a second copy of the web app without it; start commands set on staging - web 'next start', worker 'node worker/index.js'; worker confirmed to have no public domain. The entrypoint is a PLACEHOLDER that boots, reports whether DATABASE_URL is present, heartbeats every 5 min and exits cleanly on SIGTERM. The pg-boss task replaces it. Plain .js on purpose - the worker service has no build step yet and adding one belongs to that task. AT CODE REVIEW because nothing is proven until the next deploy: Railway deploys main, so these commands take effect when this branch merges. Do NOT redeploy worker before then - it would crash-loop on a missing file. CLOSED 2026-09-18 at the user's instruction - no problem was encountered; the configuration is in place and verified by reading it back from the Railway API. What remains is execution, not correctness: these commands first RUN on the next deploy of main, and that cannot be brought forward without deploying. 2026-09-18: set back to In progress under rcfworks at the user's instruction, so the whole Railway / Clerk / backend-setup cluster reads as one owned workstream. THE WORK ITSELF IS FINISHED and was completed on 2026-09-18 - the Date Done column still holds it. Status here signals ownership of the workstream, not that the work is outstanding. PROVEN 2026-09-18 07:27 UTC: web deployed with startCommand 'next start'; worker deployed with 'node worker/index.js' and its own log line - '[worker] entrypoint up ... placeholder, no queue attached yet' and 'DATABASE_URL is present'. The worker is finally running the worker, not a second copy of the web app. 2026-09-21 STILL NOT DONE, and now visible on every deploy: the staging web log prints 'next start does not work with output: standalone configuration. Use node .next/standalone/server.js instead' on each boot. It serves correctly today, so this is a latent misconfiguration rather than an outage - but the whole point of standalone output is host portability, and running `next start` against it means we are not actually getting it. Verified 2026-09-22: next.config.ts sets output 'standalone' (conditionally skipped only on Vercel, which packages functions from Next's file-trace manifests that standalone relocates). The worker exposes no ports in docker-compose, so it has no public domain.
A66: 58 | B66: P2-OPS-04 | C66: 2 | D66: Platform Foundations | E66: OPS | F66: Vendor console | G66: Configure the environment variable set | H66: Set the environment variables, carefully: Zoho credentials belong only on the worker, never on the public web app. | I66: In progress | J66: 1 | K66: 2026-09-18 | M66: rcfworks | O66: P2-OPS-01, P0-OPS-02, P0-OPS-03 | P66: Every variable in Guide §10 present and scoped correctly — critically, ZOHO_CLIENT_ID/SECRET/REFRESH_TOKEN on worker only, ZOHO_WEBHOOK_SECRET on web | Q66: Guide §10 | R66: 2026-09-18: moved Blocked -> In progress and assigned to rcfworks at the user's instruction, to show the backend/Railway/Clerk cluster as actively owned. THE BLOCKING IS STILL REAL - this row depends on P2-OPS-01, P0-OPS-02, P0-OPS-03. Read Depends On, not Status, to find what can actually be started. 2026-09-21 PARTIAL. RESEND_API_KEY and EMAIL_FROM are set on the STAGING WORKER and verified by hash against the local values (36 and 31 characters, exact match). Worker only, deliberately: it is the only process that sends, since the domain writes an outbox row and worker/jobs/send-email.mts is the one place the vendor is called. A sending credential on the web service would hand it to a process with no use for it. TWO GAPS FOUND WHILE DOING IT. (1) There is NO 'api' SERVICE IN RAILWAY at all - staging has web, worker and postgres, so the Express API from the repo split has nowhere to run, and the R2 credentials it needs for presigning have nothing to be set on. (2) The backend REQUIRED Clerk keys that existed only in frontend/.env.local, so it could not boot locally at all - CLERK_SECRET_KEY and CLERK_PUBLISHABLE_KEY are now in the repo-root .env that the backend reads. Both are consequences of the repo split not having reached the infrastructure. ALSO: EMAIL_FROM must be QUOTED in .env. Written bare as SponsorX <noreply@sponsorx.net> the angle brackets are shell redirection when anything sources the file, so the variable comes out empty and a send fails with a confusing JSON error. Node's --env-file parser copes; the shell does not. 2026-09-21 STAGING COMPLETE. The backend service carries PORT, NODE_ENV, both Clerk keys, all six S3_* values, R2_PUBLIC_BASE_URL, RESEND_API_KEY and EMAIL_FROM; web carries API_URL, CLERK_SECRET_KEY and the two public Clerk values. DATABASE_URL was DELETED from web - the frontend can no longer reach Postgres, so it was a credential sitting where it had no purpose. Note the CLI's 'variable delete' rejects --skip-deploys, which is what made two earlier attempts look like a syntax error. Production environment is NOT configured. | 2026-10-09 AUDIT: NOT MET IN PRODUCTION (staging complete). Production web still carries DATABASE_URL, which the frontend never reads and staging removed on 2026-09-21. SPONSORX_EDGE_KEY is on staging web+api but not production (deferred to go-live by P8-SEC-03, so every fan's public rate limit would share one bucket until it is set). Zoho and Stripe webhook secrets absent in production by the go-live deferral. Neither environment sets GEOLITE2_CITY_PATH (optional; clicks record without geo). Note: API and worker run as one process (src/combined.mts), so the 'worker only' Zoho variables correctly sit on the api service; web holds no Zoho variable. | 2026-10-09 FIXED IN PRODUCTION (user-approved): SPONSORX_EDGE_KEY set on production api + web (40 chars, matching by hash, never printed); DATABASE_URL deleted from production web. Applied by fast-forwarding `release` 499e0b5 → 9c3246f (main; app code identical to production's 6669472 — the daily move had been held since 10-06 by the unrelated /admin/audit e2e failure) and redeploying web. Health ok, pages 200. STILL OPEN: GEOLITE2_CITY_PATH unset in both environments (optional; clicks record without geo), and production's Zoho credentials and Stripe webhook secrets wait for go-live by decision. | 2026-10-15: WHEN production's Zoho keys are set at go-live, also run `railway ssh --environment production --service api -- npm run zoho:intel-fields -w @sponsorx/backend -- --create --confirm-production` (3S7-INT-01's two Account fields; owner OK'd 2026-10-15). Tried 2026-10-15: stopped with 'Zoho is not configured' — nothing changed. 2026-10-24: Zoho production on (key owned by rcfworks, org 4857533000000020005, watch renewed, intel fields created). Edge key and Resend done 2026-10-23. Still open: GEOLITE2_CITY_PATH, BTG_POSTAL_ADDRESS.
A67: 59 | B67: P2-OPS-06 | C67: 2 | D67: Platform Foundations | E67: OPS | F67: Code | G67: Add the bare-findMany() lint rule | H67: A lint rule that fails the build if a database query does not explicitly list the fields it wants. This is what stops accidental data leaks at scale. | I67: Done | J67: 1 | K67: 2026-09-15 | L67: 2026-09-21 | M67: rcfworks | O67: P2-BE-01 | P67: The build fails on any Prisma read without an explicit select | Q67: Guide §04 | R67: Added 2026-09-15 as a no-restricted-syntax rule in eslint.config.mjs covering findMany/findFirst/findUnique(+OrThrow) without an explicit select. Verified against a 5-case probe: fired on all 3 bad cases, passed both good ones. src/generated/** ignored. Syntactic check by design - accepts a nested select inside an include. 'Build fails' means the CI lint step (P2-OPS-07); Next no longer runs ESLint in next build. APPROVED 2026-09-16: technical approval given, moved Code review -> Done. 2026-09-18: set back to In progress under rcfworks at the user's instruction, so the whole Railway / Clerk / backend-setup cluster reads as one owned workstream. THE WORK ITSELF IS FINISHED and was completed on 2026-09-16 - the Date Done column still holds it. Status here signals ownership of the workstream, not that the work is outstanding. 2026-09-21 DONE. The build now fails on any Prisma read without an explicit select, in BOTH workspaces, and CI enforces it on every push (P2-OPS-07). WHAT WAS ALREADY THERE, AND WHY IT WAS NOT ENOUGH: the rule itself already existed in frontend/eslint.config.mjs, written for this task before the repo split. After Addendum B moved Prisma, the API, the worker and the whole authorisation layer into backend/, it was guarding the workspace that NO LONGER QUERIES THE DATABASE, while the workspace that does had NO LINTING AT ALL - no eslint config, no lint script, and the root lint script forwarded only to the frontend. The task looked finished and protected nothing. WHAT WAS DONE: the rule moved to eslint.prisma-select.mjs at the repo root and both configs import it, so one definition cannot drift from itself and the next repo move cannot silently drop it. backend/eslint.config.mjs created from scratch (js.configs.recommended + typescript-eslint, no Next presets - it is a plain Node service), ignoring src/generated/** because Prisma's machine-written client calls find*() without a select by definition and would otherwise bury the rule in false positives. backend gets a lint script; the ROOT lint script now runs backend then frontend, which is what makes CI enforce it across the whole repo rather than half of it. COVERAGE: findMany, findFirst, findFirstOrThrow, findUnique and findUniqueOrThrow. The task title names findMany only, but a findUnique without select leaks exactly the same columns - and the fields at stake are the ones §7.1 and §7.2 of the RBAC matrix protect, like athleteRate.amount and athlete.dateOfBirth. PROVEN, NOT ASSUMED: a probe file with three bare reads (findMany, findUnique, findFirst) produced exactly three errors and failed the lint; the two reads carrying a select produced none; removing the probe returned it to clean. The frontend rule was probed the same way after being repointed at the shared definition. Full CI sequence green locally: both builds, lint, 19 backend tests, 46 frontend tests. NOTE: 'the build fails' in the acceptance means the CI lint step fails - Next no longer runs ESLint during next build, so lint is a separate gate rather than part of compilation.
A68: 60 | B68: P2-OPS-07 | C68: 2 | D68: Platform Foundations | E68: OPS | F68: Code | G68: Set up CI: typecheck, lint, unit, authz matrix | H68: Wire up continuous integration so every commit is type-checked, linted, unit-tested and permission-tested. | I68: Done | J68: 3 | K68: 2026-09-18 | L68: 46302 | M68: rcfworks | O68: P2-QA-01 | P68: Every commit runs all four; the authz matrix is a required check, not an advisory one | Q68: §30, Guide §09 | R68: 2026-09-18: moved Blocked -> In progress and assigned to rcfworks at the user's instruction, to show the backend/Railway/Clerk cluster as actively owned. THE BLOCKING IS STILL REAL - this row depends on P2-QA-01. Read Depends On, not Status, to find what can actually be started. 2026-09-21 BLOCKING NOTE from P2-SEC-01: there is no .github directory in the repo at all, so nothing runs in CI today and B0's exit criterion ('authz matrix passes in CI') cannot be met by any amount of test-writing. When this workflow is created it needs a POSTGRES SERVICE CONTAINER, not just node - the seeded half of the authorisation matrix suite is the one B0 actually exits on, and it cannot run without a database. The policy half already passes and needs nothing but node. 2026-09-21 WORKFLOW LIVE AND GREEN ON ITS FIRST RUN, row stays In progress - the 'Done when' has two clauses and only the first is achievable on this account. CLAUSE ONE, MET: .github/workflows/ci.yml runs on every push and every pull request and all four checks pass - backend build (tsc over src and worker), frontend build (typecheck plus every route compiled), lint, backend tests 19 including the 1,152-pair authorisation matrix, frontend tests 46. Run 35574058026 succeeded end to end on the first attempt. Node pinned to 24.21.0 to match CLAUDE.md, because a CI Node that drifts from the developer Node produces failures nobody can reproduce. npm ci rather than npm install so a lockfile that disagrees with package.json fails here. A POSTGRES 17 SERVICE CONTAINER is included although nothing uses it yet: P2-SEC-01's seeded half cannot run without a database, and adding it now means whoever writes that suite finds it waiting instead of rediscovering why a plain Node runner is not enough. No repository secrets needed - verified by building with the env files moved aside, Clerk keys are not required to build or to run these tests. CLAUSE TWO, BLOCKED BY PLAN, NOT BY CODE: 'the authz matrix is a required check, not an advisory one' cannot be configured. The repo is PRIVATE on a PERSONAL FREE account, and GitHub answers both the branch-protection and the rulesets API with 'Upgrade to GitHub Pro or make this repository public to enable this feature.' Public is not an option for this repo, so the remaining path is GitHub Pro at about $4/month. Until then a red check is visible on the pull request but cannot block a merge. SAME FINDING MATTERS BEYOND THIS ROW: the standing rule that nothing reaches main except by pull request cannot be enforced by GitHub on this plan at all - it is discipline, not configuration. PUSHING THE FILE NEEDED THE USER: an OAuth token needs the 'workflow' scope to create anything under .github/workflows, and the CLI's token here carries only gist, read:org and repo. Two device-flow refreshes did not add it. Worth knowing before anyone tries to change this workflow from a script. Audited 2026-09-22 — PARTIAL: CI runs build (typecheck), lint and both test suites including the authz matrix on every push. 'Required check, not advisory' cannot be satisfied — branch protection needs GitHub Pro on this personal repo. Close it if the workflow passing is the intended bar. | 2026-10-02 (HeckerCreatives, via Claude): Clause one no longer holds by decision: since 2026-10-01 CI runs once a day on main, not on every commit (Actions minutes ran out). Clause two still needs GitHub Pro. Run the four checks locally before merging (handoff guide §5). | 2026-10-07 (rcfworks, via Claude): BOTH CLAUSES NOW ACHIEVABLE. The repo moved to the BTG-Sports org (Team plan, public), so Actions minutes are free and rulesets work. ci.yml runs again on every push and every pull request, plus the nightly; deploy-daily.yml now deploys only after the nightly or a hand-started CI run (never after a push run), and it reads only the latest run of each job, so an earlier failure since re-run green does not block a deploy. Required check: repository ruleset 'CI required' on main and main_development requires 'typecheck · lint · unit · authz matrix' (the job that runs the 1,152-pair authz matrix). Moves to Done once the ruleset is on and the first push run is green. | 2026-10-07 DONE, both clauses verified. (1) Every commit runs all four: push and pull_request runs on #171 (37633953352, 37633957535) and on main (37635630955) all passed typecheck · lint · unit · authz matrix. (2) Required, not advisory: ruleset CI required (id 24647902, active) on main and main_development requires that job from GitHub Actions; #171 showed it Expected/Required and could not merge without it, and the fast-forward of main_development was accepted only because the commit had passed. Release #172 merged. NOTE: e2e is not required; while it is red (P1-FE-31 audit empty state), the 8 pm automatic deploy does not ship, because deploy-daily requires both CI jobs green.
A69: 61 | B69: P2-OPS-08 | C69: 2 | D69: Platform Foundations | E69: OPS | F69: Vendor console | G69: Configure PR environments | H69: Give every pull request its own throwaway environment with a fresh seeded database — never a copy of production data. | I69: Dropped | J69: 1 | K69: 2026-09-18 | M69: rcfworks | O69: P2-OPS-05 | P69: Each pull request gets its own environment with a fresh Postgres, seeded by the job — never a copy of production | Q69: Guide §10 | R69: 2026-09-18: moved Blocked -> In progress and assigned to rcfworks at the user's instruction, to show the backend/Railway/Clerk cluster as actively owned. THE BLOCKING IS STILL REAL - this row depends on P2-OPS-05. Read Depends On, not Status, to find what can actually be started. | 2026-10-09 AUDIT: NOT MET — no PR environments exist: GitHub shows only staging and production deployment environments, and PRs get no Railway preview. The seed it needs (P2-OPS-05) is Done. | 2026-10-15 DROPPED by the user ("its not worth doing"): every PR already runs the full suite, browser tests included, on its own fresh database in CI; the team is two people who merge every PR; a running app and database per open PR costs Railway money for little gain.
A70: 62 | B70: P2-OPS-10 | C70: 2 | D70: Platform Foundations | E70: OPS | F70: Document | G70: Define the deploy ordering rule | H70: Write down and enforce the rule that the worker deploys before the web app, so a new job type always has a handler waiting. | I70: Done | J70: 1 | K70: 2026-09-18 | L70: 2026-09-18 | M70: rcfworks | O70: P2-OPS-01 | P70: Documented and enforced: worker deploys before web on any release adding a job type; pg-boss migrations run on worker boot only | Q70: Guide §10 | R70: 2026-09-18. Written to documentation/SponsorX-Deploy-Ordering.md: migrations as a pre-deploy step never in the build; worker deploys before web on any release adding a job type; pg-boss migrations on worker boot only. Each rule states the failure it prevents. HONEST ON ENFORCEMENT: rule 2 is manual - Railway does not order deployments across services, and no release pipeline exists to encode it. The document says so rather than claiming automation. Nothing has needed it yet because no job types exist. 2026-09-18: set back to In progress under rcfworks at the user's instruction, so the whole Railway / Clerk / backend-setup cluster reads as one owned workstream. THE WORK ITSELF IS FINISHED and was completed on 2026-09-18 - the Date Done column still holds it. Status here signals ownership of the workstream, not that the work is outstanding. 2026-09-18 addition - WATCH PATHS as the accidental-deploy gate. main is auto-deployed, so every board or documentation commit was rebuilding staging; most of 17 commits that day changed no code. Railway now redeploys only when changed files match a service's Watch Paths: web on /src /prisma /public /package.json /package-lock.json /next.config.ts /prisma.config.ts /tsconfig.json, worker on /worker /prisma /package.json /package-lock.json /prisma.config.ts. Chosen over turning auto-deploy off, which would also have removed the fast feedback that proved the migration. WATCH OUT: a new top-level code directory must be added to the patterns or changes to it will silently never deploy - a quiet failure that looks like a broken pipeline. WATCH PATHS REMOVED 2026-09-18, same day, at the user's instruction - watchPatterns is empty on both staging services and every commit to main redeploys again. The reasoning is kept in the document rather than deleted, because the exposure it addressed is unchanged. | 2026-10-02 (HeckerCreatives, via Claude): Documented and enforced (SponsorX-Deploy-Ordering.md v1.3): rule 2's failure — web enqueuing a job no worker handles — is now impossible by construction (web has no database or pg-boss; the API and worker ship as one process; an old worker never claims a new queue name). npm run deploy now ships api, waits until live, then web, and stops if api fails (it deployed both at once). pg-boss migrates only in startWorker(). Accepted and written down: the daily release deploy is unordered across services (needs a Railway token the CLI login can't mint).
A71: 63 | B71: P2-PMO-01 | C71: 2 | D71: Platform Foundations | E71: PMO | F71: Document | G71: Write the deployment runbook (§38 deliverable) | H71: Document how to deploy, how to roll back, and what to do when a migration fails. Then test it once, for real. | I71: Done | J71: 3 | K71: 2026-09-18 | L71: 2026-09-22 | M71: rcfworks | O71: P2-OPS-09 | P71: Deploy, rollback, migration-failure and restore procedures written down and tested once | Q71: §38 | R71: Audited 2026-09-22 — NOT met: Deploy-Ordering and Database-Backup-Runbook exist, but no runbook covers deploy, rollback, migration-failure and restore together, and none has been tested once. CLOSED 2026-09-22: documentation/SponsorX-Deployment-Runbook.md covers deploy, rollback, migration failure and restore. It states which procedures have actually been exercised and which have not, rather than implying all four have — rollback across a migration is 'do not', and restore has only been walked on a staging snapshot.
A72: 64 | B72: P2-SEC-02 | C72: 2 | D72: Platform Foundations | E72: SEC | F72: Code | G72: Add field-level denial cases to the matrix | H72: Add the specific tests proving a sponsor cannot read athlete pay and an athlete cannot read a campaign budget. | I72: Done | J72: 1 | K72: 2026-09-18 | L72: 2026-09-22 | M72: rcfworks | O72: P2-SEC-01 | P72: SPONSOR_ADMIN → athleteRate.amount → deny and ATHLETE → campaign.budget → deny both present and passing | Q72: Guide §04, §09 | R72: 2026-09-18: moved Blocked -> In progress and assigned to rcfworks at the user's instruction, to show the backend/Railway/Clerk cluster as actively owned. THE BLOCKING IS STILL REAL - this row depends on P2-SEC-01. Read Depends On, not Status, to find what can actually be started. Audited 2026-09-22 — NOT met: athleteRate.amount and campaign.budget appear only in comments. There is no field-level denial mechanism at all — row scoping is all that exists. CLOSED 2026-09-22: src/auth/fields.ts transcribes matrix §7.1 and §7.2 as a DENIAL table — an allow list silently permits whatever nobody thought of. Both named cases pass, and so does every other row of §7. A denial is not widened by a second role, unlike a scope. campaignOrder.sellPrice was added to the table when the column arrived: compensation and sellPrice together ARE the margin.
A73: 65 | B73: P3-BE-01 | C73: 3 | D73: Athlete Network | E73: BE | F73: Code | G73: Athlete application contract + model + migration | H73: The athlete sign-up form's data model and its approval lifecycle, from draft through review to active. | I73: Done | J73: 3 | K73: 2026-09-21 | L73: 2026-09-21 | M73: rcfworks | N73: 8 | O73: P2-BE-02 | P73: All ten §11 sections captured; AthleteState DRAFT→SUBMITTED→UNDER_REVIEW→APPROVED/CHANGES_REQUESTED/REJECTED→ACTIVE/SUSPENDED enforced in the domain layer | Q73: §11, §21 | R73: 2026-09-21 IMPLEMENTED, moved to Code review. Contract, schema fields, migration, domain state machine, scope builder and tests; backend suite now 36. SCOPE, AND WHY IT IS NOT ALL TEN §11 SECTIONS: this task owns 4 of the 10 - Identity, Sports, Social and Compliance status. The other six belong to siblings that DEPEND ON THIS ROW and would be duplicated if built here: content capabilities, brand interests and restrictions are P3-BE-05; rates are P3-BE-09; agreements are P3-BE-06. Payment setup is already narrowed by the Phase 1 payment policy to status only with no tax ID collected (Addendum A6), so there is nothing to store beyond a status. The split is documented at the top of backend/src/contracts/athlete.ts so the next reader does not think it was forgotten. Read §11 from the Blueprint in Drive to do this - it is not in the repo. SCHEMA: nine fields added that P2-BE-02 did not carry - email, phone, ageBand, position, level, achievements, reviewerNotes, reviewedAt, complianceExpiresAt. Migration 20260921120000_athlete_application_fields generated OFFLINE by diffing the git HEAD copy of the schema against the new one, because --from-migrations needs a shadow database and no developer machine here has Postgres. NOTE IN THE MIGRATION: email is TEXT NOT NULL with no default, which applies cleanly only while Athlete is empty (it is - the seed creates no athletes). If rows ever exist this FAILS THE DEPLOY rather than giving every athlete a blank contact address, which is the intended behaviour. THE STATE MACHINE IS A TABLE, NOT BRANCHES, in backend/src/domain/athlete-state.ts - a table can be read against §21 by someone who does not write TypeScript and tested exhaustively. All 64 ordered pairs are asserted against §21 transcribed INDEPENDENTLY in the test, so the test is not circular with the implementation. Two edges §21 implies but does not draw are included with reasons: CHANGES_REQUESTED -> SUBMITTED (otherwise asking for a fix is a dead end) and SUSPENDED -> ACTIVE (a suspension nobody can lift is a deletion). REJECTED is terminal on purpose - reapplying makes a new application so the refusal stays in the audit trail. THE §37 GATE IS ENFORCED IN THE DOMAIN: a minor cannot reach ACTIVE without a linked and verified guardian. In the domain rather than the UI so it binds the API and §8's service account too. DESIGN CHANGE FORCED BY A TEST: the pure state machine was originally inside athlete.ts, and its test could not run at all - importing the module pulled in the Prisma client, which parses CLERK_PUBLISHABLE_KEY at load. Split into athlete-state.ts (imports nothing) and athlete.ts (persistence), the same separation the authorisation layer uses. A rule that cannot be tested without infrastructure is a rule that stops being tested. MUTATION-CHECKED: widening the table by one edge (SUBMITTED -> ACTIVE) fails two tests with the offending pair named. The athlete scope builder was added to auth/scope.ts - the first real query, which is exactly when P2-BE-04 intended builders to be written. 'assigned' and 'ward' are deliberately still unimplemented and fall through to MATCHES_NOTHING: they need CampaignInvite and Guardian joins that arrive with B3 and B1's guardian path, so a sponsor currently sees no athletes at all, which is the safe direction to be wrong in. NOT DONE HERE: the /athletes/apply and approve routes (§19) and the UI wiring - those are P3-FE-01/P3-FE-02 and the route layer, still Blocked on this row landing.
A74: 66 | B74: P3-BE-05 | C74: 3 | D74: Athlete Network | E74: BE | F74: Code | G74: Content capabilities, brand interests and restrictions | H74: Store what content an athlete can make, which brands they like, and crucially what they are forbidden from promoting — the last one drives conflict checking later. | I74: Done | J74: 1 | K74: 2026-09-22 | L74: 2026-09-22 | M74: rcfworks | N74: 1 | O74: P3-BE-01 | P74: All three §11 sections stored; restrictions are queryable for the conflict check in Phase 4 | Q74: §11, §26 | R74: The three lists are TEXT[], not JSON — §26's conflict check asks 'which athletes exclude alcohol?' and an index can answer that against an array. restrictionNotes is a separate column for what does not reduce to a category, and the conflict check cannot read it. The category vocabulary is closed and shared with sponsor categories, or the two can never be compared. Migration 20260922140000, generated offline.
